Workbook

Sheet 新幕シーズン2
A1: カードID | B1: メガミ | C1: アナザーID | D1: 置換元カード | E1: 名前 | F1: ふりがな | G1: 名前（中国語） | H1: 名前（中国語G1） | I1: ふりがな（中国語） | J1: 名前（韓国語） | K1: 名前（英語） | L1: ふりがな（英語） | M1: 種別 | N1: 追加札 | O1: 追加元カード | P1: 交換先 | Q1: 毒 | R1: タイプ | S1: サブタイプ | T1: 適正距離 | U1: （開） | V1: ダメージ | W1: （開） | X1: 納 | Y1: 消費 | Z1: 封印 | AA1: 取り除く | AB1: テキスト | AC1: テキスト補足 | AD1: テキスト（中国語） | AE1: テキスト補足（中国語） | AF1: テキスト（中国語G1） | AG1: テキスト（韓国語） | AH1: テキスト（英語） | AI1: （開） | AJ1: （開）（中国語） | AK1: （開）（中国語G1） | AL1: （開）（韓国語） | AM1: （開）（英語）
A2: 01-yurina-o-n-1 | B2: yurina | E2: 斬 | F2: ざん | G2: 斩 | H2: 斩 | J2: 참 | K2: Slash | M2: 通常札 | R2: 攻撃 | T2: 3-4 | V2: 3/1 | AN2: =IF(A2="", "", IF(ROW()>=3, ", ", "")&"'"&A2&"': {megami: '"&B2&"'"&IF(C2<>"",", anotherID: '"&C2&"', replace: '"&D2&"'","")&", name: '"&SUBSTITUTE(E2,"'","\'")&"', nameEn: '"&SUBSTITUTE(K2,"'","\'")&"', nameZh: '"&SUBSTITUTE(G2,"'","\'")&"', nameZhG1: '"&SUBSTITUTE(H2,"'","\'")&"', nameKo: '"&SUBSTITUTE(J2,"'","\'")&"', ruby: '"&F2&"', rubyEn: '"&L2&IF(I2<>"", "', rubyZh: '"&I2, "")&"', baseType: '"&VLOOKUP(M2,マスタ!$A$1:$B$99,2,0)&"'"&IF(N2="○",", extra: true","")&IF(O2<>"",", extraFrom: '"&O2&"'","")&IF(P2<>"",", exchangableTo: '"&P2&"'","")&IF(Q2="○",", poison: true","")&IF(R2<>"", ", type: '"&VLOOKUP(R2,マスタ!$D$1:$E$99,2,0)&"'", "")&IF(S2<>"",", subType: '"&VLOOKUP(S2,マスタ!$D$1:$E$99,2,0)&"'","")&IF(T2<>"",", range: '"&T2&"'","")&IF(V2<>"",", damage: '"&V2&"'","")&IF(X2<>"",", capacity: '"&X2&"'","")&IF(Y2<>"",", cost: '"&Y2&"'","")&", text: '"&SUBSTITUTE(SUBSTITUTE(AB2, CHAR(13), ""),CHAR(10),"\n")&IF(AC2<>"", "', textAdditional: '"&SUBSTITUTE(SUBSTITUTE(AC2, CHAR(13), ""),CHAR(10),"\n"), "")&"', textZh: '"&SUBSTITUTE(SUBSTITUTE(SUBSTITUTE(AD2, CHAR(13), ""),CHAR(10),"\n"),"'","\'")&"', textZhG1: '"&SUBSTITUTE(SUBSTITUTE(SUBSTITUTE(AF2, CHAR(13), ""),CHAR(10),"\n"),"'","\'")&IF(AE2<>"", "', textZhAdditional: '"&SUBSTITUTE(SUBSTITUTE(AE2, CHAR(13), ""),CHAR(10),"\n"), "")&"', textKo: '"&SUBSTITUTE(SUBSTITUTE(SUBSTITUTE(AG2, CHAR(13), ""),CHAR(10),"\n"),"'","\'")&"', textEn: '"&SUBSTITUTE(SUBSTITUTE(SUBSTITUTE(AH2, CHAR(13), ""),CHAR(10),"\n"),"'","\'")&"'"&IF(Z2="○",", sealable: true","")&IF(AA2="○",", removable: true","")&"}") -> '01-yurina-o-n-1': {megami: 'yurina', name: '斬', nameEn: 'Slash', nameZh: '斩', nameZhG1: '斩', nameKo: '참', ruby: 'ざん', rubyEn: '', baseType: 'normal', type: 'attack', range: '3-4', damage: '3/1', text: '', textZh: '', textZhG1: '', textKo: '', textEn: ''} | AO2: =IF($A2<>"", " /** 《"&$E2&"》 */ export const "&SUBSTITUTE(UPPER(IF(MID($A2, 3, 1)="-", RIGHT($A2,LEN($A2)-3), $A2)), "-", "_")&": TCardId = '"&$A2&"';", "") -> /** 《斬》 */ export const YURINA_O_N_1: TCardId = '01-yurina-o-n-1'; | AP2: =IF($A2<>"", " | '"&$A2&"'", "") -> | '01-yurina-o-n-1'
A3: 01-yurina-A1-n-1 | B3: yurina | C3: A1 | D3: 01-yurina-o-n-1 | E3: 乱打 | F3: らんだ | G3: 乱打 | H3: 乱打 | J3: 난타 | K3: Wild Swing | M3: 通常札 | R3: 攻撃 | T3: 2 | V3: 2/1 | AB3: 【常時】決死-あなたのライフが3以下ならば、この《攻撃》は+0/+2となり、対応不可を得る。 | AD3: 【常时】决死～若自命中的樱花结晶数小于等于3，则此《攻击》得+0/+2和不可被对应。 | AF3: 【常时】决死-若自命中的樱花结晶的数目小于3，则此《攻击》得+0/+2和不可被对应。 | AG3: 【상시】결사-당신의 라이프가 3 이하라면, 이 《공격》은 +0/+2가 되고, 대응불가를 얻는다. | AH3: Forced: Resolve - If your Life is 3 or less, this attack gains +0/+2 and No Reactions. | AN3: =IF(A3="", "", IF(ROW()>=3, ", ", "")&"'"&A3&"': {megami: '"&B3&"'"&IF(C3<>"",", anotherID: '"&C3&"', replace: '"&D3&"'","")&", name: '"&SUBSTITUTE(E3,"'","\'")&"', nameEn: '"&SUBSTITUTE(K3,"'","\'")&"', nameZh: '"&SUBSTITUTE(G3,"'","\'")&"', nameZhG1: '"&SUBSTITUTE(H3,"'","\'")&"', nameKo: '"&SUBSTITUTE(J3,"'","\'")&"', ruby: '"&F3&"', rubyEn: '"&L3&IF(I3<>"", "', rubyZh: '"&I3, "")&"', baseType: '"&VLOOKUP(M3,マスタ!$A$1:$B$99,2,0)&"'"&IF(N3="○",", extra: true","")&IF(O3<>"",", extraFrom: '"&O3&"'","")&IF(P3<>"",", exchangableTo: '"&P3&"'","")&IF(Q3="○",", poison: true","")&IF(R3<>"", ", type: '"&VLOOKUP(R3,マスタ!$D$1:$E$99,2,0)&"'", "")&IF(S3<>"",", subType: '"&VLOOKUP(S3,マスタ!$D$1:$E$99,2,0)&"'","")&IF(T3<>"",", range: '"&T3&"'","")&IF(V3<>"",", damage: '"&V3&"'","")&IF(X3<>"",", capacity: '"&X3&"'","")&IF(Y3<>"",", cost: '"&Y3&"'","")&", text: '"&SUBSTITUTE(SUBSTITUTE(AB3, CHAR(13), ""),CHAR(10),"\n")&IF(AC3<>"", "', textAdditional: '"&SUBSTITUTE(SUBSTITUTE(AC3, CHAR(13), ""),CHAR(10),"\n"), "")&"', textZh: '"&SUBSTITUTE(SUBSTITUTE(SUBSTITUTE(AD3, CHAR(13), ""),CHAR(10),"\n"),"'","\'")&"', textZhG1: '"&SUBSTITUTE(SUBSTITUTE(SUBSTITUTE(AF3, CHAR(13), ""),CHAR(10),"\n"),"'","\'")&IF(AE3<>"", "', textZhAdditional: '"&SUBSTITUTE(SUBSTITUTE(AE3, CHAR(13), ""),CHAR(10),"\n"), "")&"', textKo: '"&SUBSTITUTE(SUBSTITUTE(SUBSTITUTE(AG3, CHAR(13), ""),CHAR(10),"\n"),"'","\'")&"', textEn: '"&SUBSTITUTE(SUBSTITUTE(SUBSTITUTE(AH3, CHAR(13), ""),CHAR(10),"\n"),"'","\'")&"'"&IF(Z3="○",", sealable: true","")&IF(AA3="○",", removable: true","")&"}") -> , '01-yurina-A1-n-1': {megami: 'yurina', anotherID: 'A1', replace: '01-yurina-o-n-1', name: '乱打', nameEn: 'Wild Swing', nameZh: '乱打', nameZhG1: '乱打', nameKo: '난타', ruby: 'らんだ', rubyEn: '', baseType: 'normal', type: 'attack', range: '2', damage: '2/1', text: '【常時】決死-あなたのライフが3以下ならば、この《攻撃》は+0/+2となり、対応不可を得る。', textZh: '【常时】决死～若自命中的樱花结晶数小于等于3，则此《攻击》得+0/+2和不可被对应。', textZhG1: '【常时】决死-若自命中的樱花结晶的数目小于3，则此《攻击》得+0/+2和不可被对应。', textKo: '【상시】결사-당신의 라이프가 3 이하라면, 이 《공격》은 +0/+2가 되고, 대응불가를 얻는다.', textEn: 'Forced: Resolve - If your Life is 3 or less, this attack gains +0/+2 and No Reactions.'} | AO3: =IF($A3<>"", " /** 《"&$E3&"》 */ export const "&SUBSTITUTE(UPPER(IF(MID($A3, 3, 1)="-", RIGHT($A3,LEN($A3)-3), $A3)), "-", "_")&": TCardId = '"&$A3&"';", "") -> /** 《乱打》 */ export const YURINA_A1_N_1: TCardId = '01-yurina-A1-n-1'; | AP3: =IF($A3<>"", " | '"&$A3&"'", "") -> | '01-yurina-A1-n-1'
A4: 01-yurina-o-n-2 | B4: yurina | E4: 一閃 | F4: いっせん | G4: 一闪 | H4: 一闪 | J4: 일섬 | K4: Brandish | M4: 通常札 | R4: 攻撃 | T4: 3 | V4: 2/2 | AB4: 【常時】決死-あなたのライフが3以下ならば、この《攻撃》は+1/+0となる。 | AD4: 【常时】决死～若自命中的樱花结晶数小于等于3，则此《攻击》得+1/+0。 | AF4: 【常时】决死-若自命中的樱花结晶的数目小于3，则此《攻击》得+1/+0。 | AG4: 【상시】결사-당신의 라이프가 3 이하라면, 이 《공격》은 +1/+0이 된다. | AH4: Forced: Resolve - This attack gains +1/+0 if your Life is 3 or less. | AN4: =IF(A4="", "", IF(ROW()>=3, ", ", "")&"'"&A4&"': {megami: '"&B4&"'"&IF(C4<>"",", anotherID: '"&C4&"', replace: '"&D4&"'","")&", name: '"&SUBSTITUTE(E4,"'","\'")&"', nameEn: '"&SUBSTITUTE(K4,"'","\'")&"', nameZh: '"&SUBSTITUTE(G4,"'","\'")&"', nameZhG1: '"&SUBSTITUTE(H4,"'","\'")&"', nameKo: '"&SUBSTITUTE(J4,"'","\'")&"', ruby: '"&F4&"', rubyEn: '"&L4&IF(I4<>"", "', rubyZh: '"&I4, "")&"', baseType: '"&VLOOKUP(M4,マスタ!$A$1:$B$99,2,0)&"'"&IF(N4="○",", extra: true","")&IF(O4<>"",", extraFrom: '"&O4&"'","")&IF(P4<>"",", exchangableTo: '"&P4&"'","")&IF(Q4="○",", poison: true","")&IF(R4<>"", ", type: '"&VLOOKUP(R4,マスタ!$D$1:$E$99,2,0)&"'", "")&IF(S4<>"",", subType: '"&VLOOKUP(S4,マスタ!$D$1:$E$99,2,0)&"'","")&IF(T4<>"",", range: '"&T4&"'","")&IF(V4<>"",", damage: '"&V4&"'","")&IF(X4<>"",", capacity: '"&X4&"'","")&IF(Y4<>"",", cost: '"&Y4&"'","")&", text: '"&SUBSTITUTE(SUBSTITUTE(AB4, CHAR(13), ""),CHAR(10),"\n")&IF(AC4<>"", "', textAdditional: '"&SUBSTITUTE(SUBSTITUTE(AC4, CHAR(13), ""),CHAR(10),"\n"), "")&"', textZh: '"&SUBSTITUTE(SUBSTITUTE(SUBSTITUTE(AD4, CHAR(13), ""),CHAR(10),"\n"),"'","\'")&"', textZhG1: '"&SUBSTITUTE(SUBSTITUTE(SUBSTITUTE(AF4, CHAR(13), ""),CHAR(10),"\n"),"'","\'")&IF(AE4<>"", "', textZhAdditional: '"&SUBSTITUTE(SUBSTITUTE(AE4, CHAR(13), ""),CHAR(10),"\n"), "")&"', textKo: '"&SUBSTITUTE(SUBSTITUTE(SUBSTITUTE(AG4, CHAR(13), ""),CHAR(10),"\n"),"'","\'")&"', textEn: '"&SUBSTITUTE(SUBSTITUTE(SUBSTITUTE(AH4, CHAR(13), ""),CHAR(10),"\n"),"'","\'")&"'"&IF(Z4="○",", sealable: true","")&IF(AA4="○",", removable: true","")&"}") -> , '01-yurina-o-n-2': {megami: 'yurina', name: '一閃', nameEn: 'Brandish', nameZh: '一闪', nameZhG1: '一闪', nameKo: '일섬', ruby: 'いっせん', rubyEn: '', baseType: 'normal', type: 'attack', range: '3', damage: '2/2', text: '【常時】決死-あなたのライフが3以下ならば、この《攻撃》は+1/+0となる。', textZh: '【常时】决死～若自命中的樱花结晶数小于等于3，则此《攻击》得+1/+0。', textZhG1: '【常时】决死-若自命中的樱花结晶的数目小于3，则此《攻击》得+1/+0。', textKo: '【상시】결사-당신의 라이프가 3 이하라면, 이 《공격》은 +1/+0이 된다.', textEn: 'Forced: Resolve - This attack gains +1/+0 if your Life is 3 or less.'} | AO4: =IF($A4<>"", " /** 《"&$E4&"》 */ export const "&SUBSTITUTE(UPPER(IF(MID($A4, 3, 1)="-", RIGHT($A4,LEN($A4)-3), $A4)), "-", "_")&": TCardId = '"&$A4&"';", "") -> /** 《一閃》 */ export const YURINA_O_N_2: TCardId = '01-yurina-o-n-2'; | AP4: =IF($A4<>"", " | '"&$A4&"'", "") -> | '01-yurina-o-n-2'
A5: 01-yurina-o-n-3 | B5: yurina | E5: 柄打ち | F5: つかうち | G5: 柄击 | H5: 柄击 | J5: 자루치기 | K5: Hilt Strike | M5: 通常札 | R5: 攻撃 | T5: 1-2 | V5: 2/1 | AB5: 【攻撃後】決死-あなたのライフが3以下ならば、このターンにあなたが次に行う《攻撃》は+1/+0となる。 | AD5: 【攻击后】决死～若自命中的樱花结晶数小于等于3，则本回合你的下一次《攻击》得+1/+0。 | AF5: 【攻击后】决死-若自命中的樱花结晶的数目小于3，则本回合你的下一次《攻击》得+1/+0。 | AG5: 【공격후】결사-당신의 라이프가 3 이하라면, 이 턴에 당신이 다음에 행하는 《공격》은 +1/+0이 된다. | AH5: After Attack: Resolve - The next attack you make this turn gains +1/+0 if your Life is 3 or less. | AN5: =IF(A5="", "", IF(ROW()>=3, ", ", "")&"'"&A5&"': {megami: '"&B5&"'"&IF(C5<>"",", anotherID: '"&C5&"', replace: '"&D5&"'","")&", name: '"&SUBSTITUTE(E5,"'","\'")&"', nameEn: '"&SUBSTITUTE(K5,"'","\'")&"', nameZh: '"&SUBSTITUTE(G5,"'","\'")&"', nameZhG1: '"&SUBSTITUTE(H5,"'","\'")&"', nameKo: '"&SUBSTITUTE(J5,"'","\'")&"', ruby: '"&F5&"', rubyEn: '"&L5&IF(I5<>"", "', rubyZh: '"&I5, "")&"', baseType: '"&VLOOKUP(M5,マスタ!$A$1:$B$99,2,0)&"'"&IF(N5="○",", extra: true","")&IF(O5<>"",", extraFrom: '"&O5&"'","")&IF(P5<>"",", exchangableTo: '"&P5&"'","")&IF(Q5="○",", poison: true","")&IF(R5<>"", ", type: '"&VLOOKUP(R5,マスタ!$D$1:$E$99,2,0)&"'", "")&IF(S5<>"",", subType: '"&VLOOKUP(S5,マスタ!$D$1:$E$99,2,0)&"'","")&IF(T5<>"",", range: '"&T5&"'","")&IF(V5<>"",", damage: '"&V5&"'","")&IF(X5<>"",", capacity: '"&X5&"'","")&IF(Y5<>"",", cost: '"&Y5&"'","")&", text: '"&SUBSTITUTE(SUBSTITUTE(AB5, CHAR(13), ""),CHAR(10),"\n")&IF(AC5<>"", "', textAdditional: '"&SUBSTITUTE(SUBSTITUTE(AC5, CHAR(13), ""),CHAR(10),"\n"), "")&"', textZh: '"&SUBSTITUTE(SUBSTITUTE(SUBSTITUTE(AD5, CHAR(13), ""),CHAR(10),"\n"),"'","\'")&"', textZhG1: '"&SUBSTITUTE(SUBSTITUTE(SUBSTITUTE(AF5, CHAR(13), ""),CHAR(10),"\n"),"'","\'")&IF(AE5<>"", "', textZhAdditional: '"&SUBSTITUTE(SUBSTITUTE(AE5, CHAR(13), ""),CHAR(10),"\n"), "")&"', textKo: '"&SUBSTITUTE(SUBSTITUTE(SUBSTITUTE(AG5, CHAR(13), ""),CHAR(10),"\n"),"'","\'")&"', textEn: '"&SUBSTITUTE(SUBSTITUTE(SUBSTITUTE(AH5, CHAR(13), ""),CHAR(10),"\n"),"'","\'")&"'"&IF(Z5="○",", sealable: true","")&IF(AA5="○",", removable: true","")&"}") -> , '01-yurina-o-n-3': {megami: 'yurina', name: '柄打ち', nameEn: 'Hilt Strike', nameZh: '柄击', nameZhG1: '柄击', nameKo: '자루치기', ruby: 'つかうち', rubyEn: '', baseType: 'normal', type: 'attack', range: '1-2', damage: '2/1', text: '【攻撃後】決死-あなたのライフが3以下ならば、このターンにあなたが次に行う《攻撃》は+1/+0となる。', textZh: '【攻击后】决死～若自命中的樱花结晶数小于等于3，则本回合你的下一次《攻击》得+1/+0。', textZhG1: '【攻击后】决死-若自命中的樱花结晶的数目小于3，则本回合你的下一次《攻击》得+1/+0。', textKo: '【공격후】결사-당신의 라이프가 3 이하라면, 이 턴에 당신이 다음에 행하는 《공격》은 +1/+0이 된다.', textEn: 'After Attack: Resolve - The next attack you make this turn gains +1/+0 if your Life is 3 or less.'} | AO5: =IF($A5<>"", " /** 《"&$E5&"》 */ export const "&SUBSTITUTE(UPPER(IF(MID($A5, 3, 1)="-", RIGHT($A5,LEN($A5)-3), $A5)), "-", "_")&": TCardId = '"&$A5&"';", "") -> /** 《柄打ち》 */ export const YURINA_O_N_3: TCardId = '01-yurina-o-n-3'; | AP5: =IF($A5<>"", " | '"&$A5&"'", "") -> | '01-yurina-o-n-3'
A6: 01-yurina-o-n-4 | B6: yurina | E6: 居合 | F6: いあい | G6: 居合 | H6: 居合斩 | J6: 거합 | K6: Art of Drawing | M6: 通常札 | R6: 攻撃 | S6: 全力 | T6: 2-4 | V6: 4/3 | AB6: 【常時】現在の間合が2以下ならば、この攻撃は-1/-1となる。 | AD6: 【常时】若当前距离小于等于2，则此《攻击》得-1/-1。 | AF6: 【常时】若当前距离小于2，则此《攻击》得-1/-1。 | AG6: 【상시】현재 간격이 2 이하라면, 이 공격은 -1/-1이 된다. | AH6: Forced: If the current Distance is 2 or less, this attack gets -1/-1. | AN6: =IF(A6="", "", IF(ROW()>=3, ", ", "")&"'"&A6&"': {megami: '"&B6&"'"&IF(C6<>"",", anotherID: '"&C6&"', replace: '"&D6&"'","")&", name: '"&SUBSTITUTE(E6,"'","\'")&"', nameEn: '"&SUBSTITUTE(K6,"'","\'")&"', nameZh: '"&SUBSTITUTE(G6,"'","\'")&"', nameZhG1: '"&SUBSTITUTE(H6,"'","\'")&"', nameKo: '"&SUBSTITUTE(J6,"'","\'")&"', ruby: '"&F6&"', rubyEn: '"&L6&IF(I6<>"", "', rubyZh: '"&I6, "")&"', baseType: '"&VLOOKUP(M6,マスタ!$A$1:$B$99,2,0)&"'"&IF(N6="○",", extra: true","")&IF(O6<>"",", extraFrom: '"&O6&"'","")&IF(P6<>"",", exchangableTo: '"&P6&"'","")&IF(Q6="○",", poison: true","")&IF(R6<>"", ", type: '"&VLOOKUP(R6,マスタ!$D$1:$E$99,2,0)&"'", "")&IF(S6<>"",", subType: '"&VLOOKUP(S6,マスタ!$D$1:$E$99,2,0)&"'","")&IF(T6<>"",", range: '"&T6&"'","")&IF(V6<>"",", damage: '"&V6&"'","")&IF(X6<>"",", capacity: '"&X6&"'","")&IF(Y6<>"",", cost: '"&Y6&"'","")&", text: '"&SUBSTITUTE(SUBSTITUTE(AB6, CHAR(13), ""),CHAR(10),"\n")&IF(AC6<>"", "', textAdditional: '"&SUBSTITUTE(SUBSTITUTE(AC6, CHAR(13), ""),CHAR(10),"\n"), "")&"', textZh: '"&SUBSTITUTE(SUBSTITUTE(SUBSTITUTE(AD6, CHAR(13), ""),CHAR(10),"\n"),"'","\'")&"', textZhG1: '"&SUBSTITUTE(SUBSTITUTE(SUBSTITUTE(AF6, CHAR(13), ""),CHAR(10),"\n"),"'","\'")&IF(AE6<>"", "', textZhAdditional: '"&SUBSTITUTE(SUBSTITUTE(AE6, CHAR(13), ""),CHAR(10),"\n"), "")&"', textKo: '"&SUBSTITUTE(SUBSTITUTE(SUBSTITUTE(AG6, CHAR(13), ""),CHAR(10),"\n"),"'","\'")&"', textEn: '"&SUBSTITUTE(SUBSTITUTE(SUBSTITUTE(AH6, CHAR(13), ""),CHAR(10),"\n"),"'","\'")&"'"&IF(Z6="○",", sealable: true","")&IF(AA6="○",", removable: true","")&"}") -> , '01-yurina-o-n-4': {megami: 'yurina', name: '居合', nameEn: 'Art of Drawing', nameZh: '居合', nameZhG1: '居合斩', nameKo: '거합', ruby: 'いあい', rubyEn: '', baseType: 'normal', type: 'attack', subType: 'fullpower', range: '2-4', damage: '4/3', text: '【常時】現在の間合が2以下ならば、この攻撃は-1/-1となる。', textZh: '【常时】若当前距离小于等于2，则此《攻击》得-1/-1。', textZhG1: '【常时】若当前距离小于2，则此《攻击》得-1/-1。', textKo: '【상시】현재 간격이 2 이하라면, 이 공격은 -1/-1이 된다.', textEn: 'Forced: If the current Distance is 2 or less, this attack gets -1/-1.'} | AO6: =IF($A6<>"", " /** 《"&$E6&"》 */ export const "&SUBSTITUTE(UPPER(IF(MID($A6, 3, 1)="-", RIGHT($A6,LEN($A6)-3), $A6)), "-", "_")&": TCardId = '"&$A6&"';", "") -> /** 《居合》 */ export const YURINA_O_N_4: TCardId = '01-yurina-o-n-4'; | AP6: =IF($A6<>"", " | '"&$A6&"'", "") -> | '01-yurina-o-n-4'
A7: 01-yurina-o-n-5 | B7: yurina | E7: 足捌き | F7: あしさばき | G7: 运足 | H7: 疾跑 | J7: 발놀림 | K7: Footwork | M7: 通常札 | R7: 行動 | AB7: 現在の間合が4以上ならば、間合→ダスト：2 現在の間合が1以下ならば、ダスト→間合：2 | AD7: 若当前距离大于等于4，则：距→2→虚。 若当前距离小于等于1，则：虚→2→距。 | AF7: 若当前距离大于4，则距（2）→虚。 若当前距离小于1，则虚（2）→距。 | AG7: 현재 간격이 4 이상이라면、간격→더스트：2 현재 간격이 1이하라면, 더스트→간격：2 | AH7: If the current Distance is 4 or more: Distance (2)→ Shadow If the current Distance is 1 or less: Shadow (2)→ Distance | AN7: =IF(A7="", "", IF(ROW()>=3, ", ", "")&"'"&A7&"': {megami: '"&B7&"'"&IF(C7<>"",", anotherID: '"&C7&"', replace: '"&D7&"'","")&", name: '"&SUBSTITUTE(E7,"'","\'")&"', nameEn: '"&SUBSTITUTE(K7,"'","\'")&"', nameZh: '"&SUBSTITUTE(G7,"'","\'")&"', nameZhG1: '"&SUBSTITUTE(H7,"'","\'")&"', nameKo: '"&SUBSTITUTE(J7,"'","\'")&"', ruby: '"&F7&"', rubyEn: '"&L7&IF(I7<>"", "', rubyZh: '"&I7, "")&"', baseType: '"&VLOOKUP(M7,マスタ!$A$1:$B$99,2,0)&"'"&IF(N7="○",", extra: true","")&IF(O7<>"",", extraFrom: '"&O7&"'","")&IF(P7<>"",", exchangableTo: '"&P7&"'","")&IF(Q7="○",", poison: true","")&IF(R7<>"", ", type: '"&VLOOKUP(R7,マスタ!$D$1:$E$99,2,0)&"'", "")&IF(S7<>"",", subType: '"&VLOOKUP(S7,マスタ!$D$1:$E$99,2,0)&"'","")&IF(T7<>"",", range: '"&T7&"'","")&IF(V7<>"",", damage: '"&V7&"'","")&IF(X7<>"",", capacity: '"&X7&"'","")&IF(Y7<>"",", cost: '"&Y7&"'","")&", text: '"&SUBSTITUTE(SUBSTITUTE(AB7, CHAR(13), ""),CHAR(10),"\n")&IF(AC7<>"", "', textAdditional: '"&SUBSTITUTE(SUBSTITUTE(AC7, CHAR(13), ""),CHAR(10),"\n"), "")&"', textZh: '"&SUBSTITUTE(SUBSTITUTE(SUBSTITUTE(AD7, CHAR(13), ""),CHAR(10),"\n"),"'","\'")&"', textZhG1: '"&SUBSTITUTE(SUBSTITUTE(SUBSTITUTE(AF7, CHAR(13), ""),CHAR(10),"\n"),"'","\'")&IF(AE7<>"", "', textZhAdditional: '"&SUBSTITUTE(SUBSTITUTE(AE7, CHAR(13), ""),CHAR(10),"\n"), "")&"', textKo: '"&SUBSTITUTE(SUBSTITUTE(SUBSTITUTE(AG7, CHAR(13), ""),CHAR(10),"\n"),"'","\'")&"', textEn: '"&SUBSTITUTE(SUBSTITUTE(SUBSTITUTE(AH7, CHAR(13), ""),CHAR(10),"\n"),"'","\'")&"'"&IF(Z7="○",", sealable: true","")&IF(AA7="○",", removable: true","")&"}") -> , '01-yurina-o-n-5': {megami: 'yurina', name: '足捌き', nameEn: 'Footwork', nameZh: '运足', nameZhG1: '疾跑', nameKo: '발놀림', ruby: 'あしさばき', rubyEn: '', baseType: 'normal', type: 'action', text: '現在の間合が4以上ならば、間合→ダスト：2\n現在の間合が1以下ならば、ダスト→間合：2', textZh: '若当前距离大于等于4，则：距→2→虚。 \n若当前距离小于等于1，则：虚→2→距。', textZhG1: '若当前距离大于4，则距（2）→虚。 \n若当前距离小于1，则虚（2）→距。', textKo: '현재 간격이 4 이상이라면、간격→더스트：2\n현재 간격이 1이하라면, 더스트→간격：2', textEn: 'If the current Distance is 4 or more:\nDistance (2)→ Shadow\n\nIf the current Distance is 1 or less:\nShadow (2)→ Distance'} | AO7: =IF($A7<>"", " /** 《"&$E7&"》 */ export const "&SUBSTITUTE(UPPER(IF(MID($A7, 3, 1)="-", RIGHT($A7,LEN($A7)-3), $A7)), "-", "_")&": TCardId = '"&$A7&"';", "") -> /** 《足捌き》 */ export const YURINA_O_N_5: TCardId = '01-yurina-o-n-5'; | AP7: =IF($A7<>"", " | '"&$A7&"'", "") -> | '01-yurina-o-n-5'
A8: 01-yurina-o-n-6 | B8: yurina | E8: 圧気 | F8: あっき | G8: 威压 | H8: 气合斩 | J8: 압기 | K8: Overawe | M8: 通常札 | R8: 付与 | X8: 2 | AB8: 隙 【破棄時】攻撃『適正距離1-4、3/-』を行う。 | AD8: 破绽 【破弃时】进行一次“攻击距离1-4、伤害3/-”的攻击。 | AF8: 破绽 【破弃时】进行一次“攻击距离1-4 伤害3/-”的攻击。 | AG8: 빈틈 【파기시】공격『적정거리1-4、3/-』을 행한다. | AH8: Unguarded Disenchant: You attack with "Range: 1-4, Damage: 3/-". | AN8: =IF(A8="", "", IF(ROW()>=3, ", ", "")&"'"&A8&"': {megami: '"&B8&"'"&IF(C8<>"",", anotherID: '"&C8&"', replace: '"&D8&"'","")&", name: '"&SUBSTITUTE(E8,"'","\'")&"', nameEn: '"&SUBSTITUTE(K8,"'","\'")&"', nameZh: '"&SUBSTITUTE(G8,"'","\'")&"', nameZhG1: '"&SUBSTITUTE(H8,"'","\'")&"', nameKo: '"&SUBSTITUTE(J8,"'","\'")&"', ruby: '"&F8&"', rubyEn: '"&L8&IF(I8<>"", "', rubyZh: '"&I8, "")&"', baseType: '"&VLOOKUP(M8,マスタ!$A$1:$B$99,2,0)&"'"&IF(N8="○",", extra: true","")&IF(O8<>"",", extraFrom: '"&O8&"'","")&IF(P8<>"",", exchangableTo: '"&P8&"'","")&IF(Q8="○",", poison: true","")&IF(R8<>"", ", type: '"&VLOOKUP(R8,マスタ!$D$1:$E$99,2,0)&"'", "")&IF(S8<>"",", subType: '"&VLOOKUP(S8,マスタ!$D$1:$E$99,2,0)&"'","")&IF(T8<>"",", range: '"&T8&"'","")&IF(V8<>"",", damage: '"&V8&"'","")&IF(X8<>"",", capacity: '"&X8&"'","")&IF(Y8<>"",", cost: '"&Y8&"'","")&", text: '"&SUBSTITUTE(SUBSTITUTE(AB8, CHAR(13), ""),CHAR(10),"\n")&IF(AC8<>"", "', textAdditional: '"&SUBSTITUTE(SUBSTITUTE(AC8, CHAR(13), ""),CHAR(10),"\n"), "")&"', textZh: '"&SUBSTITUTE(SUBSTITUTE(SUBSTITUTE(AD8, CHAR(13), ""),CHAR(10),"\n"),"'","\'")&"', textZhG1: '"&SUBSTITUTE(SUBSTITUTE(SUBSTITUTE(AF8, CHAR(13), ""),CHAR(10),"\n"),"'","\'")&IF(AE8<>"", "', textZhAdditional: '"&SUBSTITUTE(SUBSTITUTE(AE8, CHAR(13), ""),CHAR(10),"\n"), "")&"', textKo: '"&SUBSTITUTE(SUBSTITUTE(SUBSTITUTE(AG8, CHAR(13), ""),CHAR(10),"\n"),"'","\'")&"', textEn: '"&SUBSTITUTE(SUBSTITUTE(SUBSTITUTE(AH8, CHAR(13), ""),CHAR(10),"\n"),"'","\'")&"'"&IF(Z8="○",", sealable: true","")&IF(AA8="○",", removable: true","")&"}") -> , '01-yurina-o-n-6': {megami: 'yurina', name: '圧気', nameEn: 'Overawe', nameZh: '威压', nameZhG1: '气合斩', nameKo: '압기', ruby: 'あっき', rubyEn: '', baseType: 'normal', type: 'enhance', capacity: '2', text: '隙\n【破棄時】攻撃『適正距離1-4、3/-』を行う。', textZh: '破绽\n【破弃时】进行一次“攻击距离1-4、伤害3/-”的攻击。', textZhG1: '破绽\n【破弃时】进行一次“攻击距离1-4 伤害3/-”的攻击。', textKo: '빈틈\n 【파기시】공격『적정거리1-4、3/-』을 행한다.', textEn: 'Unguarded\nDisenchant: You attack with "Range: 1-4, Damage: 3/-".'} | AO8: =IF($A8<>"", " /** 《"&$E8&"》 */ export const "&SUBSTITUTE(UPPER(IF(MID($A8, 3, 1)="-", RIGHT($A8,LEN($A8)-3), $A8)), "-", "_")&": TCardId = '"&$A8&"';", "") -> /** 《圧気》 */ export const YURINA_O_N_6: TCardId = '01-yurina-o-n-6'; | AP8: =IF($A8<>"", " | '"&$A8&"'", "") -> | '01-yurina-o-n-6'
A9: 01-yurina-A1-n-6 | B9: yurina | C9: A1 | D9: 01-yurina-o-n-6 | E9: 癇癪玉 | F9: かんしゃくだま | G9: 掌心雷 | H9: 暴砂雷 | J9: 콩알탄 | K9: Outrage | M9: 通常札 | R9: 付与 | S9: 対応 | X9: １ | AB9: 【破棄時】攻撃『適正距離0-4、1/-、対応不可、【攻撃後】相手を畏縮させる』を行う。 | AD9: 【破弃时】进行一次“攻击距离0-4、伤害1/-、不可被对应、【攻击后】令对手畏缩”的攻击。 | AF9: 【破弃时】进行一次“攻击距离0-4 伤害1/- 不可被对应，【攻击后】对手畏缩”的攻击。 | AG9: 【파기시】공격『적정거리0-4、1/-、대응불가、【공격후】상대를 위축시킨다』를 행한다. | AH9: Disenchant: You attack with "Range: 0-4, Damage: 1/-, No Reactions, After Attack: Flinch your opponent." | AN9: =IF(A9="", "", IF(ROW()>=3, ", ", "")&"'"&A9&"': {megami: '"&B9&"'"&IF(C9<>"",", anotherID: '"&C9&"', replace: '"&D9&"'","")&", name: '"&SUBSTITUTE(E9,"'","\'")&"', nameEn: '"&SUBSTITUTE(K9,"'","\'")&"', nameZh: '"&SUBSTITUTE(G9,"'","\'")&"', nameZhG1: '"&SUBSTITUTE(H9,"'","\'")&"', nameKo: '"&SUBSTITUTE(J9,"'","\'")&"', ruby: '"&F9&"', rubyEn: '"&L9&IF(I9<>"", "', rubyZh: '"&I9, "")&"', baseType: '"&VLOOKUP(M9,マスタ!$A$1:$B$99,2,0)&"'"&IF(N9="○",", extra: true","")&IF(O9<>"",", extraFrom: '"&O9&"'","")&IF(P9<>"",", exchangableTo: '"&P9&"'","")&IF(Q9="○",", poison: true","")&IF(R9<>"", ", type: '"&VLOOKUP(R9,マスタ!$D$1:$E$99,2,0)&"'", "")&IF(S9<>"",", subType: '"&VLOOKUP(S9,マスタ!$D$1:$E$99,2,0)&"'","")&IF(T9<>"",", range: '"&T9&"'","")&IF(V9<>"",", damage: '"&V9&"'","")&IF(X9<>"",", capacity: '"&X9&"'","")&IF(Y9<>"",", cost: '"&Y9&"'","")&", text: '"&SUBSTITUTE(SUBSTITUTE(AB9, CHAR(13), ""),CHAR(10),"\n")&IF(AC9<>"", "', textAdditional: '"&SUBSTITUTE(SUBSTITUTE(AC9, CHAR(13), ""),CHAR(10),"\n"), "")&"', textZh: '"&SUBSTITUTE(SUBSTITUTE(SUBSTITUTE(AD9, CHAR(13), ""),CHAR(10),"\n"),"'","\'")&"', textZhG1: '"&SUBSTITUTE(SUBSTITUTE(SUBSTITUTE(AF9, CHAR(13), ""),CHAR(10),"\n"),"'","\'")&IF(AE9<>"", "', textZhAdditional: '"&SUBSTITUTE(SUBSTITUTE(AE9, CHAR(13), ""),CHAR(10),"\n"), "")&"', textKo: '"&SUBSTITUTE(SUBSTITUTE(SUBSTITUTE(AG9, CHAR(13), ""),CHAR(10),"\n"),"'","\'")&"', textEn: '"&SUBSTITUTE(SUBSTITUTE(SUBSTITUTE(AH9, CHAR(13), ""),CHAR(10),"\n"),"'","\'")&"'"&IF(Z9="○",", sealable: true","")&IF(AA9="○",", removable: true","")&"}") -> , '01-yurina-A1-n-6': {megami: 'yurina', anotherID: 'A1', replace: '01-yurina-o-n-6', name: '癇癪玉', nameEn: 'Outrage', nameZh: '掌心雷', nameZhG1: '暴砂雷', nameKo: '콩알탄', ruby: 'かんしゃくだま ', rubyEn: '', baseType: 'normal', type: 'enhance', subType: 'reaction', capacity: '１', text: '【破棄時】攻撃『適正距離0-4、1/-、対応不可、【攻撃後】相手を畏縮させる』を行う。', textZh: '【破弃时】进行一次“攻击距离0-4、伤害1/-、不可被对应、【攻击后】令对手畏缩”的攻击。', textZhG1: '【破弃时】进行一次“攻击距离0-4 伤害1/- 不可被对应，【攻击后】对手畏缩”的攻击。', textKo: '【파기시】공격『적정거리0-4、1/-、대응불가、【공격후】상대를 위축시킨다』를 행한다.', textEn: 'Disenchant: You attack with "Range: 0-4, Damage: 1/-, No Reactions, After Attack: Flinch your opponent."'} | AO9: =IF($A9<>"", " /** 《"&$E9&"》 */ export const "&SUBSTITUTE(UPPER(IF(MID($A9, 3, 1)="-", RIGHT($A9,LEN($A9)-3), $A9)), "-", "_")&": TCardId = '"&$A9&"';", "") -> /** 《癇癪玉》 */ export const YURINA_A1_N_6: TCardId = '01-yurina-A1-n-6'; | AP9: =IF($A9<>"", " | '"&$A9&"'", "") -> | '01-yurina-A1-n-6'
A10: 01-yurina-o-n-7 | B10: yurina | E10: 気炎万丈 | F10: きえんばんじょう | G10: 气焰万丈 | H10: 气焰万丈 | J10: 기염만장 | K10: Spirit of Fire | M10: 通常札 | R10: 付与 | S10: 全力 | X10: 4 | AB10: 【展開中】決死-あなたのライフが3以下ならば、あなたの他のメガミによる《攻撃》は+1/+1となるとともに超克を得る。 | AD10: 【展开中】决死～若自命中的樱花结晶数小于等于3，则你的另一柱女神的《攻击》得+1/+1和超克。 | AF10: 【展开中】决死-若自命中的樱花结晶的数目小于3，则你的另一柱女武神的《攻击》得+1/+1和超克。 | AG10: 【전개중】결사-당신의 라이프가 3 이하라면, 당신의 다른 여신에 의한 《공격》은 +1/+1이 되며 초극을 얻는다. | AH10: Ongoing: Resolve - All your other Megami's attacks gain +1/+1 and Overwhelm if your Life is 3 or less. | AN10: =IF(A10="", "", IF(ROW()>=3, ", ", "")&"'"&A10&"': {megami: '"&B10&"'"&IF(C10<>"",", anotherID: '"&C10&"', replace: '"&D10&"'","")&", name: '"&SUBSTITUTE(E10,"'","\'")&"', nameEn: '"&SUBSTITUTE(K10,"'","\'")&"', nameZh: '"&SUBSTITUTE(G10,"'","\'")&"', nameZhG1: '"&SUBSTITUTE(H10,"'","\'")&"', nameKo: '"&SUBSTITUTE(J10,"'","\'")&"', ruby: '"&F10&"', rubyEn: '"&L10&IF(I10<>"", "', rubyZh: '"&I10, "")&"', baseType: '"&VLOOKUP(M10,マスタ!$A$1:$B$99,2,0)&"'"&IF(N10="○",", extra: true","")&IF(O10<>"",", extraFrom: '"&O10&"'","")&IF(P10<>"",", exchangableTo: '"&P10&"'","")&IF(Q10="○",", poison: true","")&IF(R10<>"", ", type: '"&VLOOKUP(R10,マスタ!$D$1:$E$99,2,0)&"'", "")&IF(S10<>"",", subType: '"&VLOOKUP(S10,マスタ!$D$1:$E$99,2,0)&"'","")&IF(T10<>"",", range: '"&T10&"'","")&IF(V10<>"",", damage: '"&V10&"'","")&IF(X10<>"",", capacity: '"&X10&"'","")&IF(Y10<>"",", cost: '"&Y10&"'","")&", text: '"&SUBSTITUTE(SUBSTITUTE(AB10, CHAR(13), ""),CHAR(10),"\n")&IF(AC10<>"", "', textAdditional: '"&SUBSTITUTE(SUBSTITUTE(AC10, CHAR(13), ""),CHAR(10),"\n"), "")&"', textZh: '"&SUBSTITUTE(SUBSTITUTE(SUBSTITUTE(AD10, CHAR(13), ""),CHAR(10),"\n"),"'","\'")&"', textZhG1: '"&SUBSTITUTE(SUBSTITUTE(SUBSTITUTE(AF10, CHAR(13), ""),CHAR(10),"\n"),"'","\'")&IF(AE10<>"", "', textZhAdditional: '"&SUBSTITUTE(SUBSTITUTE(AE10, CHAR(13), ""),CHAR(10),"\n"), "")&"', textKo: '"&SUBSTITUTE(SUBSTITUTE(SUBSTITUTE(AG10, CHAR(13), ""),CHAR(10),"\n"),"'","\'")&"', textEn: '"&SUBSTITUTE(SUBSTITUTE(SUBSTITUTE(AH10, CHAR(13), ""),CHAR(10),"\n"),"'","\'")&"'"&IF(Z10="○",", sealable: true","")&IF(AA10="○",", removable: true","")&"}") -> , '01-yurina-o-n-7': {megami: 'yurina', name: '気炎万丈', nameEn: 'Spirit of Fire', nameZh: '气焰万丈', nameZhG1: '气焰万丈', nameKo: '기염만장', ruby: 'きえんばんじょう', rubyEn: '', baseType: 'normal', type: 'enhance', subType: 'fullpower', capacity: '4', text: '【展開中】決死-あなたのライフが3以下ならば、あなたの他のメガミによる《攻撃》は+1/+1となるとともに超克を得る。', textZh: '【展开中】决死～若自命中的樱花结晶数小于等于3，则你的另一柱女神的《攻击》得+1/+1和超克。', textZhG1: '【展开中】决死-若自命中的樱花结晶的数目小于3，则你的另一柱女武神的《攻击》得+1/+1和超克。', textKo: '【전개중】결사-당신의 라이프가 3 이하라면, 당신의 다른 여신에 의한 《공격》은 +1/+1이 되며 초극을 얻는다.', textEn: 'Ongoing: Resolve - All your other Megami\'s attacks gain +1/+1 and Overwhelm if your Life is 3 or less.'} | AO10: =IF($A10<>"", " /** 《"&$E10&"》 */ export const "&SUBSTITUTE(UPPER(IF(MID($A10, 3, 1)="-", RIGHT($A10,LEN($A10)-3), $A10)), "-", "_")&": TCardId = '"&$A10&"';", "") -> /** 《気炎万丈》 */ export const YURINA_O_N_7: TCardId = '01-yurina-o-n-7'; | AP10: =IF($A10<>"", " | '"&$A10&"'", "") -> | '01-yurina-o-n-7'
A11: 01-yurina-o-s-1 | B11: yurina | E11: 月影落 | F11: つきかげおとし | G11: 月影落 | H11: 月影落 | J11: 달그림자 떨어지니 | K11: Tsukikage Crush | M11: 切札 | R11: 攻撃 | T11: 3-4 | V11: 4/4 | Y11: 7 | AN11: =IF(A11="", "", IF(ROW()>=3, ", ", "")&"'"&A11&"': {megami: '"&B11&"'"&IF(C11<>"",", anotherID: '"&C11&"', replace: '"&D11&"'","")&", name: '"&SUBSTITUTE(E11,"'","\'")&"', nameEn: '"&SUBSTITUTE(K11,"'","\'")&"', nameZh: '"&SUBSTITUTE(G11,"'","\'")&"', nameZhG1: '"&SUBSTITUTE(H11,"'","\'")&"', nameKo: '"&SUBSTITUTE(J11,"'","\'")&"', ruby: '"&F11&"', rubyEn: '"&L11&IF(I11<>"", "', rubyZh: '"&I11, "")&"', baseType: '"&VLOOKUP(M11,マスタ!$A$1:$B$99,2,0)&"'"&IF(N11="○",", extra: true","")&IF(O11<>"",", extraFrom: '"&O11&"'","")&IF(P11<>"",", exchangableTo: '"&P11&"'","")&IF(Q11="○",", poison: true","")&IF(R11<>"", ", type: '"&VLOOKUP(R11,マスタ!$D$1:$E$99,2,0)&"'", "")&IF(S11<>"",", subType: '"&VLOOKUP(S11,マスタ!$D$1:$E$99,2,0)&"'","")&IF(T11<>"",", range: '"&T11&"'","")&IF(V11<>"",", damage: '"&V11&"'","")&IF(X11<>"",", capacity: '"&X11&"'","")&IF(Y11<>"",", cost: '"&Y11&"'","")&", text: '"&SUBSTITUTE(SUBSTITUTE(AB11, CHAR(13), ""),CHAR(10),"\n")&IF(AC11<>"", "', textAdditional: '"&SUBSTITUTE(SUBSTITUTE(AC11, CHAR(13), ""),CHAR(10),"\n"), "")&"', textZh: '"&SUBSTITUTE(SUBSTITUTE(SUBSTITUTE(AD11, CHAR(13), ""),CHAR(10),"\n"),"'","\'")&"', textZhG1: '"&SUBSTITUTE(SUBSTITUTE(SUBSTITUTE(AF11, CHAR(13), ""),CHAR(10),"\n"),"'","\'")&IF(AE11<>"", "', textZhAdditional: '"&SUBSTITUTE(SUBSTITUTE(AE11, CHAR(13), ""),CHAR(10),"\n"), "")&"', textKo: '"&SUBSTITUTE(SUBSTITUTE(SUBSTITUTE(AG11, CHAR(13), ""),CHAR(10),"\n"),"'","\'")&"', textEn: '"&SUBSTITUTE(SUBSTITUTE(SUBSTITUTE(AH11, CHAR(13), ""),CHAR(10),"\n"),"'","\'")&"'"&IF(Z11="○",", sealable: true","")&IF(AA11="○",", removable: true","")&"}") -> , '01-yurina-o-s-1': {megami: 'yurina', name: '月影落', nameEn: 'Tsukikage Crush', nameZh: '月影落', nameZhG1: '月影落', nameKo: '달그림자 떨어지니', ruby: 'つきかげおとし', rubyEn: '', baseType: 'special', type: 'attack', range: '3-4', damage: '4/4', cost: '7', text: '', textZh: '', textZhG1: '', textKo: '', textEn: ''} | AO11: =IF($A11<>"", " /** 《"&$E11&"》 */ export const "&SUBSTITUTE(UPPER(IF(MID($A11, 3, 1)="-", RIGHT($A11,LEN($A11)-3), $A11)), "-", "_")&": TCardId = '"&$A11&"';", "") -> /** 《月影落》 */ export const YURINA_O_S_1: TCardId = '01-yurina-o-s-1'; | AP11: =IF($A11<>"", " | '"&$A11&"'", "") -> | '01-yurina-o-s-1'
A12: 01-yurina-o-s-2 | B12: yurina | E12: 浦波嵐 | F12: うらなみあらし | G12: 浦波岚 | H12: 浦波岚 | J12: 해안에 파랑 일며 | K12: Uranami Storm | M12: 切札 | R12: 攻撃 | S12: 対応 | T12: 0-10 | V12: 2/- | Y12: 3 | AB12: 【攻撃後】対応した《攻撃》は-2/+0となる。 | AD12: 【攻击后】被对应的《攻击》得-2/+0。 | AF12: 【攻击后】被对应的《攻击》得-2/-0。 | AG12: 【공격후】대응한 《공격》은 -2/+0이 된다. | AH12: After Attack: The attack this card was played as a Reaction to gets -2/+0. | AN12: =IF(A12="", "", IF(ROW()>=3, ", ", "")&"'"&A12&"': {megami: '"&B12&"'"&IF(C12<>"",", anotherID: '"&C12&"', replace: '"&D12&"'","")&", name: '"&SUBSTITUTE(E12,"'","\'")&"', nameEn: '"&SUBSTITUTE(K12,"'","\'")&"', nameZh: '"&SUBSTITUTE(G12,"'","\'")&"', nameZhG1: '"&SUBSTITUTE(H12,"'","\'")&"', nameKo: '"&SUBSTITUTE(J12,"'","\'")&"', ruby: '"&F12&"', rubyEn: '"&L12&IF(I12<>"", "', rubyZh: '"&I12, "")&"', baseType: '"&VLOOKUP(M12,マスタ!$A$1:$B$99,2,0)&"'"&IF(N12="○",", extra: true","")&IF(O12<>"",", extraFrom: '"&O12&"'","")&IF(P12<>"",", exchangableTo: '"&P12&"'","")&IF(Q12="○",", poison: true","")&IF(R12<>"", ", type: '"&VLOOKUP(R12,マスタ!$D$1:$E$99,2,0)&"'", "")&IF(S12<>"",", subType: '"&VLOOKUP(S12,マスタ!$D$1:$E$99,2,0)&"'","")&IF(T12<>"",", range: '"&T12&"'","")&IF(V12<>"",", damage: '"&V12&"'","")&IF(X12<>"",", capacity: '"&X12&"'","")&IF(Y12<>"",", cost: '"&Y12&"'","")&", text: '"&SUBSTITUTE(SUBSTITUTE(AB12, CHAR(13), ""),CHAR(10),"\n")&IF(AC12<>"", "', textAdditional: '"&SUBSTITUTE(SUBSTITUTE(AC12, CHAR(13), ""),CHAR(10),"\n"), "")&"', textZh: '"&SUBSTITUTE(SUBSTITUTE(SUBSTITUTE(AD12, CHAR(13), ""),CHAR(10),"\n"),"'","\'")&"', textZhG1: '"&SUBSTITUTE(SUBSTITUTE(SUBSTITUTE(AF12, CHAR(13), ""),CHAR(10),"\n"),"'","\'")&IF(AE12<>"", "', textZhAdditional: '"&SUBSTITUTE(SUBSTITUTE(AE12, CHAR(13), ""),CHAR(10),"\n"), "")&"', textKo: '"&SUBSTITUTE(SUBSTITUTE(SUBSTITUTE(AG12, CHAR(13), ""),CHAR(10),"\n"),"'","\'")&"', textEn: '"&SUBSTITUTE(SUBSTITUTE(SUBSTITUTE(AH12, CHAR(13), ""),CHAR(10),"\n"),"'","\'")&"'"&IF(Z12="○",", sealable: true","")&IF(AA12="○",", removable: true","")&"}") -> , '01-yurina-o-s-2': {megami: 'yurina', name: '浦波嵐', nameEn: 'Uranami Storm', nameZh: '浦波岚', nameZhG1: '浦波岚', nameKo: '해안에 파랑 일며', ruby: 'うらなみあらし', rubyEn: '', baseType: 'special', type: 'attack', subType: 'reaction', range: '0-10', damage: '2/-', cost: '3', text: '【攻撃後】対応した《攻撃》は-2/+0となる。', textZh: '【攻击后】被对应的《攻击》得-2/+0。', textZhG1: '【攻击后】被对应的《攻击》得-2/-0。', textKo: '【공격후】대응한 《공격》은 -2/+0이 된다.', textEn: 'After Attack: The attack this card was played as a Reaction to gets -2/+0.'} | AO12: =IF($A12<>"", " /** 《"&$E12&"》 */ export const "&SUBSTITUTE(UPPER(IF(MID($A12, 3, 1)="-", RIGHT($A12,LEN($A12)-3), $A12)), "-", "_")&": TCardId = '"&$A12&"';", "") -> /** 《浦波嵐》 */ export const YURINA_O_S_2: TCardId = '01-yurina-o-s-2'; | AP12: =IF($A12<>"", " | '"&$A12&"'", "") -> | '01-yurina-o-s-2'
A13: 01-yurina-A1-s-2 | B13: yurina | C13: A1 | D13: 01-yurina-o-s-2 | E13: 不完全浦波嵐 | F13: ふかんぜんうらなみあらし | G13: 不完全浦波岚 | H13: 不完全浦波岚 | J13: 불완전 해안에 파랑 일며 | K13: Imperfect Uranami Storm | M13: 切札 | R13: 攻撃 | S13: 対応 | T13: 0-10 | V13: 3/- | Y13: 5 | AB13: 【攻撃後】対応した《攻撃》は-3/+0となる。 | AD13: 【攻击后】被对应的《攻击》得-3/+0。 | AF13: 【攻击后】被对应的《攻击》得-3/-0。 | AG13: 【공격후】대응한 《공격》은 -3/+0이 된다. | AH13: After Attack: The attack this card was played as a Reaction to gets -3/+0. | AN13: =IF(A13="", "", IF(ROW()>=3, ", ", "")&"'"&A13&"': {megami: '"&B13&"'"&IF(C13<>"",", anotherID: '"&C13&"', replace: '"&D13&"'","")&", name: '"&SUBSTITUTE(E13,"'","\'")&"', nameEn: '"&SUBSTITUTE(K13,"'","\'")&"', nameZh: '"&SUBSTITUTE(G13,"'","\'")&"', nameZhG1: '"&SUBSTITUTE(H13,"'","\'")&"', nameKo: '"&SUBSTITUTE(J13,"'","\'")&"', ruby: '"&F13&"', rubyEn: '"&L13&IF(I13<>"", "', rubyZh: '"&I13, "")&"', baseType: '"&VLOOKUP(M13,マスタ!$A$1:$B$99,2,0)&"'"&IF(N13="○",", extra: true","")&IF(O13<>"",", extraFrom: '"&O13&"'","")&IF(P13<>"",", exchangableTo: '"&P13&"'","")&IF(Q13="○",", poison: true","")&IF(R13<>"", ", type: '"&VLOOKUP(R13,マスタ!$D$1:$E$99,2,0)&"'", "")&IF(S13<>"",", subType: '"&VLOOKUP(S13,マスタ!$D$1:$E$99,2,0)&"'","")&IF(T13<>"",", range: '"&T13&"'","")&IF(V13<>"",", damage: '"&V13&"'","")&IF(X13<>"",", capacity: '"&X13&"'","")&IF(Y13<>"",", cost: '"&Y13&"'","")&", text: '"&SUBSTITUTE(SUBSTITUTE(AB13, CHAR(13), ""),CHAR(10),"\n")&IF(AC13<>"", "', textAdditional: '"&SUBSTITUTE(SUBSTITUTE(AC13, CHAR(13), ""),CHAR(10),"\n"), "")&"', textZh: '"&SUBSTITUTE(SUBSTITUTE(SUBSTITUTE(AD13, CHAR(13), ""),CHAR(10),"\n"),"'","\'")&"', textZhG1: '"&SUBSTITUTE(SUBSTITUTE(SUBSTITUTE(AF13, CHAR(13), ""),CHAR(10),"\n"),"'","\'")&IF(AE13<>"", "', textZhAdditional: '"&SUBSTITUTE(SUBSTITUTE(AE13, CHAR(13), ""),CHAR(10),"\n"), "")&"', textKo: '"&SUBSTITUTE(SUBSTITUTE(SUBSTITUTE(AG13, CHAR(13), ""),CHAR(10),"\n"),"'","\'")&"', textEn: '"&SUBSTITUTE(SUBSTITUTE(SUBSTITUTE(AH13, CHAR(13), ""),CHAR(10),"\n"),"'","\'")&"'"&IF(Z13="○",", sealable: true","")&IF(AA13="○",", removable: true","")&"}") -> , '01-yurina-A1-s-2': {megami: 'yurina', anotherID: 'A1', replace: '01-yurina-o-s-2', name: '不完全浦波嵐', nameEn: 'Imperfect Uranami Storm', nameZh: '不完全浦波岚', nameZhG1: '不完全浦波岚', nameKo: '불완전 해안에 파랑 일며', ruby: 'ふかんぜんうらなみあらし', rubyEn: '', baseType: 'special', type: 'attack', subType: 'reaction', range: '0-10', damage: '3/-', cost: '5', text: '【攻撃後】対応した《攻撃》は-3/+0となる。', textZh: '【攻击后】被对应的《攻击》得-3/+0。', textZhG1: '【攻击后】被对应的《攻击》得-3/-0。', textKo: '【공격후】대응한 《공격》은 -3/+0이 된다.', textEn: 'After Attack: The attack this card was played as a Reaction to gets -3/+0.'} | AO13: =IF($A13<>"", " /** 《"&$E13&"》 */ export const "&SUBSTITUTE(UPPER(IF(MID($A13, 3, 1)="-", RIGHT($A13,LEN($A13)-3), $A13)), "-", "_")&": TCardId = '"&$A13&"';", "") -> /** 《不完全浦波嵐》 */ export const YURINA_A1_S_2: TCardId = '01-yurina-A1-s-2'; | AP13: =IF($A13<>"", " | '"&$A13&"'", "") -> | '01-yurina-A1-s-2'
A14: 01-yurina-o-s-3 | B14: yurina | E14: 浮舟宿 | F14: うきふねやどし | G14: 浮舟宿 | H14: 浮舟宿 | J14: 쪽배에서 쉬노니 | K14: Ukifune Serene | M14: 切札 | R14: 行動 | Y14: 2 | AB14: ダスト→自オーラ：5 ---- 【即再起】決死-あなたのライフが3以下になる。 | AD14: 虚→5→自装 ---- 【即再起】决死～自命中的樱花结晶数小于等于3。 | AF14: 虚（5）→自装 ---- 【即再起】：决死-自命中的樱花结晶的数目小于3。 | AG14: 더스트→자신 오라：5 ---- 【즉재기】결사-당신의 라이프가 3 이하가 된다. | AH14: Shadow (5)→ Your Aura ---- Immediate Resurgence: Resolve - Your Life becomes 3 or less (from 4 or more). | AN14: =IF(A14="", "", IF(ROW()>=3, ", ", "")&"'"&A14&"': {megami: '"&B14&"'"&IF(C14<>"",", anotherID: '"&C14&"', replace: '"&D14&"'","")&", name: '"&SUBSTITUTE(E14,"'","\'")&"', nameEn: '"&SUBSTITUTE(K14,"'","\'")&"', nameZh: '"&SUBSTITUTE(G14,"'","\'")&"', nameZhG1: '"&SUBSTITUTE(H14,"'","\'")&"', nameKo: '"&SUBSTITUTE(J14,"'","\'")&"', ruby: '"&F14&"', rubyEn: '"&L14&IF(I14<>"", "', rubyZh: '"&I14, "")&"', baseType: '"&VLOOKUP(M14,マスタ!$A$1:$B$99,2,0)&"'"&IF(N14="○",", extra: true","")&IF(O14<>"",", extraFrom: '"&O14&"'","")&IF(P14<>"",", exchangableTo: '"&P14&"'","")&IF(Q14="○",", poison: true","")&IF(R14<>"", ", type: '"&VLOOKUP(R14,マスタ!$D$1:$E$99,2,0)&"'", "")&IF(S14<>"",", subType: '"&VLOOKUP(S14,マスタ!$D$1:$E$99,2,0)&"'","")&IF(T14<>"",", range: '"&T14&"'","")&IF(V14<>"",", damage: '"&V14&"'","")&IF(X14<>"",", capacity: '"&X14&"'","")&IF(Y14<>"",", cost: '"&Y14&"'","")&", text: '"&SUBSTITUTE(SUBSTITUTE(AB14, CHAR(13), ""),CHAR(10),"\n")&IF(AC14<>"", "', textAdditional: '"&SUBSTITUTE(SUBSTITUTE(AC14, CHAR(13), ""),CHAR(10),"\n"), "")&"', textZh: '"&SUBSTITUTE(SUBSTITUTE(SUBSTITUTE(AD14, CHAR(13), ""),CHAR(10),"\n"),"'","\'")&"', textZhG1: '"&SUBSTITUTE(SUBSTITUTE(SUBSTITUTE(AF14, CHAR(13), ""),CHAR(10),"\n"),"'","\'")&IF(AE14<>"", "', textZhAdditional: '"&SUBSTITUTE(SUBSTITUTE(AE14, CHAR(13), ""),CHAR(10),"\n"), "")&"', textKo: '"&SUBSTITUTE(SUBSTITUTE(SUBSTITUTE(AG14, CHAR(13), ""),CHAR(10),"\n"),"'","\'")&"', textEn: '"&SUBSTITUTE(SUBSTITUTE(SUBSTITUTE(AH14, CHAR(13), ""),CHAR(10),"\n"),"'","\'")&"'"&IF(Z14="○",", sealable: true","")&IF(AA14="○",", removable: true","")&"}") -> , '01-yurina-o-s-3': {megami: 'yurina', name: '浮舟宿', nameEn: 'Ukifune Serene', nameZh: '浮舟宿', nameZhG1: '浮舟宿', nameKo: '쪽배에서 쉬노니', ruby: 'うきふねやどし', rubyEn: '', baseType: 'special', type: 'action', cost: '2', text: 'ダスト→自オーラ：5 \n----\n【即再起】決死-あなたのライフが3以下になる。', textZh: '虚→5→自装 \n----\n【即再起】决死～自命中的樱花结晶数小于等于3。', textZhG1: '虚（5）→自装 \n----\n【即再起】：决死-自命中的樱花结晶的数目小于3。', textKo: '더스트→자신 오라：5 \n---- \n【즉재기】결사-당신의 라이프가 3 이하가 된다.', textEn: 'Shadow (5)→ Your Aura\n----\nImmediate Resurgence: Resolve - Your Life becomes 3 or less (from 4 or more).'} | AO14: =IF($A14<>"", " /** 《"&$E14&"》 */ export const "&SUBSTITUTE(UPPER(IF(MID($A14, 3, 1)="-", RIGHT($A14,LEN($A14)-3), $A14)), "-", "_")&": TCardId = '"&$A14&"';", "") -> /** 《浮舟宿》 */ export const YURINA_O_S_3: TCardId = '01-yurina-o-s-3'; | AP14: =IF($A14<>"", " | '"&$A14&"'", "") -> | '01-yurina-o-s-3'
A15: 01-yurina-o-s-4 | B15: yurina | E15: 天音揺波の底力 | F15: あまねゆりなのそこぢから | G15: 天音摇波的底力 | H15: 天音摇波的底力 | J15: 아마네 유리나의 저력 | K15: Yurina's Final Blow | M15: 切札 | R15: 攻撃 | S15: 全力 | T15: 1-4 | V15: 5/5 | Y15: 5 | AB15: 【常時】決死-あなたのライフが3以下でないと、このカードは使用できない。 | AD15: 【常时】决死～仅当自命中的樱花结晶数小于等于3时，才可以使用此牌。 | AF15: 【常时】决死-只能当自命中的樱花结晶的数目小于3时使用此牌。 | AG15: 【상시】결사-당신의 라이프가 3 이하가 아니면, 이 카드는 사용 할 수 없다. | AH15: Forced: Resolve - You can't play this card unless your Life is 3 or less. | AN15: =IF(A15="", "", IF(ROW()>=3, ", ", "")&"'"&A15&"': {megami: '"&B15&"'"&IF(C15<>"",", anotherID: '"&C15&"', replace: '"&D15&"'","")&", name: '"&SUBSTITUTE(E15,"'","\'")&"', nameEn: '"&SUBSTITUTE(K15,"'","\'")&"', nameZh: '"&SUBSTITUTE(G15,"'","\'")&"', nameZhG1: '"&SUBSTITUTE(H15,"'","\'")&"', nameKo: '"&SUBSTITUTE(J15,"'","\'")&"', ruby: '"&F15&"', rubyEn: '"&L15&IF(I15<>"", "', rubyZh: '"&I15, "")&"', baseType: '"&VLOOKUP(M15,マスタ!$A$1:$B$99,2,0)&"'"&IF(N15="○",", extra: true","")&IF(O15<>"",", extraFrom: '"&O15&"'","")&IF(P15<>"",", exchangableTo: '"&P15&"'","")&IF(Q15="○",", poison: true","")&IF(R15<>"", ", type: '"&VLOOKUP(R15,マスタ!$D$1:$E$99,2,0)&"'", "")&IF(S15<>"",", subType: '"&VLOOKUP(S15,マスタ!$D$1:$E$99,2,0)&"'","")&IF(T15<>"",", range: '"&T15&"'","")&IF(V15<>"",", damage: '"&V15&"'","")&IF(X15<>"",", capacity: '"&X15&"'","")&IF(Y15<>"",", cost: '"&Y15&"'","")&", text: '"&SUBSTITUTE(SUBSTITUTE(AB15, CHAR(13), ""),CHAR(10),"\n")&IF(AC15<>"", "', textAdditional: '"&SUBSTITUTE(SUBSTITUTE(AC15, CHAR(13), ""),CHAR(10),"\n"), "")&"', textZh: '"&SUBSTITUTE(SUBSTITUTE(SUBSTITUTE(AD15, CHAR(13), ""),CHAR(10),"\n"),"'","\'")&"', textZhG1: '"&SUBSTITUTE(SUBSTITUTE(SUBSTITUTE(AF15, CHAR(13), ""),CHAR(10),"\n"),"'","\'")&IF(AE15<>"", "', textZhAdditional: '"&SUBSTITUTE(SUBSTITUTE(AE15, CHAR(13), ""),CHAR(10),"\n"), "")&"', textKo: '"&SUBSTITUTE(SUBSTITUTE(SUBSTITUTE(AG15, CHAR(13), ""),CHAR(10),"\n"),"'","\'")&"', textEn: '"&SUBSTITUTE(SUBSTITUTE(SUBSTITUTE(AH15, CHAR(13), ""),CHAR(10),"\n"),"'","\'")&"'"&IF(Z15="○",", sealable: true","")&IF(AA15="○",", removable: true","")&"}") -> , '01-yurina-o-s-4': {megami: 'yurina', name: '天音揺波の底力', nameEn: 'Yurina\'s Final Blow', nameZh: '天音摇波的底力', nameZhG1: '天音摇波的底力', nameKo: '아마네 유리나의 저력', ruby: 'あまねゆりなのそこぢから', rubyEn: '', baseType: 'special', type: 'attack', subType: 'fullpower', range: '1-4', damage: '5/5', cost: '5', text: '【常時】決死-あなたのライフが3以下でないと、このカードは使用できない。', textZh: '【常时】决死～仅当自命中的樱花结晶数小于等于3时，才可以使用此牌。', textZhG1: '【常时】决死-只能当自命中的樱花结晶的数目小于3时使用此牌。', textKo: '【상시】결사-당신의 라이프가 3 이하가 아니면, 이 카드는 사용 할 수 없다.', textEn: 'Forced: Resolve - You can\'t play this card unless your Life is 3 or less.'} | AO15: =IF($A15<>"", " /** 《"&$E15&"》 */ export const "&SUBSTITUTE(UPPER(IF(MID($A15, 3, 1)="-", RIGHT($A15,LEN($A15)-3), $A15)), "-", "_")&": TCardId = '"&$A15&"';", "") -> /** 《天音揺波の底力》 */ export const YURINA_O_S_4: TCardId = '01-yurina-o-s-4'; | AP15: =IF($A15<>"", " | '"&$A15&"'", "") -> | '01-yurina-o-s-4'
AN16: =IF(A16="", "", IF(ROW()>=3, ", ", "")&"'"&A16&"': {megami: '"&B16&"'"&IF(C16<>"",", anotherID: '"&C16&"', replace: '"&D16&"'","")&", name: '"&SUBSTITUTE(E16,"'","\'")&"', nameEn: '"&SUBSTITUTE(K16,"'","\'")&"', nameZh: '"&SUBSTITUTE(G16,"'","\'")&"', nameZhG1: '"&SUBSTITUTE(H16,"'","\'")&"', nameKo: '"&SUBSTITUTE(J16,"'","\'")&"', ruby: '"&F16&"', rubyEn: '"&L16&IF(I16<>"", "', rubyZh: '"&I16, "")&"', baseType: '"&VLOOKUP(M16,マスタ!$A$1:$B$99,2,0)&"'"&IF(N16="○",", extra: true","")&IF(O16<>"",", extraFrom: '"&O16&"'","")&IF(P16<>"",", exchangableTo: '"&P16&"'","")&IF(Q16="○",", poison: true","")&IF(R16<>"", ", type: '"&VLOOKUP(R16,マスタ!$D$1:$E$99,2,0)&"'", "")&IF(S16<>"",", subType: '"&VLOOKUP(S16,マスタ!$D$1:$E$99,2,0)&"'","")&IF(T16<>"",", range: '"&T16&"'","")&IF(V16<>"",", damage: '"&V16&"'","")&IF(X16<>"",", capacity: '"&X16&"'","")&IF(Y16<>"",", cost: '"&Y16&"'","")&", text: '"&SUBSTITUTE(SUBSTITUTE(AB16, CHAR(13), ""),CHAR(10),"\n")&IF(AC16<>"", "', textAdditional: '"&SUBSTITUTE(SUBSTITUTE(AC16, CHAR(13), ""),CHAR(10),"\n"), "")&"', textZh: '"&SUBSTITUTE(SUBSTITUTE(SUBSTITUTE(AD16, CHAR(13), ""),CHAR(10),"\n"),"'","\'")&"', textZhG1: '"&SUBSTITUTE(SUBSTITUTE(SUBSTITUTE(AF16, CHAR(13), ""),CHAR(10),"\n"),"'","\'")&IF(AE16<>"", "', textZhAdditional: '"&SUBSTITUTE(SUBSTITUTE(AE16, CHAR(13), ""),CHAR(10),"\n"), "")&"', textKo: '"&SUBSTITUTE(SUBSTITUTE(SUBSTITUTE(AG16, CHAR(13), ""),CHAR(10),"\n"),"'","\'")&"', textEn: '"&SUBSTITUTE(SUBSTITUTE(SUBSTITUTE(AH16, CHAR(13), ""),CHAR(10),"\n"),"'","\'")&"'"&IF(Z16="○",", sealable: true","")&IF(AA16="○",", removable: true","")&"}") | AO16: =IF($A16<>"", " /** 《"&$E16&"》 */ export const "&SUBSTITUTE(UPPER(IF(MID($A16, 3, 1)="-", RIGHT($A16,LEN($A16)-3), $A16)), "-", "_")&": TCardId = '"&$A16&"';", "") | AP16: =IF($A16<>"", " | '"&$A16&"'", "")
A17: 02-saine-o-n-1 | B17: saine | E17: 八方振り | F17: はっぽうぶり | G17: 八方斩 | H17: 八面斩 | J17: 팔방 휘두르기 | K17: Swing Rush | M17: 通常札 | R17: 攻撃 | T17: 4-5 | V17: 2/1 | AB17: 【攻撃後】八相-あなたのオーラが0ならば、攻撃『適正距離4-5、2/1』を行う。 | AD17: 【攻击后】八相～若自装中没有樱花结晶，则进行一次“攻击距离4-5、伤害2/1”的攻击。 | AF17: 【攻击后】八相-若自装中没有樱花结晶，则进行一次“攻击距离4-5 伤害2/1”的攻击。 | AG17: 【공격후】팔상-당신의 오라가 0이라면, 공격『적정거리4-5、2/1』을 행한다. | AH17: After Attack: Idea - You attack with "Range: 4-5, Damage: 2/1" if you have no Sakura tokens on your Aura. | AN17: =IF(A17="", "", IF(ROW()>=3, ", ", "")&"'"&A17&"': {megami: '"&B17&"'"&IF(C17<>"",", anotherID: '"&C17&"', replace: '"&D17&"'","")&", name: '"&SUBSTITUTE(E17,"'","\'")&"', nameEn: '"&SUBSTITUTE(K17,"'","\'")&"', nameZh: '"&SUBSTITUTE(G17,"'","\'")&"', nameZhG1: '"&SUBSTITUTE(H17,"'","\'")&"', nameKo: '"&SUBSTITUTE(J17,"'","\'")&"', ruby: '"&F17&"', rubyEn: '"&L17&IF(I17<>"", "', rubyZh: '"&I17, "")&"', baseType: '"&VLOOKUP(M17,マスタ!$A$1:$B$99,2,0)&"'"&IF(N17="○",", extra: true","")&IF(O17<>"",", extraFrom: '"&O17&"'","")&IF(P17<>"",", exchangableTo: '"&P17&"'","")&IF(Q17="○",", poison: true","")&IF(R17<>"", ", type: '"&VLOOKUP(R17,マスタ!$D$1:$E$99,2,0)&"'", "")&IF(S17<>"",", subType: '"&VLOOKUP(S17,マスタ!$D$1:$E$99,2,0)&"'","")&IF(T17<>"",", range: '"&T17&"'","")&IF(V17<>"",", damage: '"&V17&"'","")&IF(X17<>"",", capacity: '"&X17&"'","")&IF(Y17<>"",", cost: '"&Y17&"'","")&", text: '"&SUBSTITUTE(SUBSTITUTE(AB17, CHAR(13), ""),CHAR(10),"\n")&IF(AC17<>"", "', textAdditional: '"&SUBSTITUTE(SUBSTITUTE(AC17, CHAR(13), ""),CHAR(10),"\n"), "")&"', textZh: '"&SUBSTITUTE(SUBSTITUTE(SUBSTITUTE(AD17, CHAR(13), ""),CHAR(10),"\n"),"'","\'")&"', textZhG1: '"&SUBSTITUTE(SUBSTITUTE(SUBSTITUTE(AF17, CHAR(13), ""),CHAR(10),"\n"),"'","\'")&IF(AE17<>"", "', textZhAdditional: '"&SUBSTITUTE(SUBSTITUTE(AE17, CHAR(13), ""),CHAR(10),"\n"), "")&"', textKo: '"&SUBSTITUTE(SUBSTITUTE(SUBSTITUTE(AG17, CHAR(13), ""),CHAR(10),"\n"),"'","\'")&"', textEn: '"&SUBSTITUTE(SUBSTITUTE(SUBSTITUTE(AH17, CHAR(13), ""),CHAR(10),"\n"),"'","\'")&"'"&IF(Z17="○",", sealable: true","")&IF(AA17="○",", removable: true","")&"}") -> , '02-saine-o-n-1': {megami: 'saine', name: '八方振り', nameEn: 'Swing Rush', nameZh: '八方斩', nameZhG1: '八面斩', nameKo: '팔방 휘두르기', ruby: 'はっぽうぶり', rubyEn: '', baseType: 'normal', type: 'attack', range: '4-5', damage: '2/1', text: '【攻撃後】八相-あなたのオーラが0ならば、攻撃『適正距離4-5、2/1』を行う。', textZh: '【攻击后】八相～若自装中没有樱花结晶，则进行一次“攻击距离4-5、伤害2/1”的攻击。', textZhG1: '【攻击后】八相-若自装中没有樱花结晶，则进行一次“攻击距离4-5 伤害2/1”的攻击。', textKo: '【공격후】팔상-당신의 오라가 0이라면, 공격『적정거리4-5、2/1』을 행한다.', textEn: 'After Attack: Idea - You attack with "Range: 4-5, Damage: 2/1" if you have no Sakura tokens on your Aura.'} | AO17: =IF($A17<>"", " /** 《"&$E17&"》 */ export const "&SUBSTITUTE(UPPER(IF(MID($A17, 3, 1)="-", RIGHT($A17,LEN($A17)-3), $A17)), "-", "_")&": TCardId = '"&$A17&"';", "") -> /** 《八方振り》 */ export const SAINE_O_N_1: TCardId = '02-saine-o-n-1'; | AP17: =IF($A17<>"", " | '"&$A17&"'", "") -> | '02-saine-o-n-1'
A18: 02-saine-o-n-2 | B18: saine | E18: 薙斬り | F18: なぎぎり | G18: 薙刀斩 | H18: 薙刀斩 | J18: 후려베기 | K18: Cut Down | M18: 通常札 | R18: 攻撃 | S18: 対応 | T18: 4-5 | V18: 3/1 | AN18: =IF(A18="", "", IF(ROW()>=3, ", ", "")&"'"&A18&"': {megami: '"&B18&"'"&IF(C18<>"",", anotherID: '"&C18&"', replace: '"&D18&"'","")&", name: '"&SUBSTITUTE(E18,"'","\'")&"', nameEn: '"&SUBSTITUTE(K18,"'","\'")&"', nameZh: '"&SUBSTITUTE(G18,"'","\'")&"', nameZhG1: '"&SUBSTITUTE(H18,"'","\'")&"', nameKo: '"&SUBSTITUTE(J18,"'","\'")&"', ruby: '"&F18&"', rubyEn: '"&L18&IF(I18<>"", "', rubyZh: '"&I18, "")&"', baseType: '"&VLOOKUP(M18,マスタ!$A$1:$B$99,2,0)&"'"&IF(N18="○",", extra: true","")&IF(O18<>"",", extraFrom: '"&O18&"'","")&IF(P18<>"",", exchangableTo: '"&P18&"'","")&IF(Q18="○",", poison: true","")&IF(R18<>"", ", type: '"&VLOOKUP(R18,マスタ!$D$1:$E$99,2,0)&"'", "")&IF(S18<>"",", subType: '"&VLOOKUP(S18,マスタ!$D$1:$E$99,2,0)&"'","")&IF(T18<>"",", range: '"&T18&"'","")&IF(V18<>"",", damage: '"&V18&"'","")&IF(X18<>"",", capacity: '"&X18&"'","")&IF(Y18<>"",", cost: '"&Y18&"'","")&", text: '"&SUBSTITUTE(SUBSTITUTE(AB18, CHAR(13), ""),CHAR(10),"\n")&IF(AC18<>"", "', textAdditional: '"&SUBSTITUTE(SUBSTITUTE(AC18, CHAR(13), ""),CHAR(10),"\n"), "")&"', textZh: '"&SUBSTITUTE(SUBSTITUTE(SUBSTITUTE(AD18, CHAR(13), ""),CHAR(10),"\n"),"'","\'")&"', textZhG1: '"&SUBSTITUTE(SUBSTITUTE(SUBSTITUTE(AF18, CHAR(13), ""),CHAR(10),"\n"),"'","\'")&IF(AE18<>"", "', textZhAdditional: '"&SUBSTITUTE(SUBSTITUTE(AE18, CHAR(13), ""),CHAR(10),"\n"), "")&"', textKo: '"&SUBSTITUTE(SUBSTITUTE(SUBSTITUTE(AG18, CHAR(13), ""),CHAR(10),"\n"),"'","\'")&"', textEn: '"&SUBSTITUTE(SUBSTITUTE(SUBSTITUTE(AH18, CHAR(13), ""),CHAR(10),"\n"),"'","\'")&"'"&IF(Z18="○",", sealable: true","")&IF(AA18="○",", removable: true","")&"}") -> , '02-saine-o-n-2': {megami: 'saine', name: '薙斬り', nameEn: 'Cut Down', nameZh: '薙刀斩', nameZhG1: '薙刀斩', nameKo: '후려베기', ruby: 'なぎぎり', rubyEn: '', baseType: 'normal', type: 'attack', subType: 'reaction', range: '4-5', damage: '3/1', text: '', textZh: '', textZhG1: '', textKo: '', textEn: ''} | AO18: =IF($A18<>"", " /** 《"&$E18&"》 */ export const "&SUBSTITUTE(UPPER(IF(MID($A18, 3, 1)="-", RIGHT($A18,LEN($A18)-3), $A18)), "-", "_")&": TCardId = '"&$A18&"';", "") -> /** 《薙斬り》 */ export const SAINE_O_N_2: TCardId = '02-saine-o-n-2'; | AP18: =IF($A18<>"", " | '"&$A18&"'", "") -> | '02-saine-o-n-2'
A19: 02-saine-o-n-3 | B19: saine | E19: 返し刃 | F19: かえしやいば | G19: 回马斩 | H19: 反身斩 | J19: 칼날 반환 | K19: Cut In | M19: 通常札 | R19: 攻撃 | S19: 対応 | T19: 3-5 | V19: 1/1 | AB19: 【攻撃後】このカードを対応で使用したならば、攻撃『適正距離3-5、2/1、対応不可』を行う。 | AD19: 【攻击后】若此牌作为对应使用，则进行一次“攻击距离3-5、伤害2/1、不可被对应”的攻击。 | AF19: 【攻击后】若此牌作为对应使用，则进行一次“攻击距离3-5 伤害2/1 不可被对应”的攻击。 | AG19: 【공격후】이 카드를 대응으로 사용했다면, 공격『적정거리3-5、2/1、대응불가』를 행한다. | AH19: After Attack: If this card was played as a Reaction, you attack with "Range: 3-5, Damage: 2/1, No Reactions". | AN19: =IF(A19="", "", IF(ROW()>=3, ", ", "")&"'"&A19&"': {megami: '"&B19&"'"&IF(C19<>"",", anotherID: '"&C19&"', replace: '"&D19&"'","")&", name: '"&SUBSTITUTE(E19,"'","\'")&"', nameEn: '"&SUBSTITUTE(K19,"'","\'")&"', nameZh: '"&SUBSTITUTE(G19,"'","\'")&"', nameZhG1: '"&SUBSTITUTE(H19,"'","\'")&"', nameKo: '"&SUBSTITUTE(J19,"'","\'")&"', ruby: '"&F19&"', rubyEn: '"&L19&IF(I19<>"", "', rubyZh: '"&I19, "")&"', baseType: '"&VLOOKUP(M19,マスタ!$A$1:$B$99,2,0)&"'"&IF(N19="○",", extra: true","")&IF(O19<>"",", extraFrom: '"&O19&"'","")&IF(P19<>"",", exchangableTo: '"&P19&"'","")&IF(Q19="○",", poison: true","")&IF(R19<>"", ", type: '"&VLOOKUP(R19,マスタ!$D$1:$E$99,2,0)&"'", "")&IF(S19<>"",", subType: '"&VLOOKUP(S19,マスタ!$D$1:$E$99,2,0)&"'","")&IF(T19<>"",", range: '"&T19&"'","")&IF(V19<>"",", damage: '"&V19&"'","")&IF(X19<>"",", capacity: '"&X19&"'","")&IF(Y19<>"",", cost: '"&Y19&"'","")&", text: '"&SUBSTITUTE(SUBSTITUTE(AB19, CHAR(13), ""),CHAR(10),"\n")&IF(AC19<>"", "', textAdditional: '"&SUBSTITUTE(SUBSTITUTE(AC19, CHAR(13), ""),CHAR(10),"\n"), "")&"', textZh: '"&SUBSTITUTE(SUBSTITUTE(SUBSTITUTE(AD19, CHAR(13), ""),CHAR(10),"\n"),"'","\'")&"', textZhG1: '"&SUBSTITUTE(SUBSTITUTE(SUBSTITUTE(AF19, CHAR(13), ""),CHAR(10),"\n"),"'","\'")&IF(AE19<>"", "', textZhAdditional: '"&SUBSTITUTE(SUBSTITUTE(AE19, CHAR(13), ""),CHAR(10),"\n"), "")&"', textKo: '"&SUBSTITUTE(SUBSTITUTE(SUBSTITUTE(AG19, CHAR(13), ""),CHAR(10),"\n"),"'","\'")&"', textEn: '"&SUBSTITUTE(SUBSTITUTE(SUBSTITUTE(AH19, CHAR(13), ""),CHAR(10),"\n"),"'","\'")&"'"&IF(Z19="○",", sealable: true","")&IF(AA19="○",", removable: true","")&"}") -> , '02-saine-o-n-3': {megami: 'saine', name: '返し刃', nameEn: 'Cut In', nameZh: '回马斩', nameZhG1: '反身斩', nameKo: '칼날 반환', ruby: 'かえしやいば', rubyEn: '', baseType: 'normal', type: 'attack', subType: 'reaction', range: '3-5', damage: '1/1', text: '【攻撃後】このカードを対応で使用したならば、攻撃『適正距離3-5、2/1、対応不可』を行う。', textZh: '【攻击后】若此牌作为对应使用，则进行一次“攻击距离3-5、伤害2/1、不可被对应”的攻击。', textZhG1: '【攻击后】若此牌作为对应使用，则进行一次“攻击距离3-5 伤害2/1 不可被对应”的攻击。', textKo: '【공격후】이 카드를 대응으로 사용했다면, 공격『적정거리3-5、2/1、대응불가』를 행한다.', textEn: 'After Attack: If this card was played as a Reaction, you attack with "Range: 3-5, Damage: 2/1, No Reactions".'} | AO19: =IF($A19<>"", " /** 《"&$E19&"》 */ export const "&SUBSTITUTE(UPPER(IF(MID($A19, 3, 1)="-", RIGHT($A19,LEN($A19)-3), $A19)), "-", "_")&": TCardId = '"&$A19&"';", "") -> /** 《返し刃》 */ export const SAINE_O_N_3: TCardId = '02-saine-o-n-3'; | AP19: =IF($A19<>"", " | '"&$A19&"'", "") -> | '02-saine-o-n-3'
A20: 02-saine-A1-n-3 | B20: saine | C20: A1 | D20: 02-saine-o-n-3 | E20: 氷の音 | F20: ひのね | G20: 冰之音 | H20: 冰之音 | J20: 얼음의 소리 | K20: Sound of Ice | M20: 通常札 | R20: 行動 | S20: 対応 | AB20: 相オーラ→ダスト：1 このカードを対応で使用したならば、さらに 相オーラ→ダスト：1 | AD20: 敌装→1→虚 若此牌作为《对应》使用，则：敌装→1→虚 | AF20: 敌装（1）→虚 若此牌作为《对应》使用，则敌装（1）→虚。 | AG20: 상대 오라→더스트：1 이 카드를 대응으로 사용했다면, 추가로 상대 오라→더스트：1 | AH20: Opponent's Aura (1)→ Shadow If this card was played as a Reaction: Opponent's Aura (1)→ Shadow (again) | AN20: =IF(A20="", "", IF(ROW()>=3, ", ", "")&"'"&A20&"': {megami: '"&B20&"'"&IF(C20<>"",", anotherID: '"&C20&"', replace: '"&D20&"'","")&", name: '"&SUBSTITUTE(E20,"'","\'")&"', nameEn: '"&SUBSTITUTE(K20,"'","\'")&"', nameZh: '"&SUBSTITUTE(G20,"'","\'")&"', nameZhG1: '"&SUBSTITUTE(H20,"'","\'")&"', nameKo: '"&SUBSTITUTE(J20,"'","\'")&"', ruby: '"&F20&"', rubyEn: '"&L20&IF(I20<>"", "', rubyZh: '"&I20, "")&"', baseType: '"&VLOOKUP(M20,マスタ!$A$1:$B$99,2,0)&"'"&IF(N20="○",", extra: true","")&IF(O20<>"",", extraFrom: '"&O20&"'","")&IF(P20<>"",", exchangableTo: '"&P20&"'","")&IF(Q20="○",", poison: true","")&IF(R20<>"", ", type: '"&VLOOKUP(R20,マスタ!$D$1:$E$99,2,0)&"'", "")&IF(S20<>"",", subType: '"&VLOOKUP(S20,マスタ!$D$1:$E$99,2,0)&"'","")&IF(T20<>"",", range: '"&T20&"'","")&IF(V20<>"",", damage: '"&V20&"'","")&IF(X20<>"",", capacity: '"&X20&"'","")&IF(Y20<>"",", cost: '"&Y20&"'","")&", text: '"&SUBSTITUTE(SUBSTITUTE(AB20, CHAR(13), ""),CHAR(10),"\n")&IF(AC20<>"", "', textAdditional: '"&SUBSTITUTE(SUBSTITUTE(AC20, CHAR(13), ""),CHAR(10),"\n"), "")&"', textZh: '"&SUBSTITUTE(SUBSTITUTE(SUBSTITUTE(AD20, CHAR(13), ""),CHAR(10),"\n"),"'","\'")&"', textZhG1: '"&SUBSTITUTE(SUBSTITUTE(SUBSTITUTE(AF20, CHAR(13), ""),CHAR(10),"\n"),"'","\'")&IF(AE20<>"", "', textZhAdditional: '"&SUBSTITUTE(SUBSTITUTE(AE20, CHAR(13), ""),CHAR(10),"\n"), "")&"', textKo: '"&SUBSTITUTE(SUBSTITUTE(SUBSTITUTE(AG20, CHAR(13), ""),CHAR(10),"\n"),"'","\'")&"', textEn: '"&SUBSTITUTE(SUBSTITUTE(SUBSTITUTE(AH20, CHAR(13), ""),CHAR(10),"\n"),"'","\'")&"'"&IF(Z20="○",", sealable: true","")&IF(AA20="○",", removable: true","")&"}") -> , '02-saine-A1-n-3': {megami: 'saine', anotherID: 'A1', replace: '02-saine-o-n-3', name: '氷の音', nameEn: 'Sound of Ice', nameZh: '冰之音', nameZhG1: '冰之音', nameKo: '얼음의 소리', ruby: 'ひのね', rubyEn: '', baseType: 'normal', type: 'action', subType: 'reaction', text: '相オーラ→ダスト：1\nこのカードを対応で使用したならば、さらに\n相オーラ→ダスト：1', textZh: '敌装→1→虚\n若此牌作为《对应》使用，则：敌装→1→虚', textZhG1: '敌装（1）→虚\n若此牌作为《对应》使用，则敌装（1）→虚。', textKo: '상대 오라→더스트：1 \n이 카드를 대응으로 사용했다면, 추가로 \n상대 오라→더스트：1', textEn: 'Opponent\'s Aura (1)→ Shadow\nIf this card was played as a Reaction:\nOpponent\'s Aura (1)→ Shadow (again)'} | AO20: =IF($A20<>"", " /** 《"&$E20&"》 */ export const "&SUBSTITUTE(UPPER(IF(MID($A20, 3, 1)="-", RIGHT($A20,LEN($A20)-3), $A20)), "-", "_")&": TCardId = '"&$A20&"';", "") -> /** 《氷の音》 */ export const SAINE_A1_N_3: TCardId = '02-saine-A1-n-3'; | AP20: =IF($A20<>"", " | '"&$A20&"'", "") -> | '02-saine-A1-n-3'
A21: 02-saine-o-n-4 | B21: saine | E21: 見切り | F21: みきり | G21: 识破 | H21: 识破 | J21: 간파 | K21: Outclass | M21: 通常札 | R21: 行動 | AB21: 【常時】八相-あなたのオーラが0ならば、このカードを《対応》を持つかのように相手の《攻撃》に割り込んで使用できる。 間合⇔ダスト：1 | AD21: 【常时】八相～若自装中没有樱花结晶，则此牌可以如《对应》牌一样对应《攻击》使用。 距↔1↔虚 | AF21: 【常时】八相-若自装中没有樱花结晶，则此牌额外具有《对应》副类别。 距（1） ⇔ 虚 | AG21: 【상시】팔상-당신의 오라가 0이라면, 이 카드를 《대응》을 갖는것과 같이 상대의 《공격》 에 끼어들어 사용 가능하다. 간격⇔더스트：1 | AH21: Forced: Idea - You may play this card as if it were a Reaction if you have no Sakura tokens on your Aura. Distance (1)⇔ Shadow | AN21: =IF(A21="", "", IF(ROW()>=3, ", ", "")&"'"&A21&"': {megami: '"&B21&"'"&IF(C21<>"",", anotherID: '"&C21&"', replace: '"&D21&"'","")&", name: '"&SUBSTITUTE(E21,"'","\'")&"', nameEn: '"&SUBSTITUTE(K21,"'","\'")&"', nameZh: '"&SUBSTITUTE(G21,"'","\'")&"', nameZhG1: '"&SUBSTITUTE(H21,"'","\'")&"', nameKo: '"&SUBSTITUTE(J21,"'","\'")&"', ruby: '"&F21&"', rubyEn: '"&L21&IF(I21<>"", "', rubyZh: '"&I21, "")&"', baseType: '"&VLOOKUP(M21,マスタ!$A$1:$B$99,2,0)&"'"&IF(N21="○",", extra: true","")&IF(O21<>"",", extraFrom: '"&O21&"'","")&IF(P21<>"",", exchangableTo: '"&P21&"'","")&IF(Q21="○",", poison: true","")&IF(R21<>"", ", type: '"&VLOOKUP(R21,マスタ!$D$1:$E$99,2,0)&"'", "")&IF(S21<>"",", subType: '"&VLOOKUP(S21,マスタ!$D$1:$E$99,2,0)&"'","")&IF(T21<>"",", range: '"&T21&"'","")&IF(V21<>"",", damage: '"&V21&"'","")&IF(X21<>"",", capacity: '"&X21&"'","")&IF(Y21<>"",", cost: '"&Y21&"'","")&", text: '"&SUBSTITUTE(SUBSTITUTE(AB21, CHAR(13), ""),CHAR(10),"\n")&IF(AC21<>"", "', textAdditional: '"&SUBSTITUTE(SUBSTITUTE(AC21, CHAR(13), ""),CHAR(10),"\n"), "")&"', textZh: '"&SUBSTITUTE(SUBSTITUTE(SUBSTITUTE(AD21, CHAR(13), ""),CHAR(10),"\n"),"'","\'")&"', textZhG1: '"&SUBSTITUTE(SUBSTITUTE(SUBSTITUTE(AF21, CHAR(13), ""),CHAR(10),"\n"),"'","\'")&IF(AE21<>"", "', textZhAdditional: '"&SUBSTITUTE(SUBSTITUTE(AE21, CHAR(13), ""),CHAR(10),"\n"), "")&"', textKo: '"&SUBSTITUTE(SUBSTITUTE(SUBSTITUTE(AG21, CHAR(13), ""),CHAR(10),"\n"),"'","\'")&"', textEn: '"&SUBSTITUTE(SUBSTITUTE(SUBSTITUTE(AH21, CHAR(13), ""),CHAR(10),"\n"),"'","\'")&"'"&IF(Z21="○",", sealable: true","")&IF(AA21="○",", removable: true","")&"}") -> , '02-saine-o-n-4': {megami: 'saine', name: '見切り', nameEn: 'Outclass', nameZh: '识破', nameZhG1: '识破', nameKo: '간파', ruby: 'みきり', rubyEn: '', baseType: 'normal', type: 'action', text: '【常時】八相-あなたのオーラが0ならば、このカードを《対応》を持つかのように相手の《攻撃》に割り込んで使用できる。\n間合⇔ダスト：1', textZh: '【常时】八相～若自装中没有樱花结晶，则此牌可以如《对应》牌一样对应《攻击》使用。\n距↔1↔虚', textZhG1: '【常时】八相-若自装中没有樱花结晶，则此牌额外具有《对应》副类别。\n距（1） ⇔ 虚', textKo: '【상시】팔상-당신의 오라가 0이라면, 이 카드를 《대응》을 갖는것과 같이 상대의 《공격》 에 끼어들어 사용 가능하다. \n간격⇔더스트：1', textEn: 'Forced: Idea - You may play this card as if it were a Reaction if you have no Sakura tokens on your Aura.\n\nDistance (1)⇔ Shadow'} | AO21: =IF($A21<>"", " /** 《"&$E21&"》 */ export const "&SUBSTITUTE(UPPER(IF(MID($A21, 3, 1)="-", RIGHT($A21,LEN($A21)-3), $A21)), "-", "_")&": TCardId = '"&$A21&"';", "") -> /** 《見切り》 */ export const SAINE_O_N_4: TCardId = '02-saine-o-n-4'; | AP21: =IF($A21<>"", " | '"&$A21&"'", "") -> | '02-saine-o-n-4'
A22: 02-saine-o-n-5 | B22: saine | E22: 圏域 | F22: けんいき | G22: 圈域 | H22: 圈域 | J22: 권역 | K22: Space for Master | M22: 通常札 | R22: 付与 | X22: 3 | AB22: 【展開時】ダスト→間合：1 【展開中】達人の間合は2大きくなる。 | AD22: 【展开时】虚→1→距 【展开中】达人距离的值增大2。 | AF22: 【展开时】虚（1）→距 【展开中】达人距离的值增大2。 | AG22: 【전개시】더스트→간격：1 【전개중】달인의 간격은 2 크게 된다. | AH22: Initialize: Shadow (1)→ Distance. Ongoing: Increase the size of the Mastery Zone by 2. | AN22: =IF(A22="", "", IF(ROW()>=3, ", ", "")&"'"&A22&"': {megami: '"&B22&"'"&IF(C22<>"",", anotherID: '"&C22&"', replace: '"&D22&"'","")&", name: '"&SUBSTITUTE(E22,"'","\'")&"', nameEn: '"&SUBSTITUTE(K22,"'","\'")&"', nameZh: '"&SUBSTITUTE(G22,"'","\'")&"', nameZhG1: '"&SUBSTITUTE(H22,"'","\'")&"', nameKo: '"&SUBSTITUTE(J22,"'","\'")&"', ruby: '"&F22&"', rubyEn: '"&L22&IF(I22<>"", "', rubyZh: '"&I22, "")&"', baseType: '"&VLOOKUP(M22,マスタ!$A$1:$B$99,2,0)&"'"&IF(N22="○",", extra: true","")&IF(O22<>"",", extraFrom: '"&O22&"'","")&IF(P22<>"",", exchangableTo: '"&P22&"'","")&IF(Q22="○",", poison: true","")&IF(R22<>"", ", type: '"&VLOOKUP(R22,マスタ!$D$1:$E$99,2,0)&"'", "")&IF(S22<>"",", subType: '"&VLOOKUP(S22,マスタ!$D$1:$E$99,2,0)&"'","")&IF(T22<>"",", range: '"&T22&"'","")&IF(V22<>"",", damage: '"&V22&"'","")&IF(X22<>"",", capacity: '"&X22&"'","")&IF(Y22<>"",", cost: '"&Y22&"'","")&", text: '"&SUBSTITUTE(SUBSTITUTE(AB22, CHAR(13), ""),CHAR(10),"\n")&IF(AC22<>"", "', textAdditional: '"&SUBSTITUTE(SUBSTITUTE(AC22, CHAR(13), ""),CHAR(10),"\n"), "")&"', textZh: '"&SUBSTITUTE(SUBSTITUTE(SUBSTITUTE(AD22, CHAR(13), ""),CHAR(10),"\n"),"'","\'")&"', textZhG1: '"&SUBSTITUTE(SUBSTITUTE(SUBSTITUTE(AF22, CHAR(13), ""),CHAR(10),"\n"),"'","\'")&IF(AE22<>"", "', textZhAdditional: '"&SUBSTITUTE(SUBSTITUTE(AE22, CHAR(13), ""),CHAR(10),"\n"), "")&"', textKo: '"&SUBSTITUTE(SUBSTITUTE(SUBSTITUTE(AG22, CHAR(13), ""),CHAR(10),"\n"),"'","\'")&"', textEn: '"&SUBSTITUTE(SUBSTITUTE(SUBSTITUTE(AH22, CHAR(13), ""),CHAR(10),"\n"),"'","\'")&"'"&IF(Z22="○",", sealable: true","")&IF(AA22="○",", removable: true","")&"}") -> , '02-saine-o-n-5': {megami: 'saine', name: '圏域', nameEn: 'Space for Master', nameZh: '圈域', nameZhG1: '圈域', nameKo: '권역', ruby: 'けんいき', rubyEn: '', baseType: 'normal', type: 'enhance', capacity: '3', text: '【展開時】ダスト→間合：1\n【展開中】達人の間合は2大きくなる。', textZh: '【展开时】虚→1→距 \n【展开中】达人距离的值增大2。', textZhG1: '【展开时】虚（1）→距 \n【展开中】达人距离的值增大2。', textKo: '【전개시】더스트→간격：1 \n【전개중】달인의 간격은 2 크게 된다. ', textEn: 'Initialize: Shadow (1)→ Distance.\n\nOngoing: Increase the size of the Mastery Zone by 2.'} | AO22: =IF($A22<>"", " /** 《"&$E22&"》 */ export const "&SUBSTITUTE(UPPER(IF(MID($A22, 3, 1)="-", RIGHT($A22,LEN($A22)-3), $A22)), "-", "_")&": TCardId = '"&$A22&"';", "") -> /** 《圏域》 */ export const SAINE_O_N_5: TCardId = '02-saine-o-n-5'; | AP22: =IF($A22<>"", " | '"&$A22&"'", "") -> | '02-saine-o-n-5'
A23: 02-saine-o-n-6 | B23: saine | E23: 衝音晶 | F23: しょうおんしょう | G23: 冲音晶 | H23: 冲音晶 | J23: 충음정 | K23: Wavering Crystal | M23: 通常札 | R23: 付与 | S23: 対応 | X23: 1 | AB23: 【展開時】対応した《攻撃》は-1/+0となる。 【破棄時】攻撃『適正距離0-10、1/-、対応不可』を行う。 | AD23: 【展开时】被对应的《攻击》得-1/+0。 【破弃时】进行一次“攻击距离0-10、伤害1/-、不可被对应”的攻击。 | AF23: 【展开时】被对应的《攻击》得-1/-0 。 【破弃时】进行一次“攻击距离0-10 伤害1/- 不可被对应”的攻击。 | AG23: 【전개시】대응한 《공격》은 -1/+0이 된다. 【파기시】공격『적정거리0-10、1/-、대응불가』를 행한다. | AH23: Initialize: The attack you played this card as a Reaction to gets -1/+0. Disenchant: You attack with "Range: 0-10, Damage: 1/-, No Reactions". | AN23: =IF(A23="", "", IF(ROW()>=3, ", ", "")&"'"&A23&"': {megami: '"&B23&"'"&IF(C23<>"",", anotherID: '"&C23&"', replace: '"&D23&"'","")&", name: '"&SUBSTITUTE(E23,"'","\'")&"', nameEn: '"&SUBSTITUTE(K23,"'","\'")&"', nameZh: '"&SUBSTITUTE(G23,"'","\'")&"', nameZhG1: '"&SUBSTITUTE(H23,"'","\'")&"', nameKo: '"&SUBSTITUTE(J23,"'","\'")&"', ruby: '"&F23&"', rubyEn: '"&L23&IF(I23<>"", "', rubyZh: '"&I23, "")&"', baseType: '"&VLOOKUP(M23,マスタ!$A$1:$B$99,2,0)&"'"&IF(N23="○",", extra: true","")&IF(O23<>"",", extraFrom: '"&O23&"'","")&IF(P23<>"",", exchangableTo: '"&P23&"'","")&IF(Q23="○",", poison: true","")&IF(R23<>"", ", type: '"&VLOOKUP(R23,マスタ!$D$1:$E$99,2,0)&"'", "")&IF(S23<>"",", subType: '"&VLOOKUP(S23,マスタ!$D$1:$E$99,2,0)&"'","")&IF(T23<>"",", range: '"&T23&"'","")&IF(V23<>"",", damage: '"&V23&"'","")&IF(X23<>"",", capacity: '"&X23&"'","")&IF(Y23<>"",", cost: '"&Y23&"'","")&", text: '"&SUBSTITUTE(SUBSTITUTE(AB23, CHAR(13), ""),CHAR(10),"\n")&IF(AC23<>"", "', textAdditional: '"&SUBSTITUTE(SUBSTITUTE(AC23, CHAR(13), ""),CHAR(10),"\n"), "")&"', textZh: '"&SUBSTITUTE(SUBSTITUTE(SUBSTITUTE(AD23, CHAR(13), ""),CHAR(10),"\n"),"'","\'")&"', textZhG1: '"&SUBSTITUTE(SUBSTITUTE(SUBSTITUTE(AF23, CHAR(13), ""),CHAR(10),"\n"),"'","\'")&IF(AE23<>"", "', textZhAdditional: '"&SUBSTITUTE(SUBSTITUTE(AE23, CHAR(13), ""),CHAR(10),"\n"), "")&"', textKo: '"&SUBSTITUTE(SUBSTITUTE(SUBSTITUTE(AG23, CHAR(13), ""),CHAR(10),"\n"),"'","\'")&"', textEn: '"&SUBSTITUTE(SUBSTITUTE(SUBSTITUTE(AH23, CHAR(13), ""),CHAR(10),"\n"),"'","\'")&"'"&IF(Z23="○",", sealable: true","")&IF(AA23="○",", removable: true","")&"}") -> , '02-saine-o-n-6': {megami: 'saine', name: '衝音晶', nameEn: 'Wavering Crystal', nameZh: '冲音晶', nameZhG1: '冲音晶', nameKo: '충음정', ruby: 'しょうおんしょう', rubyEn: '', baseType: 'normal', type: 'enhance', subType: 'reaction', capacity: '1', text: '【展開時】対応した《攻撃》は-1/+0となる。\n【破棄時】攻撃『適正距離0-10、1/-、対応不可』を行う。', textZh: '【展开时】被对应的《攻击》得-1/+0。\n【破弃时】进行一次“攻击距离0-10、伤害1/-、不可被对应”的攻击。', textZhG1: '【展开时】被对应的《攻击》得-1/-0 。\n【破弃时】进行一次“攻击距离0-10 伤害1/- 不可被对应”的攻击。', textKo: '【전개시】대응한 《공격》은 -1/+0이 된다.\n 【파기시】공격『적정거리0-10、1/-、대응불가』를 행한다.', textEn: 'Initialize: The attack you played this card as a Reaction to gets -1/+0.\n\nDisenchant: You attack with "Range: 0-10, Damage: 1/-, No Reactions".'} | AO23: =IF($A23<>"", " /** 《"&$E23&"》 */ export const "&SUBSTITUTE(UPPER(IF(MID($A23, 3, 1)="-", RIGHT($A23,LEN($A23)-3), $A23)), "-", "_")&": TCardId = '"&$A23&"';", "") -> /** 《衝音晶》 */ export const SAINE_O_N_6: TCardId = '02-saine-o-n-6'; | AP23: =IF($A23<>"", " | '"&$A23&"'", "") -> | '02-saine-o-n-6'
A24: 02-saine-A1-n-6 | B24: saine | C24: A1 | D24: 02-saine-o-n-6 | E24: 伴奏 | F24: ばんそう | G24: 伴奏 | H24: 伴奏 | J24: 반주 | K24: Accompaniment | M24: 通常札 | R24: 付与 | X24: 4 | AB24: 【展開中】あなたの他のメガミの切札が1枚以上使用済ならば、各ターンの最初の相手の《攻撃》は-1/+0となる。 【展開中】あなたのサイネの切札が1枚以上使用済ならば、各ターンにあなたが最初に使用する切札の消費は1少なくなる(0未満にはならない)。 | AD24: 【展开中】若你有至少1张另一柱女神的王牌为已使用状态，则每回合对手的第一次《攻击》得-1/+0。 【展开中】若你有至少1张细音的王牌为已使用状态，则每回合你使用的第一张王牌费用减小1（王牌的费用不会为负值）。 | AF24: 【展开中】若你有至少一张另一柱女武神的王牌正面朝上，则每回合对手的第一次《攻击》得-1/+0 。 【展开中】若你有至少一张细音的王牌正面朝上，则每回合你使用的第一张王牌费用减小1（王牌的消费不会为负）。 | AG24: 【전개중】당신의 다른 여신의 비장패가 1장 이상 사용완료라면, 매 턴 첫 상대의 《공격》은 -1/+0이 된다. 【전개중】당신의 사이네의 비장패가 1장 이상 사용완료라면, 당신이 매 턴 처음 사용하는 비장패의 소비는 1 적게 된다(0미만으로는 되지 않는다). | AH24: Ongoing: If at least one of your other Megami's Special cards is Devoted, the first attack your opponent makes each turn gets -1/+0. Ongoing: If at least one of your Saine's Special cards is Devoted, the first Special you play each turn costs 1 less to play. | AN24: =IF(A24="", "", IF(ROW()>=3, ", ", "")&"'"&A24&"': {megami: '"&B24&"'"&IF(C24<>"",", anotherID: '"&C24&"', replace: '"&D24&"'","")&", name: '"&SUBSTITUTE(E24,"'","\'")&"', nameEn: '"&SUBSTITUTE(K24,"'","\'")&"', nameZh: '"&SUBSTITUTE(G24,"'","\'")&"', nameZhG1: '"&SUBSTITUTE(H24,"'","\'")&"', nameKo: '"&SUBSTITUTE(J24,"'","\'")&"', ruby: '"&F24&"', rubyEn: '"&L24&IF(I24<>"", "', rubyZh: '"&I24, "")&"', baseType: '"&VLOOKUP(M24,マスタ!$A$1:$B$99,2,0)&"'"&IF(N24="○",", extra: true","")&IF(O24<>"",", extraFrom: '"&O24&"'","")&IF(P24<>"",", exchangableTo: '"&P24&"'","")&IF(Q24="○",", poison: true","")&IF(R24<>"", ", type: '"&VLOOKUP(R24,マスタ!$D$1:$E$99,2,0)&"'", "")&IF(S24<>"",", subType: '"&VLOOKUP(S24,マスタ!$D$1:$E$99,2,0)&"'","")&IF(T24<>"",", range: '"&T24&"'","")&IF(V24<>"",", damage: '"&V24&"'","")&IF(X24<>"",", capacity: '"&X24&"'","")&IF(Y24<>"",", cost: '"&Y24&"'","")&", text: '"&SUBSTITUTE(SUBSTITUTE(AB24, CHAR(13), ""),CHAR(10),"\n")&IF(AC24<>"", "', textAdditional: '"&SUBSTITUTE(SUBSTITUTE(AC24, CHAR(13), ""),CHAR(10),"\n"), "")&"', textZh: '"&SUBSTITUTE(SUBSTITUTE(SUBSTITUTE(AD24, CHAR(13), ""),CHAR(10),"\n"),"'","\'")&"', textZhG1: '"&SUBSTITUTE(SUBSTITUTE(SUBSTITUTE(AF24, CHAR(13), ""),CHAR(10),"\n"),"'","\'")&IF(AE24<>"", "', textZhAdditional: '"&SUBSTITUTE(SUBSTITUTE(AE24, CHAR(13), ""),CHAR(10),"\n"), "")&"', textKo: '"&SUBSTITUTE(SUBSTITUTE(SUBSTITUTE(AG24, CHAR(13), ""),CHAR(10),"\n"),"'","\'")&"', textEn: '"&SUBSTITUTE(SUBSTITUTE(SUBSTITUTE(AH24, CHAR(13), ""),CHAR(10),"\n"),"'","\'")&"'"&IF(Z24="○",", sealable: true","")&IF(AA24="○",", removable: true","")&"}") -> , '02-saine-A1-n-6': {megami: 'saine', anotherID: 'A1', replace: '02-saine-o-n-6', name: '伴奏', nameEn: 'Accompaniment', nameZh: '伴奏', nameZhG1: '伴奏', nameKo: '반주', ruby: 'ばんそう', rubyEn: '', baseType: 'normal', type: 'enhance', capacity: '4', text: '【展開中】あなたの他のメガミの切札が1枚以上使用済ならば、各ターンの最初の相手の《攻撃》は-1/+0となる。\n【展開中】あなたのサイネの切札が1枚以上使用済ならば、各ターンにあなたが最初に使用する切札の消費は1少なくなる(0未満にはならない)。', textZh: '【展开中】若你有至少1张另一柱女神的王牌为已使用状态，则每回合对手的第一次《攻击》得-1/+0。\n【展开中】若你有至少1张细音的王牌为已使用状态，则每回合你使用的第一张王牌费用减小1（王牌的费用不会为负值）。', textZhG1: '【展开中】若你有至少一张另一柱女武神的王牌正面朝上，则每回合对手的第一次《攻击》得-1/+0 。\n【展开中】若你有至少一张细音的王牌正面朝上，则每回合你使用的第一张王牌费用减小1（王牌的消费不会为负）。', textKo: '【전개중】당신의 다른 여신의 비장패가 1장 이상 사용완료라면, 매 턴 첫 상대의 《공격》은 -1/+0이 된다.\n 【전개중】당신의 사이네의 비장패가 1장 이상 사용완료라면, 당신이 매 턴 처음 사용하는 비장패의 소비는 1 적게 된다(0미만으로는 되지 않는다).', textEn: 'Ongoing: If at least one of your other Megami\'s Special cards is Devoted, the first attack your opponent makes each turn gets -1/+0.\n\nOngoing: If at least one of your Saine\'s Special cards is Devoted, the first Special you play each turn costs 1 less to play.'} | AO24: =IF($A24<>"", " /** 《"&$E24&"》 */ export const "&SUBSTITUTE(UPPER(IF(MID($A24, 3, 1)="-", RIGHT($A24,LEN($A24)-3), $A24)), "-", "_")&": TCardId = '"&$A24&"';", "") -> /** 《伴奏》 */ export const SAINE_A1_N_6: TCardId = '02-saine-A1-n-6'; | AP24: =IF($A24<>"", " | '"&$A24&"'", "") -> | '02-saine-A1-n-6'
A25: 02-saine-o-n-7 | B25: saine | E25: 無音壁 | F25: むおんへき | G25: 无音壁 | H25: 无音壁 | J25: 무음벽 | K25: Silent Wall | M25: 通常札 | R25: 付与 | S25: 全力 | X25: 5 | AB25: 【展開中】あなたへのダメージを解決するに際し、このカードの上に置かれた桜花結晶をあなたのオーラにあるかのように扱う。 | AD25: 对你造成的伤害结算时，此牌上的樱花结晶视为在自装中。 | AF25: 【展开中】当自装将要受到伤害时，移除此牌上的樱花结晶，直到伤害被防止或移除了此牌上最后一个樱花结晶为止。每以此法移除一个樱花结晶，便防止1点对装伤害。 | AG25: 【전개중】당신으로의 대미지를 해결 할 때, 이 카드 위에 놓인 벚꽃 결정을 당신의 오라에 있는 것처럼 취급한다. | AH25: Ongoing: Treat Sakura tokens on this card as if they were on your Aura whenever you are dealt damage. | AN25: =IF(A25="", "", IF(ROW()>=3, ", ", "")&"'"&A25&"': {megami: '"&B25&"'"&IF(C25<>"",", anotherID: '"&C25&"', replace: '"&D25&"'","")&", name: '"&SUBSTITUTE(E25,"'","\'")&"', nameEn: '"&SUBSTITUTE(K25,"'","\'")&"', nameZh: '"&SUBSTITUTE(G25,"'","\'")&"', nameZhG1: '"&SUBSTITUTE(H25,"'","\'")&"', nameKo: '"&SUBSTITUTE(J25,"'","\'")&"', ruby: '"&F25&"', rubyEn: '"&L25&IF(I25<>"", "', rubyZh: '"&I25, "")&"', baseType: '"&VLOOKUP(M25,マスタ!$A$1:$B$99,2,0)&"'"&IF(N25="○",", extra: true","")&IF(O25<>"",", extraFrom: '"&O25&"'","")&IF(P25<>"",", exchangableTo: '"&P25&"'","")&IF(Q25="○",", poison: true","")&IF(R25<>"", ", type: '"&VLOOKUP(R25,マスタ!$D$1:$E$99,2,0)&"'", "")&IF(S25<>"",", subType: '"&VLOOKUP(S25,マスタ!$D$1:$E$99,2,0)&"'","")&IF(T25<>"",", range: '"&T25&"'","")&IF(V25<>"",", damage: '"&V25&"'","")&IF(X25<>"",", capacity: '"&X25&"'","")&IF(Y25<>"",", cost: '"&Y25&"'","")&", text: '"&SUBSTITUTE(SUBSTITUTE(AB25, CHAR(13), ""),CHAR(10),"\n")&IF(AC25<>"", "', textAdditional: '"&SUBSTITUTE(SUBSTITUTE(AC25, CHAR(13), ""),CHAR(10),"\n"), "")&"', textZh: '"&SUBSTITUTE(SUBSTITUTE(SUBSTITUTE(AD25, CHAR(13), ""),CHAR(10),"\n"),"'","\'")&"', textZhG1: '"&SUBSTITUTE(SUBSTITUTE(SUBSTITUTE(AF25, CHAR(13), ""),CHAR(10),"\n"),"'","\'")&IF(AE25<>"", "', textZhAdditional: '"&SUBSTITUTE(SUBSTITUTE(AE25, CHAR(13), ""),CHAR(10),"\n"), "")&"', textKo: '"&SUBSTITUTE(SUBSTITUTE(SUBSTITUTE(AG25, CHAR(13), ""),CHAR(10),"\n"),"'","\'")&"', textEn: '"&SUBSTITUTE(SUBSTITUTE(SUBSTITUTE(AH25, CHAR(13), ""),CHAR(10),"\n"),"'","\'")&"'"&IF(Z25="○",", sealable: true","")&IF(AA25="○",", removable: true","")&"}") -> , '02-saine-o-n-7': {megami: 'saine', name: '無音壁', nameEn: 'Silent Wall', nameZh: '无音壁', nameZhG1: '无音壁', nameKo: '무음벽', ruby: 'むおんへき', rubyEn: '', baseType: 'normal', type: 'enhance', subType: 'fullpower', capacity: '5', text: '【展開中】あなたへのダメージを解決するに際し、このカードの上に置かれた桜花結晶をあなたのオーラにあるかのように扱う。', textZh: '对你造成的伤害结算时，此牌上的樱花结晶视为在自装中。', textZhG1: '【展开中】当自装将要受到伤害时，移除此牌上的樱花结晶，直到伤害被防止或移除了此牌上最后一个樱花结晶为止。每以此法移除一个樱花结晶，便防止1点对装伤害。', textKo: '【전개중】당신으로의 대미지를 해결 할 때, 이 카드 위에 놓인 벚꽃 결정을 당신의 오라에 있는 것처럼 취급한다.', textEn: 'Ongoing: Treat Sakura tokens on this card as if they were on your Aura whenever you are dealt damage.'} | AO25: =IF($A25<>"", " /** 《"&$E25&"》 */ export const "&SUBSTITUTE(UPPER(IF(MID($A25, 3, 1)="-", RIGHT($A25,LEN($A25)-3), $A25)), "-", "_")&": TCardId = '"&$A25&"';", "") -> /** 《無音壁》 */ export const SAINE_O_N_7: TCardId = '02-saine-o-n-7'; | AP25: =IF($A25<>"", " | '"&$A25&"'", "") -> | '02-saine-o-n-7'
A26: 02-saine-o-s-1 | B26: saine | E26: 律動弧戟 | F26: りつどうこげき | G26: 律动弧戟 | H26: 律动弧戟 | J26: 율동호극 | K26: Rhythmic Arc | M26: 切札 | R26: 行動 | Y26: 6 | AB26: 攻撃『適正距離3-4、1/1』を行う。 攻撃『適正距離4-5、1/1』を行う。 攻撃『適正距離3-5、2/2』を行う。 | AD26: 进行一次“攻击距离3-4、伤害1/1”的攻击。 进行一次“攻击距离4-5、伤害1/1”的攻击。 进行一次“攻击距离3-5、伤害2/2”的攻击。 | AF26: 进行一次“攻击距离3-4 伤害1/1”的攻击。 进行一次“攻击距离4-5 伤害1/1”的攻击。 进行一次“攻击距离3-5 伤害2/2”的攻击。 | AG26: 공격『적정거리3-4、1/1』을 행한다. 공격『적정거리4-5、1/1』을 행한다. 공격『적정거리3-5、2/2』을 행한다. | AH26: You attack with "Range: 3-4, Damage: 1/1", "Range: 4-5, Damage: 1/1", and "Range: 3-5, Damage: 2/2" in this order. | AN26: =IF(A26="", "", IF(ROW()>=3, ", ", "")&"'"&A26&"': {megami: '"&B26&"'"&IF(C26<>"",", anotherID: '"&C26&"', replace: '"&D26&"'","")&", name: '"&SUBSTITUTE(E26,"'","\'")&"', nameEn: '"&SUBSTITUTE(K26,"'","\'")&"', nameZh: '"&SUBSTITUTE(G26,"'","\'")&"', nameZhG1: '"&SUBSTITUTE(H26,"'","\'")&"', nameKo: '"&SUBSTITUTE(J26,"'","\'")&"', ruby: '"&F26&"', rubyEn: '"&L26&IF(I26<>"", "', rubyZh: '"&I26, "")&"', baseType: '"&VLOOKUP(M26,マスタ!$A$1:$B$99,2,0)&"'"&IF(N26="○",", extra: true","")&IF(O26<>"",", extraFrom: '"&O26&"'","")&IF(P26<>"",", exchangableTo: '"&P26&"'","")&IF(Q26="○",", poison: true","")&IF(R26<>"", ", type: '"&VLOOKUP(R26,マスタ!$D$1:$E$99,2,0)&"'", "")&IF(S26<>"",", subType: '"&VLOOKUP(S26,マスタ!$D$1:$E$99,2,0)&"'","")&IF(T26<>"",", range: '"&T26&"'","")&IF(V26<>"",", damage: '"&V26&"'","")&IF(X26<>"",", capacity: '"&X26&"'","")&IF(Y26<>"",", cost: '"&Y26&"'","")&", text: '"&SUBSTITUTE(SUBSTITUTE(AB26, CHAR(13), ""),CHAR(10),"\n")&IF(AC26<>"", "', textAdditional: '"&SUBSTITUTE(SUBSTITUTE(AC26, CHAR(13), ""),CHAR(10),"\n"), "")&"', textZh: '"&SUBSTITUTE(SUBSTITUTE(SUBSTITUTE(AD26, CHAR(13), ""),CHAR(10),"\n"),"'","\'")&"', textZhG1: '"&SUBSTITUTE(SUBSTITUTE(SUBSTITUTE(AF26, CHAR(13), ""),CHAR(10),"\n"),"'","\'")&IF(AE26<>"", "', textZhAdditional: '"&SUBSTITUTE(SUBSTITUTE(AE26, CHAR(13), ""),CHAR(10),"\n"), "")&"', textKo: '"&SUBSTITUTE(SUBSTITUTE(SUBSTITUTE(AG26, CHAR(13), ""),CHAR(10),"\n"),"'","\'")&"', textEn: '"&SUBSTITUTE(SUBSTITUTE(SUBSTITUTE(AH26, CHAR(13), ""),CHAR(10),"\n"),"'","\'")&"'"&IF(Z26="○",", sealable: true","")&IF(AA26="○",", removable: true","")&"}") -> , '02-saine-o-s-1': {megami: 'saine', name: '律動弧戟', nameEn: 'Rhythmic Arc', nameZh: '律动弧戟', nameZhG1: '律动弧戟', nameKo: '율동호극', ruby: 'りつどうこげき', rubyEn: '', baseType: 'special', type: 'action', cost: '6', text: '攻撃『適正距離3-4、1/1』を行う。\n攻撃『適正距離4-5、1/1』を行う。\n攻撃『適正距離3-5、2/2』を行う。', textZh: '进行一次“攻击距离3-4、伤害1/1”的攻击。\n进行一次“攻击距离4-5、伤害1/1”的攻击。\n进行一次“攻击距离3-5、伤害2/2”的攻击。', textZhG1: '进行一次“攻击距离3-4 伤害1/1”的攻击。\n进行一次“攻击距离4-5 伤害1/1”的攻击。\n进行一次“攻击距离3-5 伤害2/2”的攻击。', textKo: '공격『적정거리3-4、1/1』을 행한다. 공격『적정거리4-5、1/1』을 행한다. 공격『적정거리3-5、2/2』을 행한다.', textEn: 'You attack with\n"Range: 3-4, Damage: 1/1", \n"Range: 4-5, Damage: 1/1", and \n"Range: 3-5, Damage: 2/2" \nin this order.'} | AO26: =IF($A26<>"", " /** 《"&$E26&"》 */ export const "&SUBSTITUTE(UPPER(IF(MID($A26, 3, 1)="-", RIGHT($A26,LEN($A26)-3), $A26)), "-", "_")&": TCardId = '"&$A26&"';", "") -> /** 《律動弧戟》 */ export const SAINE_O_S_1: TCardId = '02-saine-o-s-1'; | AP26: =IF($A26<>"", " | '"&$A26&"'", "") -> | '02-saine-o-s-1'
A27: 02-saine-o-s-2 | B27: saine | E27: 響鳴共振 | F27: きょうめいきょうしん | G27: 响鸣共振 | H27: 响鸣共振 | J27: 항명공진 | K27: Resonant Beat | M27: 切札 | R27: 行動 | Y27: 8 | AB27: 【常時】このカードの消費は相手のオーラの数だけ少なくなる。 相オーラ→間合：2 | AD27: 【常时】此牌的费用减小X，X等于敌装中的樱花结晶的数目。 敌装→2→距 | AF27: 【常时】这张卡的费用减小X，X等于敌装中的樱花结晶的数目。 敌装（2）→距 | AG27: 【상시】이 카드의 소비는 상대 오라의 수 만큼 적어진다. 상대 오라→간격：2 | AH27: Forced: This card costs 1 less for each Sakura token on your opponent's Aura. Opponent's Aura (2)→ Distance | AN27: =IF(A27="", "", IF(ROW()>=3, ", ", "")&"'"&A27&"': {megami: '"&B27&"'"&IF(C27<>"",", anotherID: '"&C27&"', replace: '"&D27&"'","")&", name: '"&SUBSTITUTE(E27,"'","\'")&"', nameEn: '"&SUBSTITUTE(K27,"'","\'")&"', nameZh: '"&SUBSTITUTE(G27,"'","\'")&"', nameZhG1: '"&SUBSTITUTE(H27,"'","\'")&"', nameKo: '"&SUBSTITUTE(J27,"'","\'")&"', ruby: '"&F27&"', rubyEn: '"&L27&IF(I27<>"", "', rubyZh: '"&I27, "")&"', baseType: '"&VLOOKUP(M27,マスタ!$A$1:$B$99,2,0)&"'"&IF(N27="○",", extra: true","")&IF(O27<>"",", extraFrom: '"&O27&"'","")&IF(P27<>"",", exchangableTo: '"&P27&"'","")&IF(Q27="○",", poison: true","")&IF(R27<>"", ", type: '"&VLOOKUP(R27,マスタ!$D$1:$E$99,2,0)&"'", "")&IF(S27<>"",", subType: '"&VLOOKUP(S27,マスタ!$D$1:$E$99,2,0)&"'","")&IF(T27<>"",", range: '"&T27&"'","")&IF(V27<>"",", damage: '"&V27&"'","")&IF(X27<>"",", capacity: '"&X27&"'","")&IF(Y27<>"",", cost: '"&Y27&"'","")&", text: '"&SUBSTITUTE(SUBSTITUTE(AB27, CHAR(13), ""),CHAR(10),"\n")&IF(AC27<>"", "', textAdditional: '"&SUBSTITUTE(SUBSTITUTE(AC27, CHAR(13), ""),CHAR(10),"\n"), "")&"', textZh: '"&SUBSTITUTE(SUBSTITUTE(SUBSTITUTE(AD27, CHAR(13), ""),CHAR(10),"\n"),"'","\'")&"', textZhG1: '"&SUBSTITUTE(SUBSTITUTE(SUBSTITUTE(AF27, CHAR(13), ""),CHAR(10),"\n"),"'","\'")&IF(AE27<>"", "', textZhAdditional: '"&SUBSTITUTE(SUBSTITUTE(AE27, CHAR(13), ""),CHAR(10),"\n"), "")&"', textKo: '"&SUBSTITUTE(SUBSTITUTE(SUBSTITUTE(AG27, CHAR(13), ""),CHAR(10),"\n"),"'","\'")&"', textEn: '"&SUBSTITUTE(SUBSTITUTE(SUBSTITUTE(AH27, CHAR(13), ""),CHAR(10),"\n"),"'","\'")&"'"&IF(Z27="○",", sealable: true","")&IF(AA27="○",", removable: true","")&"}") -> , '02-saine-o-s-2': {megami: 'saine', name: '響鳴共振', nameEn: 'Resonant Beat', nameZh: '响鸣共振', nameZhG1: '响鸣共振', nameKo: '항명공진', ruby: 'きょうめいきょうしん', rubyEn: '', baseType: 'special', type: 'action', cost: '8', text: '【常時】このカードの消費は相手のオーラの数だけ少なくなる。\n相オーラ→間合：2', textZh: '【常时】此牌的费用减小X，X等于敌装中的樱花结晶的数目。 \n敌装→2→距', textZhG1: '【常时】这张卡的费用减小X，X等于敌装中的樱花结晶的数目。 \n敌装（2）→距', textKo: '【상시】이 카드의 소비는 상대 오라의 수 만큼 적어진다.\n 상대 오라→간격：2', textEn: 'Forced: This card costs 1 less for each Sakura token on your opponent\'s Aura.\nOpponent\'s Aura (2)→ Distance'} | AO27: =IF($A27<>"", " /** 《"&$E27&"》 */ export const "&SUBSTITUTE(UPPER(IF(MID($A27, 3, 1)="-", RIGHT($A27,LEN($A27)-3), $A27)), "-", "_")&": TCardId = '"&$A27&"';", "") -> /** 《響鳴共振》 */ export const SAINE_O_S_2: TCardId = '02-saine-o-s-2'; | AP27: =IF($A27<>"", " | '"&$A27&"'", "") -> | '02-saine-o-s-2'
A28: 02-saine-A1-s-2 | B28: saine | C28: A1 | D28: 02-saine-o-s-2 | E28: 二重奏:弾奏氷瞑 | F28: にじゅうそう:だんそうひょうめい | G28: 二重奏：弹奏冰瞑 | H28: 二重奏：弹奏冰瞑 | J28: 이중주:탄주빙명 | K28: Duet: Chilling Tranquility | M28: 切札 | R28: 行動 | Y28: 2 | AB28: 現在のフェイズを終了する。 【使用済】あなたの他のメガミによる《攻撃》は+0/+1となる。 ---- 【即再起】あなたが再構成以外でライフに1以上のダメージを受ける。 | AD28: 结束当前阶段。 【已使用】你的另一柱女神的《攻击》得+0/+1。 ---- 【即再起】自命受到除重铸牌库以外的1点或以上的伤害。 | AF28: 结束当前阶段。 【已使用】你的另一柱女武神的《攻击》得+0/+1。 ---- 【即再起】自命受到除重铸牌库以外的1点以上的伤害。 | AG28: 현재 페이즈를 종료한다. 【사용완료】당신의 다른 여신에 의한 《공격》은 +0/+1이 된다. ---- 【즉재기】당신이 재구성 이외로 라이프에 1 이상의 대미지를 받는다. | AH28: End the current phase. Devoted: All your other Megami's attacks gain +0/+1. ---- Immediate Resurgence: You take 1 or more damage to your Life, excluding reshuffle damage. | AN28: =IF(A28="", "", IF(ROW()>=3, ", ", "")&"'"&A28&"': {megami: '"&B28&"'"&IF(C28<>"",", anotherID: '"&C28&"', replace: '"&D28&"'","")&", name: '"&SUBSTITUTE(E28,"'","\'")&"', nameEn: '"&SUBSTITUTE(K28,"'","\'")&"', nameZh: '"&SUBSTITUTE(G28,"'","\'")&"', nameZhG1: '"&SUBSTITUTE(H28,"'","\'")&"', nameKo: '"&SUBSTITUTE(J28,"'","\'")&"', ruby: '"&F28&"', rubyEn: '"&L28&IF(I28<>"", "', rubyZh: '"&I28, "")&"', baseType: '"&VLOOKUP(M28,マスタ!$A$1:$B$99,2,0)&"'"&IF(N28="○",", extra: true","")&IF(O28<>"",", extraFrom: '"&O28&"'","")&IF(P28<>"",", exchangableTo: '"&P28&"'","")&IF(Q28="○",", poison: true","")&IF(R28<>"", ", type: '"&VLOOKUP(R28,マスタ!$D$1:$E$99,2,0)&"'", "")&IF(S28<>"",", subType: '"&VLOOKUP(S28,マスタ!$D$1:$E$99,2,0)&"'","")&IF(T28<>"",", range: '"&T28&"'","")&IF(V28<>"",", damage: '"&V28&"'","")&IF(X28<>"",", capacity: '"&X28&"'","")&IF(Y28<>"",", cost: '"&Y28&"'","")&", text: '"&SUBSTITUTE(SUBSTITUTE(AB28, CHAR(13), ""),CHAR(10),"\n")&IF(AC28<>"", "', textAdditional: '"&SUBSTITUTE(SUBSTITUTE(AC28, CHAR(13), ""),CHAR(10),"\n"), "")&"', textZh: '"&SUBSTITUTE(SUBSTITUTE(SUBSTITUTE(AD28, CHAR(13), ""),CHAR(10),"\n"),"'","\'")&"', textZhG1: '"&SUBSTITUTE(SUBSTITUTE(SUBSTITUTE(AF28, CHAR(13), ""),CHAR(10),"\n"),"'","\'")&IF(AE28<>"", "', textZhAdditional: '"&SUBSTITUTE(SUBSTITUTE(AE28, CHAR(13), ""),CHAR(10),"\n"), "")&"', textKo: '"&SUBSTITUTE(SUBSTITUTE(SUBSTITUTE(AG28, CHAR(13), ""),CHAR(10),"\n"),"'","\'")&"', textEn: '"&SUBSTITUTE(SUBSTITUTE(SUBSTITUTE(AH28, CHAR(13), ""),CHAR(10),"\n"),"'","\'")&"'"&IF(Z28="○",", sealable: true","")&IF(AA28="○",", removable: true","")&"}") -> , '02-saine-A1-s-2': {megami: 'saine', anotherID: 'A1', replace: '02-saine-o-s-2', name: '二重奏:弾奏氷瞑', nameEn: 'Duet: Chilling Tranquility', nameZh: '二重奏：弹奏冰瞑', nameZhG1: '二重奏：弹奏冰瞑', nameKo: '이중주:탄주빙명', ruby: 'にじゅうそう:だんそうひょうめい', rubyEn: '', baseType: 'special', type: 'action', cost: '2', text: '現在のフェイズを終了する。\n【使用済】あなたの他のメガミによる《攻撃》は+0/+1となる。\n----\n【即再起】あなたが再構成以外でライフに1以上のダメージを受ける。', textZh: '结束当前阶段。\n【已使用】你的另一柱女神的《攻击》得+0/+1。\n----\n【即再起】自命受到除重铸牌库以外的1点或以上的伤害。', textZhG1: '结束当前阶段。\n【已使用】你的另一柱女武神的《攻击》得+0/+1。\n----\n【即再起】自命受到除重铸牌库以外的1点以上的伤害。', textKo: '현재 페이즈를 종료한다.\n【사용완료】당신의 다른 여신에 의한 《공격》은 +0/+1이 된다. \n---- \n【즉재기】당신이 재구성 이외로 라이프에 1 이상의 대미지를 받는다.', textEn: 'End the current phase.\n\nDevoted: All your other Megami\'s attacks gain +0/+1.\n----\nImmediate Resurgence: You take 1 or more damage to your Life, excluding reshuffle damage.'} | AO28: =IF($A28<>"", " /** 《"&$E28&"》 */ export const "&SUBSTITUTE(UPPER(IF(MID($A28, 3, 1)="-", RIGHT($A28,LEN($A28)-3), $A28)), "-", "_")&": TCardId = '"&$A28&"';", "") -> /** 《二重奏:弾奏氷瞑》 */ export const SAINE_A1_S_2: TCardId = '02-saine-A1-s-2'; | AP28: =IF($A28<>"", " | '"&$A28&"'", "") -> | '02-saine-A1-s-2'
A29: 02-saine-o-s-3 | B29: saine | E29: 音無砕氷 | F29: おとなしさいひょう | G29: 音无碎冰 | H29: 音无碎冰 | J29: 음무쇄빙 | K29: Silent Icebreaker | M29: 切札 | R29: 攻撃 | S29: 対応 | T29: 0-10 | V29: 1/1 | Y29: 2 | AB29: 【攻撃後】対応した《攻撃》は-1/-1となる。 ---- 【再起】八相-あなたのオーラが0である。 | AD29: 【攻击后】被对应的《攻击》得-1/-1。 ---- 【再起】八相～自装中没有樱花结晶。 | AF29: 【攻击后】被对应的《攻击》得-1/-1 。 ---- 【再起】：八相-自装等于0。 | AG29: 【공격후】대응한 《공격》은 -1/-1이 된다. ---- 【재기】팔상-당신의 오라가 0이다. | AH29: After Attack: The attack you played this card as a Reaction to gets -1/-1. ---- Resurgence: Idea - You have no Sakura tokens on your Aura. | AN29: =IF(A29="", "", IF(ROW()>=3, ", ", "")&"'"&A29&"': {megami: '"&B29&"'"&IF(C29<>"",", anotherID: '"&C29&"', replace: '"&D29&"'","")&", name: '"&SUBSTITUTE(E29,"'","\'")&"', nameEn: '"&SUBSTITUTE(K29,"'","\'")&"', nameZh: '"&SUBSTITUTE(G29,"'","\'")&"', nameZhG1: '"&SUBSTITUTE(H29,"'","\'")&"', nameKo: '"&SUBSTITUTE(J29,"'","\'")&"', ruby: '"&F29&"', rubyEn: '"&L29&IF(I29<>"", "', rubyZh: '"&I29, "")&"', baseType: '"&VLOOKUP(M29,マスタ!$A$1:$B$99,2,0)&"'"&IF(N29="○",", extra: true","")&IF(O29<>"",", extraFrom: '"&O29&"'","")&IF(P29<>"",", exchangableTo: '"&P29&"'","")&IF(Q29="○",", poison: true","")&IF(R29<>"", ", type: '"&VLOOKUP(R29,マスタ!$D$1:$E$99,2,0)&"'", "")&IF(S29<>"",", subType: '"&VLOOKUP(S29,マスタ!$D$1:$E$99,2,0)&"'","")&IF(T29<>"",", range: '"&T29&"'","")&IF(V29<>"",", damage: '"&V29&"'","")&IF(X29<>"",", capacity: '"&X29&"'","")&IF(Y29<>"",", cost: '"&Y29&"'","")&", text: '"&SUBSTITUTE(SUBSTITUTE(AB29, CHAR(13), ""),CHAR(10),"\n")&IF(AC29<>"", "', textAdditional: '"&SUBSTITUTE(SUBSTITUTE(AC29, CHAR(13), ""),CHAR(10),"\n"), "")&"', textZh: '"&SUBSTITUTE(SUBSTITUTE(SUBSTITUTE(AD29, CHAR(13), ""),CHAR(10),"\n"),"'","\'")&"', textZhG1: '"&SUBSTITUTE(SUBSTITUTE(SUBSTITUTE(AF29, CHAR(13), ""),CHAR(10),"\n"),"'","\'")&IF(AE29<>"", "', textZhAdditional: '"&SUBSTITUTE(SUBSTITUTE(AE29, CHAR(13), ""),CHAR(10),"\n"), "")&"', textKo: '"&SUBSTITUTE(SUBSTITUTE(SUBSTITUTE(AG29, CHAR(13), ""),CHAR(10),"\n"),"'","\'")&"', textEn: '"&SUBSTITUTE(SUBSTITUTE(SUBSTITUTE(AH29, CHAR(13), ""),CHAR(10),"\n"),"'","\'")&"'"&IF(Z29="○",", sealable: true","")&IF(AA29="○",", removable: true","")&"}") -> , '02-saine-o-s-3': {megami: 'saine', name: '音無砕氷', nameEn: 'Silent Icebreaker', nameZh: '音无碎冰', nameZhG1: '音无碎冰', nameKo: '음무쇄빙', ruby: 'おとなしさいひょう', rubyEn: '', baseType: 'special', type: 'attack', subType: 'reaction', range: '0-10', damage: '1/1', cost: '2', text: '【攻撃後】対応した《攻撃》は-1/-1となる。\n----\n【再起】八相-あなたのオーラが0である。', textZh: '【攻击后】被对应的《攻击》得-1/-1。\n----\n【再起】八相～自装中没有樱花结晶。', textZhG1: '【攻击后】被对应的《攻击》得-1/-1 。\n----\n【再起】：八相-自装等于0。', textKo: '【공격후】대응한 《공격》은 -1/-1이 된다.\n ----\n 【재기】팔상-당신의 오라가 0이다.', textEn: 'After Attack: The attack you played this card as a Reaction to gets -1/-1.\n----\nResurgence: Idea - You have no Sakura tokens on your Aura.'} | AO29: =IF($A29<>"", " /** 《"&$E29&"》 */ export const "&SUBSTITUTE(UPPER(IF(MID($A29, 3, 1)="-", RIGHT($A29,LEN($A29)-3), $A29)), "-", "_")&": TCardId = '"&$A29&"';", "") -> /** 《音無砕氷》 */ export const SAINE_O_S_3: TCardId = '02-saine-o-s-3'; | AP29: =IF($A29<>"", " | '"&$A29&"'", "") -> | '02-saine-o-s-3'
A30: 02-saine-o-s-4 | B30: saine | E30: 氷雨細音の果ての果て | F30: ひさめさいねのはてのはて | G30: 冰雨细音的终焉之末 | H30: 冰雨细音的终焉 | J30: 히사메 사이네의 최후의 종극 | K30: Saine's Final Stage | M30: 切札 | R30: 攻撃 | S30: 対応 | T30: 1-5 | V30: 5/5 | Y30: 5 | AB30: 【常時】このカードは切札に対する対応でしか使用できない。 | AD30: 【常时】仅当你对应王牌时可以使用此牌。 | AF30: 【常时】只能当你对应王牌时使用此牌。 | AG30: 【상시】이 카드는 비장패에 대한 대응으로만 사용한다. | AH30: Forced: This can only be played as a Reaction to a Special card. | AN30: =IF(A30="", "", IF(ROW()>=3, ", ", "")&"'"&A30&"': {megami: '"&B30&"'"&IF(C30<>"",", anotherID: '"&C30&"', replace: '"&D30&"'","")&", name: '"&SUBSTITUTE(E30,"'","\'")&"', nameEn: '"&SUBSTITUTE(K30,"'","\'")&"', nameZh: '"&SUBSTITUTE(G30,"'","\'")&"', nameZhG1: '"&SUBSTITUTE(H30,"'","\'")&"', nameKo: '"&SUBSTITUTE(J30,"'","\'")&"', ruby: '"&F30&"', rubyEn: '"&L30&IF(I30<>"", "', rubyZh: '"&I30, "")&"', baseType: '"&VLOOKUP(M30,マスタ!$A$1:$B$99,2,0)&"'"&IF(N30="○",", extra: true","")&IF(O30<>"",", extraFrom: '"&O30&"'","")&IF(P30<>"",", exchangableTo: '"&P30&"'","")&IF(Q30="○",", poison: true","")&IF(R30<>"", ", type: '"&VLOOKUP(R30,マスタ!$D$1:$E$99,2,0)&"'", "")&IF(S30<>"",", subType: '"&VLOOKUP(S30,マスタ!$D$1:$E$99,2,0)&"'","")&IF(T30<>"",", range: '"&T30&"'","")&IF(V30<>"",", damage: '"&V30&"'","")&IF(X30<>"",", capacity: '"&X30&"'","")&IF(Y30<>"",", cost: '"&Y30&"'","")&", text: '"&SUBSTITUTE(SUBSTITUTE(AB30, CHAR(13), ""),CHAR(10),"\n")&IF(AC30<>"", "', textAdditional: '"&SUBSTITUTE(SUBSTITUTE(AC30, CHAR(13), ""),CHAR(10),"\n"), "")&"', textZh: '"&SUBSTITUTE(SUBSTITUTE(SUBSTITUTE(AD30, CHAR(13), ""),CHAR(10),"\n"),"'","\'")&"', textZhG1: '"&SUBSTITUTE(SUBSTITUTE(SUBSTITUTE(AF30, CHAR(13), ""),CHAR(10),"\n"),"'","\'")&IF(AE30<>"", "', textZhAdditional: '"&SUBSTITUTE(SUBSTITUTE(AE30, CHAR(13), ""),CHAR(10),"\n"), "")&"', textKo: '"&SUBSTITUTE(SUBSTITUTE(SUBSTITUTE(AG30, CHAR(13), ""),CHAR(10),"\n"),"'","\'")&"', textEn: '"&SUBSTITUTE(SUBSTITUTE(SUBSTITUTE(AH30, CHAR(13), ""),CHAR(10),"\n"),"'","\'")&"'"&IF(Z30="○",", sealable: true","")&IF(AA30="○",", removable: true","")&"}") -> , '02-saine-o-s-4': {megami: 'saine', name: '氷雨細音の果ての果て', nameEn: 'Saine\'s Final Stage', nameZh: '冰雨细音的终焉之末', nameZhG1: '冰雨细音的终焉', nameKo: '히사메 사이네의 최후의 종극', ruby: 'ひさめさいねのはてのはて', rubyEn: '', baseType: 'special', type: 'attack', subType: 'reaction', range: '1-5', damage: '5/5', cost: '5', text: '【常時】このカードは切札に対する対応でしか使用できない。', textZh: '【常时】仅当你对应王牌时可以使用此牌。', textZhG1: '【常时】只能当你对应王牌时使用此牌。', textKo: '【상시】이 카드는 비장패에 대한 대응으로만 사용한다.', textEn: 'Forced: This can only be played as a Reaction to a Special card.'} | AO30: =IF($A30<>"", " /** 《"&$E30&"》 */ export const "&SUBSTITUTE(UPPER(IF(MID($A30, 3, 1)="-", RIGHT($A30,LEN($A30)-3), $A30)), "-", "_")&": TCardId = '"&$A30&"';", "") -> /** 《氷雨細音の果ての果て》 */ export const SAINE_O_S_4: TCardId = '02-saine-o-s-4'; | AP30: =IF($A30<>"", " | '"&$A30&"'", "") -> | '02-saine-o-s-4'
AN31: =IF(A31="", "", IF(ROW()>=3, ", ", "")&"'"&A31&"': {megami: '"&B31&"'"&IF(C31<>"",", anotherID: '"&C31&"', replace: '"&D31&"'","")&", name: '"&SUBSTITUTE(E31,"'","\'")&"', nameEn: '"&SUBSTITUTE(K31,"'","\'")&"', nameZh: '"&SUBSTITUTE(G31,"'","\'")&"', nameZhG1: '"&SUBSTITUTE(H31,"'","\'")&"', nameKo: '"&SUBSTITUTE(J31,"'","\'")&"', ruby: '"&F31&"', rubyEn: '"&L31&IF(I31<>"", "', rubyZh: '"&I31, "")&"', baseType: '"&VLOOKUP(M31,マスタ!$A$1:$B$99,2,0)&"'"&IF(N31="○",", extra: true","")&IF(O31<>"",", extraFrom: '"&O31&"'","")&IF(P31<>"",", exchangableTo: '"&P31&"'","")&IF(Q31="○",", poison: true","")&IF(R31<>"", ", type: '"&VLOOKUP(R31,マスタ!$D$1:$E$99,2,0)&"'", "")&IF(S31<>"",", subType: '"&VLOOKUP(S31,マスタ!$D$1:$E$99,2,0)&"'","")&IF(T31<>"",", range: '"&T31&"'","")&IF(V31<>"",", damage: '"&V31&"'","")&IF(X31<>"",", capacity: '"&X31&"'","")&IF(Y31<>"",", cost: '"&Y31&"'","")&", text: '"&SUBSTITUTE(SUBSTITUTE(AB31, CHAR(13), ""),CHAR(10),"\n")&IF(AC31<>"", "', textAdditional: '"&SUBSTITUTE(SUBSTITUTE(AC31, CHAR(13), ""),CHAR(10),"\n"), "")&"', textZh: '"&SUBSTITUTE(SUBSTITUTE(SUBSTITUTE(AD31, CHAR(13), ""),CHAR(10),"\n"),"'","\'")&"', textZhG1: '"&SUBSTITUTE(SUBSTITUTE(SUBSTITUTE(AF31, CHAR(13), ""),CHAR(10),"\n"),"'","\'")&IF(AE31<>"", "', textZhAdditional: '"&SUBSTITUTE(SUBSTITUTE(AE31, CHAR(13), ""),CHAR(10),"\n"), "")&"', textKo: '"&SUBSTITUTE(SUBSTITUTE(SUBSTITUTE(AG31, CHAR(13), ""),CHAR(10),"\n"),"'","\'")&"', textEn: '"&SUBSTITUTE(SUBSTITUTE(SUBSTITUTE(AH31, CHAR(13), ""),CHAR(10),"\n"),"'","\'")&"'"&IF(Z31="○",", sealable: true","")&IF(AA31="○",", removable: true","")&"}") | AO31: =IF($A31<>"", " /** 《"&$E31&"》 */ export const "&SUBSTITUTE(UPPER(IF(MID($A31, 3, 1)="-", RIGHT($A31,LEN($A31)-3), $A31)), "-", "_")&": TCardId = '"&$A31&"';", "") | AP31: =IF($A31<>"", " | '"&$A31&"'", "")
A32: 03-himika-o-n-1 | B32: himika | E32: シュート | G32: 射击 | H32: 射击 | I32: Shoot | J32: 슛 | K32: Shoot | M32: 通常札 | R32: 攻撃 | T32: 4-10 | V32: 2/1 | AN32: =IF(A32="", "", IF(ROW()>=3, ", ", "")&"'"&A32&"': {megami: '"&B32&"'"&IF(C32<>"",", anotherID: '"&C32&"', replace: '"&D32&"'","")&", name: '"&SUBSTITUTE(E32,"'","\'")&"', nameEn: '"&SUBSTITUTE(K32,"'","\'")&"', nameZh: '"&SUBSTITUTE(G32,"'","\'")&"', nameZhG1: '"&SUBSTITUTE(H32,"'","\'")&"', nameKo: '"&SUBSTITUTE(J32,"'","\'")&"', ruby: '"&F32&"', rubyEn: '"&L32&IF(I32<>"", "', rubyZh: '"&I32, "")&"', baseType: '"&VLOOKUP(M32,マスタ!$A$1:$B$99,2,0)&"'"&IF(N32="○",", extra: true","")&IF(O32<>"",", extraFrom: '"&O32&"'","")&IF(P32<>"",", exchangableTo: '"&P32&"'","")&IF(Q32="○",", poison: true","")&IF(R32<>"", ", type: '"&VLOOKUP(R32,マスタ!$D$1:$E$99,2,0)&"'", "")&IF(S32<>"",", subType: '"&VLOOKUP(S32,マスタ!$D$1:$E$99,2,0)&"'","")&IF(T32<>"",", range: '"&T32&"'","")&IF(V32<>"",", damage: '"&V32&"'","")&IF(X32<>"",", capacity: '"&X32&"'","")&IF(Y32<>"",", cost: '"&Y32&"'","")&", text: '"&SUBSTITUTE(SUBSTITUTE(AB32, CHAR(13), ""),CHAR(10),"\n")&IF(AC32<>"", "', textAdditional: '"&SUBSTITUTE(SUBSTITUTE(AC32, CHAR(13), ""),CHAR(10),"\n"), "")&"', textZh: '"&SUBSTITUTE(SUBSTITUTE(SUBSTITUTE(AD32, CHAR(13), ""),CHAR(10),"\n"),"'","\'")&"', textZhG1: '"&SUBSTITUTE(SUBSTITUTE(SUBSTITUTE(AF32, CHAR(13), ""),CHAR(10),"\n"),"'","\'")&IF(AE32<>"", "', textZhAdditional: '"&SUBSTITUTE(SUBSTITUTE(AE32, CHAR(13), ""),CHAR(10),"\n"), "")&"', textKo: '"&SUBSTITUTE(SUBSTITUTE(SUBSTITUTE(AG32, CHAR(13), ""),CHAR(10),"\n"),"'","\'")&"', textEn: '"&SUBSTITUTE(SUBSTITUTE(SUBSTITUTE(AH32, CHAR(13), ""),CHAR(10),"\n"),"'","\'")&"'"&IF(Z32="○",", sealable: true","")&IF(AA32="○",", removable: true","")&"}") -> , '03-himika-o-n-1': {megami: 'himika', name: 'シュート', nameEn: 'Shoot', nameZh: '射击', nameZhG1: '射击', nameKo: '슛', ruby: '', rubyEn: '', rubyZh: 'Shoot', baseType: 'normal', type: 'attack', range: '4-10', damage: '2/1', text: '', textZh: '', textZhG1: '', textKo: '', textEn: ''} | AO32: =IF($A32<>"", " /** 《"&$E32&"》 */ export const "&SUBSTITUTE(UPPER(IF(MID($A32, 3, 1)="-", RIGHT($A32,LEN($A32)-3), $A32)), "-", "_")&": TCardId = '"&$A32&"';", "") -> /** 《シュート》 */ export const HIMIKA_O_N_1: TCardId = '03-himika-o-n-1'; | AP32: =IF($A32<>"", " | '"&$A32&"'", "") -> | '03-himika-o-n-1'
A33: 03-himika-o-n-2 | B33: himika | E33: ラピッドファイア | G33: 速射 | H33: 速射 | I33: Rapid Fire | J33: 래피드 파이어 | K33: Quick Shot | M33: 通常札 | R33: 攻撃 | T33: 7-8 | V33: 2/1 | AB33: 【常時】連火-このカードがこのターンに使用した3枚目以降のカードならば、この《攻撃》は+1/+1となる。 | AD33: 【常时】连火～若此牌是本回合你使用的第3张或更多的牌，则此《攻击》得+1/+1。 | AF33: 【常时】连火-若本回合你已使用至少2张牌，则此《攻击》得+1/+1。 | AG33: 【상시】연화-이 카드가 이 턴에 사용한 3장째 이후의 카드라면, 이 《공격》은 +1/+1이 된다. | AH33: Forced: Inferno - This attack gains +1/+1 if this is the third or later card you've played this turn. | AN33: =IF(A33="", "", IF(ROW()>=3, ", ", "")&"'"&A33&"': {megami: '"&B33&"'"&IF(C33<>"",", anotherID: '"&C33&"', replace: '"&D33&"'","")&", name: '"&SUBSTITUTE(E33,"'","\'")&"', nameEn: '"&SUBSTITUTE(K33,"'","\'")&"', nameZh: '"&SUBSTITUTE(G33,"'","\'")&"', nameZhG1: '"&SUBSTITUTE(H33,"'","\'")&"', nameKo: '"&SUBSTITUTE(J33,"'","\'")&"', ruby: '"&F33&"', rubyEn: '"&L33&IF(I33<>"", "', rubyZh: '"&I33, "")&"', baseType: '"&VLOOKUP(M33,マスタ!$A$1:$B$99,2,0)&"'"&IF(N33="○",", extra: true","")&IF(O33<>"",", extraFrom: '"&O33&"'","")&IF(P33<>"",", exchangableTo: '"&P33&"'","")&IF(Q33="○",", poison: true","")&IF(R33<>"", ", type: '"&VLOOKUP(R33,マスタ!$D$1:$E$99,2,0)&"'", "")&IF(S33<>"",", subType: '"&VLOOKUP(S33,マスタ!$D$1:$E$99,2,0)&"'","")&IF(T33<>"",", range: '"&T33&"'","")&IF(V33<>"",", damage: '"&V33&"'","")&IF(X33<>"",", capacity: '"&X33&"'","")&IF(Y33<>"",", cost: '"&Y33&"'","")&", text: '"&SUBSTITUTE(SUBSTITUTE(AB33, CHAR(13), ""),CHAR(10),"\n")&IF(AC33<>"", "', textAdditional: '"&SUBSTITUTE(SUBSTITUTE(AC33, CHAR(13), ""),CHAR(10),"\n"), "")&"', textZh: '"&SUBSTITUTE(SUBSTITUTE(SUBSTITUTE(AD33, CHAR(13), ""),CHAR(10),"\n"),"'","\'")&"', textZhG1: '"&SUBSTITUTE(SUBSTITUTE(SUBSTITUTE(AF33, CHAR(13), ""),CHAR(10),"\n"),"'","\'")&IF(AE33<>"", "', textZhAdditional: '"&SUBSTITUTE(SUBSTITUTE(AE33, CHAR(13), ""),CHAR(10),"\n"), "")&"', textKo: '"&SUBSTITUTE(SUBSTITUTE(SUBSTITUTE(AG33, CHAR(13), ""),CHAR(10),"\n"),"'","\'")&"', textEn: '"&SUBSTITUTE(SUBSTITUTE(SUBSTITUTE(AH33, CHAR(13), ""),CHAR(10),"\n"),"'","\'")&"'"&IF(Z33="○",", sealable: true","")&IF(AA33="○",", removable: true","")&"}") -> , '03-himika-o-n-2': {megami: 'himika', name: 'ラピッドファイア', nameEn: 'Quick Shot', nameZh: '速射', nameZhG1: '速射', nameKo: '래피드 파이어', ruby: '', rubyEn: '', rubyZh: 'Rapid Fire', baseType: 'normal', type: 'attack', range: '7-8', damage: '2/1', text: '【常時】連火-このカードがこのターンに使用した3枚目以降のカードならば、この《攻撃》は+1/+1となる。', textZh: '【常时】连火～若此牌是本回合你使用的第3张或更多的牌，则此《攻击》得+1/+1。', textZhG1: '【常时】连火-若本回合你已使用至少2张牌，则此《攻击》得+1/+1。', textKo: '【상시】연화-이 카드가 이 턴에 사용한 3장째 이후의 카드라면, 이 《공격》은 +1/+1이 된다.', textEn: 'Forced: Inferno - This attack gains +1/+1 if this is the third or later card you\'ve played this turn.'} | AO33: =IF($A33<>"", " /** 《"&$E33&"》 */ export const "&SUBSTITUTE(UPPER(IF(MID($A33, 3, 1)="-", RIGHT($A33,LEN($A33)-3), $A33)), "-", "_")&": TCardId = '"&$A33&"';", "") -> /** 《ラピッドファイア》 */ export const HIMIKA_O_N_2: TCardId = '03-himika-o-n-2'; | AP33: =IF($A33<>"", " | '"&$A33&"'", "") -> | '03-himika-o-n-2'
A34: 03-himika-A1-n-2 | B34: himika | C34: A1 | D34: 03-himika-o-n-2 | E34: 火炎流 | F34: かえんりゅう | G34: 火炎流 | H34: 火炎流 | J34: 화염류 | K34: Path of Flame | M34: 通常札 | R34: 攻撃 | T34: 1-3 | V34: 2/1 | AB34: 【常時】連火-このカードがこのターンに使用した3枚目以降のカードならば、この《攻撃》は+0/+1となる。 | AD34: 【常时】连火～若此牌是本回合你使用的第3张或更多的牌，则此《攻击》得+0/+1。 | AF34: 【常时】连火-若本回合你已使用至少2张牌，则此《攻击》得+0/+1。 | AG34: 【상시】연화-이 카드가 이 턴에 사용한 3장째 이후의 카드라면, 이 《공격》은 +0/+1이 된다. | AH34: Forced: Inferno - This attack gains +0/+1 if this is the third or later card you've played this turn. | AN34: =IF(A34="", "", IF(ROW()>=3, ", ", "")&"'"&A34&"': {megami: '"&B34&"'"&IF(C34<>"",", anotherID: '"&C34&"', replace: '"&D34&"'","")&", name: '"&SUBSTITUTE(E34,"'","\'")&"', nameEn: '"&SUBSTITUTE(K34,"'","\'")&"', nameZh: '"&SUBSTITUTE(G34,"'","\'")&"', nameZhG1: '"&SUBSTITUTE(H34,"'","\'")&"', nameKo: '"&SUBSTITUTE(J34,"'","\'")&"', ruby: '"&F34&"', rubyEn: '"&L34&IF(I34<>"", "', rubyZh: '"&I34, "")&"', baseType: '"&VLOOKUP(M34,マスタ!$A$1:$B$99,2,0)&"'"&IF(N34="○",", extra: true","")&IF(O34<>"",", extraFrom: '"&O34&"'","")&IF(P34<>"",", exchangableTo: '"&P34&"'","")&IF(Q34="○",", poison: true","")&IF(R34<>"", ", type: '"&VLOOKUP(R34,マスタ!$D$1:$E$99,2,0)&"'", "")&IF(S34<>"",", subType: '"&VLOOKUP(S34,マスタ!$D$1:$E$99,2,0)&"'","")&IF(T34<>"",", range: '"&T34&"'","")&IF(V34<>"",", damage: '"&V34&"'","")&IF(X34<>"",", capacity: '"&X34&"'","")&IF(Y34<>"",", cost: '"&Y34&"'","")&", text: '"&SUBSTITUTE(SUBSTITUTE(AB34, CHAR(13), ""),CHAR(10),"\n")&IF(AC34<>"", "', textAdditional: '"&SUBSTITUTE(SUBSTITUTE(AC34, CHAR(13), ""),CHAR(10),"\n"), "")&"', textZh: '"&SUBSTITUTE(SUBSTITUTE(SUBSTITUTE(AD34, CHAR(13), ""),CHAR(10),"\n"),"'","\'")&"', textZhG1: '"&SUBSTITUTE(SUBSTITUTE(SUBSTITUTE(AF34, CHAR(13), ""),CHAR(10),"\n"),"'","\'")&IF(AE34<>"", "', textZhAdditional: '"&SUBSTITUTE(SUBSTITUTE(AE34, CHAR(13), ""),CHAR(10),"\n"), "")&"', textKo: '"&SUBSTITUTE(SUBSTITUTE(SUBSTITUTE(AG34, CHAR(13), ""),CHAR(10),"\n"),"'","\'")&"', textEn: '"&SUBSTITUTE(SUBSTITUTE(SUBSTITUTE(AH34, CHAR(13), ""),CHAR(10),"\n"),"'","\'")&"'"&IF(Z34="○",", sealable: true","")&IF(AA34="○",", removable: true","")&"}") -> , '03-himika-A1-n-2': {megami: 'himika', anotherID: 'A1', replace: '03-himika-o-n-2', name: '火炎流', nameEn: 'Path of Flame', nameZh: '火炎流', nameZhG1: '火炎流', nameKo: '화염류', ruby: 'かえんりゅう', rubyEn: '', baseType: 'normal', type: 'attack', range: '1-3', damage: '2/1', text: '【常時】連火-このカードがこのターンに使用した3枚目以降のカードならば、この《攻撃》は+0/+1となる。', textZh: '【常时】连火～若此牌是本回合你使用的第3张或更多的牌，则此《攻击》得+0/+1。', textZhG1: '【常时】连火-若本回合你已使用至少2张牌，则此《攻击》得+0/+1。', textKo: '【상시】연화-이 카드가 이 턴에 사용한 3장째 이후의 카드라면, 이 《공격》은 +0/+1이 된다.', textEn: 'Forced: Inferno - This attack gains +0/+1 if this is the third or later card you\'ve played this turn.'} | AO34: =IF($A34<>"", " /** 《"&$E34&"》 */ export const "&SUBSTITUTE(UPPER(IF(MID($A34, 3, 1)="-", RIGHT($A34,LEN($A34)-3), $A34)), "-", "_")&": TCardId = '"&$A34&"';", "") -> /** 《火炎流》 */ export const HIMIKA_A1_N_2: TCardId = '03-himika-A1-n-2'; | AP34: =IF($A34<>"", " | '"&$A34&"'", "") -> | '03-himika-A1-n-2'
A35: 03-himika-o-n-3 | B35: himika | E35: マグナムカノン | G35: 麦林加农炮 | H35: 麦林加农炮 | I35: Magnum Cannon | J35: 매그넘 캐논 | K35: Magnum | M35: 通常札 | R35: 攻撃 | T35: 5-8 | V35: 3/2 | AB35: 【攻撃後】自ライフ→ダスト：1 | AD35: 【攻击后】自命→1→虚 | AF35: 【攻击后】自命（1）→虚 | AG35: 【공격후】자신 라이프→더스트：1 | AH35: After Attack: Your Life (1)→ Shadow | AN35: =IF(A35="", "", IF(ROW()>=3, ", ", "")&"'"&A35&"': {megami: '"&B35&"'"&IF(C35<>"",", anotherID: '"&C35&"', replace: '"&D35&"'","")&", name: '"&SUBSTITUTE(E35,"'","\'")&"', nameEn: '"&SUBSTITUTE(K35,"'","\'")&"', nameZh: '"&SUBSTITUTE(G35,"'","\'")&"', nameZhG1: '"&SUBSTITUTE(H35,"'","\'")&"', nameKo: '"&SUBSTITUTE(J35,"'","\'")&"', ruby: '"&F35&"', rubyEn: '"&L35&IF(I35<>"", "', rubyZh: '"&I35, "")&"', baseType: '"&VLOOKUP(M35,マスタ!$A$1:$B$99,2,0)&"'"&IF(N35="○",", extra: true","")&IF(O35<>"",", extraFrom: '"&O35&"'","")&IF(P35<>"",", exchangableTo: '"&P35&"'","")&IF(Q35="○",", poison: true","")&IF(R35<>"", ", type: '"&VLOOKUP(R35,マスタ!$D$1:$E$99,2,0)&"'", "")&IF(S35<>"",", subType: '"&VLOOKUP(S35,マスタ!$D$1:$E$99,2,0)&"'","")&IF(T35<>"",", range: '"&T35&"'","")&IF(V35<>"",", damage: '"&V35&"'","")&IF(X35<>"",", capacity: '"&X35&"'","")&IF(Y35<>"",", cost: '"&Y35&"'","")&", text: '"&SUBSTITUTE(SUBSTITUTE(AB35, CHAR(13), ""),CHAR(10),"\n")&IF(AC35<>"", "', textAdditional: '"&SUBSTITUTE(SUBSTITUTE(AC35, CHAR(13), ""),CHAR(10),"\n"), "")&"', textZh: '"&SUBSTITUTE(SUBSTITUTE(SUBSTITUTE(AD35, CHAR(13), ""),CHAR(10),"\n"),"'","\'")&"', textZhG1: '"&SUBSTITUTE(SUBSTITUTE(SUBSTITUTE(AF35, CHAR(13), ""),CHAR(10),"\n"),"'","\'")&IF(AE35<>"", "', textZhAdditional: '"&SUBSTITUTE(SUBSTITUTE(AE35, CHAR(13), ""),CHAR(10),"\n"), "")&"', textKo: '"&SUBSTITUTE(SUBSTITUTE(SUBSTITUTE(AG35, CHAR(13), ""),CHAR(10),"\n"),"'","\'")&"', textEn: '"&SUBSTITUTE(SUBSTITUTE(SUBSTITUTE(AH35, CHAR(13), ""),CHAR(10),"\n"),"'","\'")&"'"&IF(Z35="○",", sealable: true","")&IF(AA35="○",", removable: true","")&"}") -> , '03-himika-o-n-3': {megami: 'himika', name: 'マグナムカノン', nameEn: 'Magnum', nameZh: '麦林加农炮', nameZhG1: '麦林加农炮', nameKo: '매그넘 캐논', ruby: '', rubyEn: '', rubyZh: 'Magnum Cannon', baseType: 'normal', type: 'attack', range: '5-8', damage: '3/2', text: '【攻撃後】自ライフ→ダスト：1', textZh: '【攻击后】自命→1→虚', textZhG1: '【攻击后】自命（1）→虚', textKo: '【공격후】자신 라이프→더스트：1', textEn: 'After Attack:\nYour Life (1)→ Shadow'} | AO35: =IF($A35<>"", " /** 《"&$E35&"》 */ export const "&SUBSTITUTE(UPPER(IF(MID($A35, 3, 1)="-", RIGHT($A35,LEN($A35)-3), $A35)), "-", "_")&": TCardId = '"&$A35&"';", "") -> /** 《マグナムカノン》 */ export const HIMIKA_O_N_3: TCardId = '03-himika-o-n-3'; | AP35: =IF($A35<>"", " | '"&$A35&"'", "") -> | '03-himika-o-n-3'
A36: 03-himika-o-n-4 | B36: himika | E36: フルバースト | G36: 全弹发射 | H36: 完全爆破 | I36: Full Burst | J36: 풀 버스트 | K36: Barrage | M36: 通常札 | R36: 攻撃 | S36: 全力 | T36: 5-9 | V36: 3/1 | AB36: 【常時】この《攻撃》がダメージを与えるならば、相手は片方を選ぶのではなく両方のダメージを受ける。 | AD36: 【常时】此《攻击》对敌装和敌命均造成伤害。 | AF36: 【常时】对方结算伤害时，装和命需要同时结算。 | AG36: 【상시】이 《공격》이 대미지를 준다면, 상대는 한쪽을 고르는 것이 아닌 양방 모두의 대미지를 받는다. | AH36: Forced: This attack deals Damage to both Aura and Life. | AN36: =IF(A36="", "", IF(ROW()>=3, ", ", "")&"'"&A36&"': {megami: '"&B36&"'"&IF(C36<>"",", anotherID: '"&C36&"', replace: '"&D36&"'","")&", name: '"&SUBSTITUTE(E36,"'","\'")&"', nameEn: '"&SUBSTITUTE(K36,"'","\'")&"', nameZh: '"&SUBSTITUTE(G36,"'","\'")&"', nameZhG1: '"&SUBSTITUTE(H36,"'","\'")&"', nameKo: '"&SUBSTITUTE(J36,"'","\'")&"', ruby: '"&F36&"', rubyEn: '"&L36&IF(I36<>"", "', rubyZh: '"&I36, "")&"', baseType: '"&VLOOKUP(M36,マスタ!$A$1:$B$99,2,0)&"'"&IF(N36="○",", extra: true","")&IF(O36<>"",", extraFrom: '"&O36&"'","")&IF(P36<>"",", exchangableTo: '"&P36&"'","")&IF(Q36="○",", poison: true","")&IF(R36<>"", ", type: '"&VLOOKUP(R36,マスタ!$D$1:$E$99,2,0)&"'", "")&IF(S36<>"",", subType: '"&VLOOKUP(S36,マスタ!$D$1:$E$99,2,0)&"'","")&IF(T36<>"",", range: '"&T36&"'","")&IF(V36<>"",", damage: '"&V36&"'","")&IF(X36<>"",", capacity: '"&X36&"'","")&IF(Y36<>"",", cost: '"&Y36&"'","")&", text: '"&SUBSTITUTE(SUBSTITUTE(AB36, CHAR(13), ""),CHAR(10),"\n")&IF(AC36<>"", "', textAdditional: '"&SUBSTITUTE(SUBSTITUTE(AC36, CHAR(13), ""),CHAR(10),"\n"), "")&"', textZh: '"&SUBSTITUTE(SUBSTITUTE(SUBSTITUTE(AD36, CHAR(13), ""),CHAR(10),"\n"),"'","\'")&"', textZhG1: '"&SUBSTITUTE(SUBSTITUTE(SUBSTITUTE(AF36, CHAR(13), ""),CHAR(10),"\n"),"'","\'")&IF(AE36<>"", "', textZhAdditional: '"&SUBSTITUTE(SUBSTITUTE(AE36, CHAR(13), ""),CHAR(10),"\n"), "")&"', textKo: '"&SUBSTITUTE(SUBSTITUTE(SUBSTITUTE(AG36, CHAR(13), ""),CHAR(10),"\n"),"'","\'")&"', textEn: '"&SUBSTITUTE(SUBSTITUTE(SUBSTITUTE(AH36, CHAR(13), ""),CHAR(10),"\n"),"'","\'")&"'"&IF(Z36="○",", sealable: true","")&IF(AA36="○",", removable: true","")&"}") -> , '03-himika-o-n-4': {megami: 'himika', name: 'フルバースト', nameEn: 'Barrage', nameZh: '全弹发射', nameZhG1: '完全爆破', nameKo: '풀 버스트', ruby: '', rubyEn: '', rubyZh: 'Full Burst', baseType: 'normal', type: 'attack', subType: 'fullpower', range: '5-9', damage: '3/1', text: '【常時】この《攻撃》がダメージを与えるならば、相手は片方を選ぶのではなく両方のダメージを受ける。', textZh: '【常时】此《攻击》对敌装和敌命均造成伤害。', textZhG1: '【常时】对方结算伤害时，装和命需要同时结算。', textKo: '【상시】이 《공격》이 대미지를 준다면, 상대는 한쪽을 고르는 것이 아닌 양방 모두의 대미지를 받는다.', textEn: 'Forced: This attack deals Damage to both Aura and Life.'} | AO36: =IF($A36<>"", " /** 《"&$E36&"》 */ export const "&SUBSTITUTE(UPPER(IF(MID($A36, 3, 1)="-", RIGHT($A36,LEN($A36)-3), $A36)), "-", "_")&": TCardId = '"&$A36&"';", "") -> /** 《フルバースト》 */ export const HIMIKA_O_N_4: TCardId = '03-himika-o-n-4'; | AP36: =IF($A36<>"", " | '"&$A36&"'", "") -> | '03-himika-o-n-4'
A37: 03-himika-o-n-5 | B37: himika | E37: バックステップ | G37: 后撤 | H37: 后跳 | I37: Backstep | J37: 백스탭 | K37: Backstep | M37: 通常札 | R37: 行動 | AB37: カードを1枚引く。 ダスト→間合：1 | AD37: 抓一张牌。 虚→1→距 | AF37: 抓一张牌。 虚（1）→距 | AG37: 카드를 1장 뽑는다. 더스트→간격：1 | AH37: Draw a card. Shadow (1)→ Distance | AN37: =IF(A37="", "", IF(ROW()>=3, ", ", "")&"'"&A37&"': {megami: '"&B37&"'"&IF(C37<>"",", anotherID: '"&C37&"', replace: '"&D37&"'","")&", name: '"&SUBSTITUTE(E37,"'","\'")&"', nameEn: '"&SUBSTITUTE(K37,"'","\'")&"', nameZh: '"&SUBSTITUTE(G37,"'","\'")&"', nameZhG1: '"&SUBSTITUTE(H37,"'","\'")&"', nameKo: '"&SUBSTITUTE(J37,"'","\'")&"', ruby: '"&F37&"', rubyEn: '"&L37&IF(I37<>"", "', rubyZh: '"&I37, "")&"', baseType: '"&VLOOKUP(M37,マスタ!$A$1:$B$99,2,0)&"'"&IF(N37="○",", extra: true","")&IF(O37<>"",", extraFrom: '"&O37&"'","")&IF(P37<>"",", exchangableTo: '"&P37&"'","")&IF(Q37="○",", poison: true","")&IF(R37<>"", ", type: '"&VLOOKUP(R37,マスタ!$D$1:$E$99,2,0)&"'", "")&IF(S37<>"",", subType: '"&VLOOKUP(S37,マスタ!$D$1:$E$99,2,0)&"'","")&IF(T37<>"",", range: '"&T37&"'","")&IF(V37<>"",", damage: '"&V37&"'","")&IF(X37<>"",", capacity: '"&X37&"'","")&IF(Y37<>"",", cost: '"&Y37&"'","")&", text: '"&SUBSTITUTE(SUBSTITUTE(AB37, CHAR(13), ""),CHAR(10),"\n")&IF(AC37<>"", "', textAdditional: '"&SUBSTITUTE(SUBSTITUTE(AC37, CHAR(13), ""),CHAR(10),"\n"), "")&"', textZh: '"&SUBSTITUTE(SUBSTITUTE(SUBSTITUTE(AD37, CHAR(13), ""),CHAR(10),"\n"),"'","\'")&"', textZhG1: '"&SUBSTITUTE(SUBSTITUTE(SUBSTITUTE(AF37, CHAR(13), ""),CHAR(10),"\n"),"'","\'")&IF(AE37<>"", "', textZhAdditional: '"&SUBSTITUTE(SUBSTITUTE(AE37, CHAR(13), ""),CHAR(10),"\n"), "")&"', textKo: '"&SUBSTITUTE(SUBSTITUTE(SUBSTITUTE(AG37, CHAR(13), ""),CHAR(10),"\n"),"'","\'")&"', textEn: '"&SUBSTITUTE(SUBSTITUTE(SUBSTITUTE(AH37, CHAR(13), ""),CHAR(10),"\n"),"'","\'")&"'"&IF(Z37="○",", sealable: true","")&IF(AA37="○",", removable: true","")&"}") -> , '03-himika-o-n-5': {megami: 'himika', name: 'バックステップ', nameEn: 'Backstep', nameZh: '后撤', nameZhG1: '后跳', nameKo: '백스탭', ruby: '', rubyEn: '', rubyZh: 'Backstep', baseType: 'normal', type: 'action', text: 'カードを1枚引く。 \nダスト→間合：1', textZh: '抓一张牌。 \n虚→1→距', textZhG1: '抓一张牌。 \n虚（1）→距', textKo: '카드를 1장 뽑는다. 더스트→간격：1', textEn: 'Draw a card.\n\nShadow (1)→ Distance'} | AO37: =IF($A37<>"", " /** 《"&$E37&"》 */ export const "&SUBSTITUTE(UPPER(IF(MID($A37, 3, 1)="-", RIGHT($A37,LEN($A37)-3), $A37)), "-", "_")&": TCardId = '"&$A37&"';", "") -> /** 《バックステップ》 */ export const HIMIKA_O_N_5: TCardId = '03-himika-o-n-5'; | AP37: =IF($A37<>"", " | '"&$A37&"'", "") -> | '03-himika-o-n-5'
A38: 03-himika-A1-n-5 | B38: himika | C38: A1 | D38: 03-himika-o-n-5 | E38: 殺意 | F38: さつい | G38: 杀意 | H38: 杀意 | J38: 살의 | K38: Killing Intent | M38: 通常札 | R38: 行動 | AB38: あなたの手札が0枚ならば、相オーラ→ダスト：2 | AD38: 若你没有手牌，则：敌装→2→虚。 | AF38: 若你没有手牌，则敌装（2）→虚。 | AG38: 당신의 손패가 0장이라면, 상대 오라→더스트：2 | AH38: If you have no cards in your hand: Opponent's Aura (2)→ Shadow | AN38: =IF(A38="", "", IF(ROW()>=3, ", ", "")&"'"&A38&"': {megami: '"&B38&"'"&IF(C38<>"",", anotherID: '"&C38&"', replace: '"&D38&"'","")&", name: '"&SUBSTITUTE(E38,"'","\'")&"', nameEn: '"&SUBSTITUTE(K38,"'","\'")&"', nameZh: '"&SUBSTITUTE(G38,"'","\'")&"', nameZhG1: '"&SUBSTITUTE(H38,"'","\'")&"', nameKo: '"&SUBSTITUTE(J38,"'","\'")&"', ruby: '"&F38&"', rubyEn: '"&L38&IF(I38<>"", "', rubyZh: '"&I38, "")&"', baseType: '"&VLOOKUP(M38,マスタ!$A$1:$B$99,2,0)&"'"&IF(N38="○",", extra: true","")&IF(O38<>"",", extraFrom: '"&O38&"'","")&IF(P38<>"",", exchangableTo: '"&P38&"'","")&IF(Q38="○",", poison: true","")&IF(R38<>"", ", type: '"&VLOOKUP(R38,マスタ!$D$1:$E$99,2,0)&"'", "")&IF(S38<>"",", subType: '"&VLOOKUP(S38,マスタ!$D$1:$E$99,2,0)&"'","")&IF(T38<>"",", range: '"&T38&"'","")&IF(V38<>"",", damage: '"&V38&"'","")&IF(X38<>"",", capacity: '"&X38&"'","")&IF(Y38<>"",", cost: '"&Y38&"'","")&", text: '"&SUBSTITUTE(SUBSTITUTE(AB38, CHAR(13), ""),CHAR(10),"\n")&IF(AC38<>"", "', textAdditional: '"&SUBSTITUTE(SUBSTITUTE(AC38, CHAR(13), ""),CHAR(10),"\n"), "")&"', textZh: '"&SUBSTITUTE(SUBSTITUTE(SUBSTITUTE(AD38, CHAR(13), ""),CHAR(10),"\n"),"'","\'")&"', textZhG1: '"&SUBSTITUTE(SUBSTITUTE(SUBSTITUTE(AF38, CHAR(13), ""),CHAR(10),"\n"),"'","\'")&IF(AE38<>"", "', textZhAdditional: '"&SUBSTITUTE(SUBSTITUTE(AE38, CHAR(13), ""),CHAR(10),"\n"), "")&"', textKo: '"&SUBSTITUTE(SUBSTITUTE(SUBSTITUTE(AG38, CHAR(13), ""),CHAR(10),"\n"),"'","\'")&"', textEn: '"&SUBSTITUTE(SUBSTITUTE(SUBSTITUTE(AH38, CHAR(13), ""),CHAR(10),"\n"),"'","\'")&"'"&IF(Z38="○",", sealable: true","")&IF(AA38="○",", removable: true","")&"}") -> , '03-himika-A1-n-5': {megami: 'himika', anotherID: 'A1', replace: '03-himika-o-n-5', name: '殺意', nameEn: 'Killing Intent', nameZh: '杀意', nameZhG1: '杀意', nameKo: '살의', ruby: 'さつい', rubyEn: '', baseType: 'normal', type: 'action', text: 'あなたの手札が0枚ならば、相オーラ→ダスト：2', textZh: '若你没有手牌，则：敌装→2→虚。', textZhG1: '若你没有手牌，则敌装（2）→虚。', textKo: '당신의 손패가 0장이라면, 상대 오라→더스트：2', textEn: 'If you have no cards in your hand:\nOpponent\'s Aura (2)→ Shadow'} | AO38: =IF($A38<>"", " /** 《"&$E38&"》 */ export const "&SUBSTITUTE(UPPER(IF(MID($A38, 3, 1)="-", RIGHT($A38,LEN($A38)-3), $A38)), "-", "_")&": TCardId = '"&$A38&"';", "") -> /** 《殺意》 */ export const HIMIKA_A1_N_5: TCardId = '03-himika-A1-n-5'; | AP38: =IF($A38<>"", " | '"&$A38&"'", "") -> | '03-himika-A1-n-5'
A39: 03-himika-o-n-6 | B39: himika | E39: バックドラフト | G39: 回燃 | H39: 回燃 | I39: Backdraft | J39: 백드래프트 | K39: Backdraft | M39: 通常札 | R39: 行動 | AB39: 相手を畏縮させる。 連火-このカードがこのターンに使用した3枚目以降のカードならば、このターンにあなたが次に行う他のメガミによる《攻撃》を+1/+1する。 | AD39: 令对手畏缩。 连火～若此牌是本回合你使用的第3张或更多的牌，则本回合你的另一柱女神的下一次《攻击》得+1/+1。 | AF39: 对手畏缩。 连火-若本回合你已使用至少2张牌，则本回合你的另一柱女武神的下一次《攻击》得+1/+1。 | AG39: 상대를 위축시킨다。 연화-이 카드가 이 턴에 사용한 3장째 이후의 카드라면, 이 턴 당신이 다음에 행하는 다른 여신에 의한 《공격》을 +1/+1 한다. | AH39: Flinch your opponent. Inferno - If this is the third or later card you've played this turn, the next attack from your other Megami that you make this turn gains +1/+1. | AN39: =IF(A39="", "", IF(ROW()>=3, ", ", "")&"'"&A39&"': {megami: '"&B39&"'"&IF(C39<>"",", anotherID: '"&C39&"', replace: '"&D39&"'","")&", name: '"&SUBSTITUTE(E39,"'","\'")&"', nameEn: '"&SUBSTITUTE(K39,"'","\'")&"', nameZh: '"&SUBSTITUTE(G39,"'","\'")&"', nameZhG1: '"&SUBSTITUTE(H39,"'","\'")&"', nameKo: '"&SUBSTITUTE(J39,"'","\'")&"', ruby: '"&F39&"', rubyEn: '"&L39&IF(I39<>"", "', rubyZh: '"&I39, "")&"', baseType: '"&VLOOKUP(M39,マスタ!$A$1:$B$99,2,0)&"'"&IF(N39="○",", extra: true","")&IF(O39<>"",", extraFrom: '"&O39&"'","")&IF(P39<>"",", exchangableTo: '"&P39&"'","")&IF(Q39="○",", poison: true","")&IF(R39<>"", ", type: '"&VLOOKUP(R39,マスタ!$D$1:$E$99,2,0)&"'", "")&IF(S39<>"",", subType: '"&VLOOKUP(S39,マスタ!$D$1:$E$99,2,0)&"'","")&IF(T39<>"",", range: '"&T39&"'","")&IF(V39<>"",", damage: '"&V39&"'","")&IF(X39<>"",", capacity: '"&X39&"'","")&IF(Y39<>"",", cost: '"&Y39&"'","")&", text: '"&SUBSTITUTE(SUBSTITUTE(AB39, CHAR(13), ""),CHAR(10),"\n")&IF(AC39<>"", "', textAdditional: '"&SUBSTITUTE(SUBSTITUTE(AC39, CHAR(13), ""),CHAR(10),"\n"), "")&"', textZh: '"&SUBSTITUTE(SUBSTITUTE(SUBSTITUTE(AD39, CHAR(13), ""),CHAR(10),"\n"),"'","\'")&"', textZhG1: '"&SUBSTITUTE(SUBSTITUTE(SUBSTITUTE(AF39, CHAR(13), ""),CHAR(10),"\n"),"'","\'")&IF(AE39<>"", "', textZhAdditional: '"&SUBSTITUTE(SUBSTITUTE(AE39, CHAR(13), ""),CHAR(10),"\n"), "")&"', textKo: '"&SUBSTITUTE(SUBSTITUTE(SUBSTITUTE(AG39, CHAR(13), ""),CHAR(10),"\n"),"'","\'")&"', textEn: '"&SUBSTITUTE(SUBSTITUTE(SUBSTITUTE(AH39, CHAR(13), ""),CHAR(10),"\n"),"'","\'")&"'"&IF(Z39="○",", sealable: true","")&IF(AA39="○",", removable: true","")&"}") -> , '03-himika-o-n-6': {megami: 'himika', name: 'バックドラフト', nameEn: 'Backdraft', nameZh: '回燃', nameZhG1: '回燃', nameKo: '백드래프트', ruby: '', rubyEn: '', rubyZh: 'Backdraft', baseType: 'normal', type: 'action', text: '相手を畏縮させる。\n連火-このカードがこのターンに使用した3枚目以降のカードならば、このターンにあなたが次に行う他のメガミによる《攻撃》を+1/+1する。', textZh: '令对手畏缩。\n连火～若此牌是本回合你使用的第3张或更多的牌，则本回合你的另一柱女神的下一次《攻击》得+1/+1。', textZhG1: '对手畏缩。\n连火-若本回合你已使用至少2张牌，则本回合你的另一柱女武神的下一次《攻击》得+1/+1。', textKo: '상대를 위축시킨다。\n 연화-이 카드가 이 턴에 사용한 3장째 이후의 카드라면, 이 턴 당신이 다음에 행하는 다른 여신에 의한 《공격》을 +1/+1 한다.', textEn: 'Flinch your opponent.\n\nInferno - If this is the third or later card you\'ve played this turn, the next attack from your other Megami that you make this turn gains +1/+1.'} | AO39: =IF($A39<>"", " /** 《"&$E39&"》 */ export const "&SUBSTITUTE(UPPER(IF(MID($A39, 3, 1)="-", RIGHT($A39,LEN($A39)-3), $A39)), "-", "_")&": TCardId = '"&$A39&"';", "") -> /** 《バックドラフト》 */ export const HIMIKA_O_N_6: TCardId = '03-himika-o-n-6'; | AP39: =IF($A39<>"", " | '"&$A39&"'", "") -> | '03-himika-o-n-6'
A40: 03-himika-o-n-7 | B40: himika | E40: スモーク | G40: 烟幕 | H40: 迷烟 | I40: Smoke | J40: 스모크 | K40: Smoke | M40: 通常札 | R40: 付与 | X40: 3 | AB40: 【展開中】カードの矢印(→)により間合にある桜花結晶は移動しない。 | AD40: 【展开中】距中的樱花结晶不能被卡牌上的箭头效果移出距。 | AF40: 【展开中】所有从距中移出樱花结晶的卡牌效果无效。 | AG40: 【전개중】간격에 있는 벚꽃 결정은 카드의 화살표(→)에 의해서는 이동하지 않는다. | AH40: Ongoing: Cards cannot move Sakura tokens from Distance using arrows (→). | AN40: =IF(A40="", "", IF(ROW()>=3, ", ", "")&"'"&A40&"': {megami: '"&B40&"'"&IF(C40<>"",", anotherID: '"&C40&"', replace: '"&D40&"'","")&", name: '"&SUBSTITUTE(E40,"'","\'")&"', nameEn: '"&SUBSTITUTE(K40,"'","\'")&"', nameZh: '"&SUBSTITUTE(G40,"'","\'")&"', nameZhG1: '"&SUBSTITUTE(H40,"'","\'")&"', nameKo: '"&SUBSTITUTE(J40,"'","\'")&"', ruby: '"&F40&"', rubyEn: '"&L40&IF(I40<>"", "', rubyZh: '"&I40, "")&"', baseType: '"&VLOOKUP(M40,マスタ!$A$1:$B$99,2,0)&"'"&IF(N40="○",", extra: true","")&IF(O40<>"",", extraFrom: '"&O40&"'","")&IF(P40<>"",", exchangableTo: '"&P40&"'","")&IF(Q40="○",", poison: true","")&IF(R40<>"", ", type: '"&VLOOKUP(R40,マスタ!$D$1:$E$99,2,0)&"'", "")&IF(S40<>"",", subType: '"&VLOOKUP(S40,マスタ!$D$1:$E$99,2,0)&"'","")&IF(T40<>"",", range: '"&T40&"'","")&IF(V40<>"",", damage: '"&V40&"'","")&IF(X40<>"",", capacity: '"&X40&"'","")&IF(Y40<>"",", cost: '"&Y40&"'","")&", text: '"&SUBSTITUTE(SUBSTITUTE(AB40, CHAR(13), ""),CHAR(10),"\n")&IF(AC40<>"", "', textAdditional: '"&SUBSTITUTE(SUBSTITUTE(AC40, CHAR(13), ""),CHAR(10),"\n"), "")&"', textZh: '"&SUBSTITUTE(SUBSTITUTE(SUBSTITUTE(AD40, CHAR(13), ""),CHAR(10),"\n"),"'","\'")&"', textZhG1: '"&SUBSTITUTE(SUBSTITUTE(SUBSTITUTE(AF40, CHAR(13), ""),CHAR(10),"\n"),"'","\'")&IF(AE40<>"", "', textZhAdditional: '"&SUBSTITUTE(SUBSTITUTE(AE40, CHAR(13), ""),CHAR(10),"\n"), "")&"', textKo: '"&SUBSTITUTE(SUBSTITUTE(SUBSTITUTE(AG40, CHAR(13), ""),CHAR(10),"\n"),"'","\'")&"', textEn: '"&SUBSTITUTE(SUBSTITUTE(SUBSTITUTE(AH40, CHAR(13), ""),CHAR(10),"\n"),"'","\'")&"'"&IF(Z40="○",", sealable: true","")&IF(AA40="○",", removable: true","")&"}") -> , '03-himika-o-n-7': {megami: 'himika', name: 'スモーク', nameEn: 'Smoke', nameZh: '烟幕', nameZhG1: '迷烟', nameKo: '스모크', ruby: '', rubyEn: '', rubyZh: 'Smoke', baseType: 'normal', type: 'enhance', capacity: '3', text: '【展開中】カードの矢印(→)により間合にある桜花結晶は移動しない。', textZh: '【展开中】距中的樱花结晶不能被卡牌上的箭头效果移出距。', textZhG1: '【展开中】所有从距中移出樱花结晶的卡牌效果无效。', textKo: '【전개중】간격에 있는 벚꽃 결정은 카드의 화살표(→)에 의해서는 이동하지 않는다.', textEn: 'Ongoing: Cards cannot move Sakura tokens from Distance using arrows (→).'} | AO40: =IF($A40<>"", " /** 《"&$E40&"》 */ export const "&SUBSTITUTE(UPPER(IF(MID($A40, 3, 1)="-", RIGHT($A40,LEN($A40)-3), $A40)), "-", "_")&": TCardId = '"&$A40&"';", "") -> /** 《スモーク》 */ export const HIMIKA_O_N_7: TCardId = '03-himika-o-n-7'; | AP40: =IF($A40<>"", " | '"&$A40&"'", "") -> | '03-himika-o-n-7'
A41: 03-himika-o-s-1 | B41: himika | E41: レッドバレット | G41: 真红凶弹 | H41: 真红凶弹 | I41: Red Bullet | J41: 레드 불릿 | K41: Red Bullet | M41: 切札 | R41: 攻撃 | T41: 5-10 | V41: 3/1 | Y41: 0 | AN41: =IF(A41="", "", IF(ROW()>=3, ", ", "")&"'"&A41&"': {megami: '"&B41&"'"&IF(C41<>"",", anotherID: '"&C41&"', replace: '"&D41&"'","")&", name: '"&SUBSTITUTE(E41,"'","\'")&"', nameEn: '"&SUBSTITUTE(K41,"'","\'")&"', nameZh: '"&SUBSTITUTE(G41,"'","\'")&"', nameZhG1: '"&SUBSTITUTE(H41,"'","\'")&"', nameKo: '"&SUBSTITUTE(J41,"'","\'")&"', ruby: '"&F41&"', rubyEn: '"&L41&IF(I41<>"", "', rubyZh: '"&I41, "")&"', baseType: '"&VLOOKUP(M41,マスタ!$A$1:$B$99,2,0)&"'"&IF(N41="○",", extra: true","")&IF(O41<>"",", extraFrom: '"&O41&"'","")&IF(P41<>"",", exchangableTo: '"&P41&"'","")&IF(Q41="○",", poison: true","")&IF(R41<>"", ", type: '"&VLOOKUP(R41,マスタ!$D$1:$E$99,2,0)&"'", "")&IF(S41<>"",", subType: '"&VLOOKUP(S41,マスタ!$D$1:$E$99,2,0)&"'","")&IF(T41<>"",", range: '"&T41&"'","")&IF(V41<>"",", damage: '"&V41&"'","")&IF(X41<>"",", capacity: '"&X41&"'","")&IF(Y41<>"",", cost: '"&Y41&"'","")&", text: '"&SUBSTITUTE(SUBSTITUTE(AB41, CHAR(13), ""),CHAR(10),"\n")&IF(AC41<>"", "', textAdditional: '"&SUBSTITUTE(SUBSTITUTE(AC41, CHAR(13), ""),CHAR(10),"\n"), "")&"', textZh: '"&SUBSTITUTE(SUBSTITUTE(SUBSTITUTE(AD41, CHAR(13), ""),CHAR(10),"\n"),"'","\'")&"', textZhG1: '"&SUBSTITUTE(SUBSTITUTE(SUBSTITUTE(AF41, CHAR(13), ""),CHAR(10),"\n"),"'","\'")&IF(AE41<>"", "', textZhAdditional: '"&SUBSTITUTE(SUBSTITUTE(AE41, CHAR(13), ""),CHAR(10),"\n"), "")&"', textKo: '"&SUBSTITUTE(SUBSTITUTE(SUBSTITUTE(AG41, CHAR(13), ""),CHAR(10),"\n"),"'","\'")&"', textEn: '"&SUBSTITUTE(SUBSTITUTE(SUBSTITUTE(AH41, CHAR(13), ""),CHAR(10),"\n"),"'","\'")&"'"&IF(Z41="○",", sealable: true","")&IF(AA41="○",", removable: true","")&"}") -> , '03-himika-o-s-1': {megami: 'himika', name: 'レッドバレット', nameEn: 'Red Bullet', nameZh: '真红凶弹', nameZhG1: '真红凶弹', nameKo: '레드 불릿', ruby: '', rubyEn: '', rubyZh: 'Red Bullet', baseType: 'special', type: 'attack', range: '5-10', damage: '3/1', cost: '0', text: '', textZh: '', textZhG1: '', textKo: '', textEn: ''} | AO41: =IF($A41<>"", " /** 《"&$E41&"》 */ export const "&SUBSTITUTE(UPPER(IF(MID($A41, 3, 1)="-", RIGHT($A41,LEN($A41)-3), $A41)), "-", "_")&": TCardId = '"&$A41&"';", "") -> /** 《レッドバレット》 */ export const HIMIKA_O_S_1: TCardId = '03-himika-o-s-1'; | AP41: =IF($A41<>"", " | '"&$A41&"'", "") -> | '03-himika-o-s-1'
A42: 03-himika-o-s-2 | B42: himika | E42: クリムゾンゼロ | G42: 绯红零时 | H42: 绯红零时 | I42: Crimson Zero | J42: 크림슨 제로 | K42: Crimson Zero | M42: 切札 | R42: 攻撃 | T42: 0-2 | V42: 2/2 | Y42: 5 | AB42: 【常時】この《攻撃》がダメージを与えるならば、相手は片方を選ぶのではなく両方のダメージを受ける。 【常時】現在の間合が0ならば、この《攻撃》は対応不可を得る。 | AD42: 【常时】此《攻击》对敌装和敌命均造成伤害。 【常时】若当前距离为0，则此《攻击》得不可被对应。 | AF42: 【常时】此牌对装和命均造成伤害。 【常时】若当前距离等于0，则此《攻击》得不可被对应。 | AG42: 【상시】이 《공격》이 대미지를 주었다면, 상대는 한쪽을 고르는 것이 아닌 양쪽의 대미지를 받는다. 【상시】현재 간격이 0이라면, 이 《공격》은 대응불가를 얻는다. | AH42: Forced: This attack deals Damage to both Aura and Life. Forced: If the current Distance is 0, this attack gains No Reactions. | AN42: =IF(A42="", "", IF(ROW()>=3, ", ", "")&"'"&A42&"': {megami: '"&B42&"'"&IF(C42<>"",", anotherID: '"&C42&"', replace: '"&D42&"'","")&", name: '"&SUBSTITUTE(E42,"'","\'")&"', nameEn: '"&SUBSTITUTE(K42,"'","\'")&"', nameZh: '"&SUBSTITUTE(G42,"'","\'")&"', nameZhG1: '"&SUBSTITUTE(H42,"'","\'")&"', nameKo: '"&SUBSTITUTE(J42,"'","\'")&"', ruby: '"&F42&"', rubyEn: '"&L42&IF(I42<>"", "', rubyZh: '"&I42, "")&"', baseType: '"&VLOOKUP(M42,マスタ!$A$1:$B$99,2,0)&"'"&IF(N42="○",", extra: true","")&IF(O42<>"",", extraFrom: '"&O42&"'","")&IF(P42<>"",", exchangableTo: '"&P42&"'","")&IF(Q42="○",", poison: true","")&IF(R42<>"", ", type: '"&VLOOKUP(R42,マスタ!$D$1:$E$99,2,0)&"'", "")&IF(S42<>"",", subType: '"&VLOOKUP(S42,マスタ!$D$1:$E$99,2,0)&"'","")&IF(T42<>"",", range: '"&T42&"'","")&IF(V42<>"",", damage: '"&V42&"'","")&IF(X42<>"",", capacity: '"&X42&"'","")&IF(Y42<>"",", cost: '"&Y42&"'","")&", text: '"&SUBSTITUTE(SUBSTITUTE(AB42, CHAR(13), ""),CHAR(10),"\n")&IF(AC42<>"", "', textAdditional: '"&SUBSTITUTE(SUBSTITUTE(AC42, CHAR(13), ""),CHAR(10),"\n"), "")&"', textZh: '"&SUBSTITUTE(SUBSTITUTE(SUBSTITUTE(AD42, CHAR(13), ""),CHAR(10),"\n"),"'","\'")&"', textZhG1: '"&SUBSTITUTE(SUBSTITUTE(SUBSTITUTE(AF42, CHAR(13), ""),CHAR(10),"\n"),"'","\'")&IF(AE42<>"", "', textZhAdditional: '"&SUBSTITUTE(SUBSTITUTE(AE42, CHAR(13), ""),CHAR(10),"\n"), "")&"', textKo: '"&SUBSTITUTE(SUBSTITUTE(SUBSTITUTE(AG42, CHAR(13), ""),CHAR(10),"\n"),"'","\'")&"', textEn: '"&SUBSTITUTE(SUBSTITUTE(SUBSTITUTE(AH42, CHAR(13), ""),CHAR(10),"\n"),"'","\'")&"'"&IF(Z42="○",", sealable: true","")&IF(AA42="○",", removable: true","")&"}") -> , '03-himika-o-s-2': {megami: 'himika', name: 'クリムゾンゼロ', nameEn: 'Crimson Zero', nameZh: '绯红零时', nameZhG1: '绯红零时', nameKo: '크림슨 제로', ruby: '', rubyEn: '', rubyZh: 'Crimson Zero', baseType: 'special', type: 'attack', range: '0-2', damage: '2/2', cost: '5', text: '【常時】この《攻撃》がダメージを与えるならば、相手は片方を選ぶのではなく両方のダメージを受ける。\n【常時】現在の間合が0ならば、この《攻撃》は対応不可を得る。', textZh: '【常时】此《攻击》对敌装和敌命均造成伤害。\n【常时】若当前距离为0，则此《攻击》得不可被对应。', textZhG1: '【常时】此牌对装和命均造成伤害。\n【常时】若当前距离等于0，则此《攻击》得不可被对应。', textKo: '【상시】이 《공격》이 대미지를 주었다면, 상대는 한쪽을 고르는 것이 아닌 양쪽의 대미지를 받는다.\n 【상시】현재 간격이 0이라면, 이 《공격》은 대응불가를 얻는다.', textEn: 'Forced: This attack deals Damage to both Aura and Life.\n\nForced: If the current Distance is 0, this attack gains No Reactions.'} | AO42: =IF($A42<>"", " /** 《"&$E42&"》 */ export const "&SUBSTITUTE(UPPER(IF(MID($A42, 3, 1)="-", RIGHT($A42,LEN($A42)-3), $A42)), "-", "_")&": TCardId = '"&$A42&"';", "") -> /** 《クリムゾンゼロ》 */ export const HIMIKA_O_S_2: TCardId = '03-himika-o-s-2'; | AP42: =IF($A42<>"", " | '"&$A42&"'", "") -> | '03-himika-o-s-2'
A43: 03-himika-A1-s-2 | B43: himika | C43: A1 | D43: 03-himika-o-s-2 | E43: 炎天・紅緋弥香 | F43: えんてん・くれないひみか | G43: 炎天·红绯弥香 | H43: 炎天·红绯弥香 | J43: 염천·쿠레나이 히미카 | K43: Blazing Sun - Crimson Himika | M43: 切札 | R43: 攻撃 | S43: 全力 | T43: 0-6 | V43: X/X | Y43: 7 | AB43: 対応不可 【常時】Xは7から現在の間合を引いた値に等しい。 【攻撃後】あなたは敗北する。 | AD43: 不可被对应 【常时】X等于7减去当前距离。 【攻击后】你输掉这局游戏。 | AF43: 不可被对应 【常时】X等于7减去当前距离。 【攻击后】你输掉这局游戏。 | AG43: 대응불가 【상시】X는 7에서 현재 간격을 뺀 수치와 같다. 【공격후】당신은 패배한다. | AH43: No Reactions Forced: X is equal to 7 minus the current Distance. After Attack: You lose the game. | AN43: =IF(A43="", "", IF(ROW()>=3, ", ", "")&"'"&A43&"': {megami: '"&B43&"'"&IF(C43<>"",", anotherID: '"&C43&"', replace: '"&D43&"'","")&", name: '"&SUBSTITUTE(E43,"'","\'")&"', nameEn: '"&SUBSTITUTE(K43,"'","\'")&"', nameZh: '"&SUBSTITUTE(G43,"'","\'")&"', nameZhG1: '"&SUBSTITUTE(H43,"'","\'")&"', nameKo: '"&SUBSTITUTE(J43,"'","\'")&"', ruby: '"&F43&"', rubyEn: '"&L43&IF(I43<>"", "', rubyZh: '"&I43, "")&"', baseType: '"&VLOOKUP(M43,マスタ!$A$1:$B$99,2,0)&"'"&IF(N43="○",", extra: true","")&IF(O43<>"",", extraFrom: '"&O43&"'","")&IF(P43<>"",", exchangableTo: '"&P43&"'","")&IF(Q43="○",", poison: true","")&IF(R43<>"", ", type: '"&VLOOKUP(R43,マスタ!$D$1:$E$99,2,0)&"'", "")&IF(S43<>"",", subType: '"&VLOOKUP(S43,マスタ!$D$1:$E$99,2,0)&"'","")&IF(T43<>"",", range: '"&T43&"'","")&IF(V43<>"",", damage: '"&V43&"'","")&IF(X43<>"",", capacity: '"&X43&"'","")&IF(Y43<>"",", cost: '"&Y43&"'","")&", text: '"&SUBSTITUTE(SUBSTITUTE(AB43, CHAR(13), ""),CHAR(10),"\n")&IF(AC43<>"", "', textAdditional: '"&SUBSTITUTE(SUBSTITUTE(AC43, CHAR(13), ""),CHAR(10),"\n"), "")&"', textZh: '"&SUBSTITUTE(SUBSTITUTE(SUBSTITUTE(AD43, CHAR(13), ""),CHAR(10),"\n"),"'","\'")&"', textZhG1: '"&SUBSTITUTE(SUBSTITUTE(SUBSTITUTE(AF43, CHAR(13), ""),CHAR(10),"\n"),"'","\'")&IF(AE43<>"", "', textZhAdditional: '"&SUBSTITUTE(SUBSTITUTE(AE43, CHAR(13), ""),CHAR(10),"\n"), "")&"', textKo: '"&SUBSTITUTE(SUBSTITUTE(SUBSTITUTE(AG43, CHAR(13), ""),CHAR(10),"\n"),"'","\'")&"', textEn: '"&SUBSTITUTE(SUBSTITUTE(SUBSTITUTE(AH43, CHAR(13), ""),CHAR(10),"\n"),"'","\'")&"'"&IF(Z43="○",", sealable: true","")&IF(AA43="○",", removable: true","")&"}") -> , '03-himika-A1-s-2': {megami: 'himika', anotherID: 'A1', replace: '03-himika-o-s-2', name: '炎天・紅緋弥香', nameEn: 'Blazing Sun - Crimson Himika', nameZh: '炎天·红绯弥香', nameZhG1: '炎天·红绯弥香', nameKo: '염천·쿠레나이 히미카', ruby: 'えんてん・くれないひみか', rubyEn: '', baseType: 'special', type: 'attack', subType: 'fullpower', range: '0-6', damage: 'X/X', cost: '7', text: '対応不可 \n【常時】Xは7から現在の間合を引いた値に等しい。 \n【攻撃後】あなたは敗北する。', textZh: '不可被对应\n【常时】X等于7减去当前距离。\n【攻击后】你输掉这局游戏。', textZhG1: '不可被对应\n【常时】X等于7减去当前距离。\n【攻击后】你输掉这局游戏。', textKo: '대응불가 \n 【상시】X는 7에서 현재 간격을 뺀 수치와 같다.\n 【공격후】당신은 패배한다.', textEn: 'No Reactions\n\nForced: X is equal to 7 minus the current Distance.\n\nAfter Attack: You lose the game.'} | AO43: =IF($A43<>"", " /** 《"&$E43&"》 */ export const "&SUBSTITUTE(UPPER(IF(MID($A43, 3, 1)="-", RIGHT($A43,LEN($A43)-3), $A43)), "-", "_")&": TCardId = '"&$A43&"';", "") -> /** 《炎天・紅緋弥香》 */ export const HIMIKA_A1_S_2: TCardId = '03-himika-A1-s-2'; | AP43: =IF($A43<>"", " | '"&$A43&"'", "") -> | '03-himika-A1-s-2'
A44: 03-himika-o-s-3 | B44: himika | E44: スカーレットイマジン | G44: 猩红狂想 | H44: 猩红狂想 | I44: Scarlet Imagine | J44: 스칼렛 이매진 | K44: Scarlet Visions | M44: 切札 | R44: 行動 | Y44: 3 | AB44: カードを2枚引く。その後、あなたは手札を1枚伏せ札にする。 | AD44: 抓2张牌，然后盖伏1张手牌。 | AF44: 抓2张牌，然后盖伏一张牌。 | AG44: 카드를 2장 뽑는다. 그 후, 당신은 손패를 1장 덮임패로 한다. | AH44: Draw two cards, then discard a card. | AN44: =IF(A44="", "", IF(ROW()>=3, ", ", "")&"'"&A44&"': {megami: '"&B44&"'"&IF(C44<>"",", anotherID: '"&C44&"', replace: '"&D44&"'","")&", name: '"&SUBSTITUTE(E44,"'","\'")&"', nameEn: '"&SUBSTITUTE(K44,"'","\'")&"', nameZh: '"&SUBSTITUTE(G44,"'","\'")&"', nameZhG1: '"&SUBSTITUTE(H44,"'","\'")&"', nameKo: '"&SUBSTITUTE(J44,"'","\'")&"', ruby: '"&F44&"', rubyEn: '"&L44&IF(I44<>"", "', rubyZh: '"&I44, "")&"', baseType: '"&VLOOKUP(M44,マスタ!$A$1:$B$99,2,0)&"'"&IF(N44="○",", extra: true","")&IF(O44<>"",", extraFrom: '"&O44&"'","")&IF(P44<>"",", exchangableTo: '"&P44&"'","")&IF(Q44="○",", poison: true","")&IF(R44<>"", ", type: '"&VLOOKUP(R44,マスタ!$D$1:$E$99,2,0)&"'", "")&IF(S44<>"",", subType: '"&VLOOKUP(S44,マスタ!$D$1:$E$99,2,0)&"'","")&IF(T44<>"",", range: '"&T44&"'","")&IF(V44<>"",", damage: '"&V44&"'","")&IF(X44<>"",", capacity: '"&X44&"'","")&IF(Y44<>"",", cost: '"&Y44&"'","")&", text: '"&SUBSTITUTE(SUBSTITUTE(AB44, CHAR(13), ""),CHAR(10),"\n")&IF(AC44<>"", "', textAdditional: '"&SUBSTITUTE(SUBSTITUTE(AC44, CHAR(13), ""),CHAR(10),"\n"), "")&"', textZh: '"&SUBSTITUTE(SUBSTITUTE(SUBSTITUTE(AD44, CHAR(13), ""),CHAR(10),"\n"),"'","\'")&"', textZhG1: '"&SUBSTITUTE(SUBSTITUTE(SUBSTITUTE(AF44, CHAR(13), ""),CHAR(10),"\n"),"'","\'")&IF(AE44<>"", "', textZhAdditional: '"&SUBSTITUTE(SUBSTITUTE(AE44, CHAR(13), ""),CHAR(10),"\n"), "")&"', textKo: '"&SUBSTITUTE(SUBSTITUTE(SUBSTITUTE(AG44, CHAR(13), ""),CHAR(10),"\n"),"'","\'")&"', textEn: '"&SUBSTITUTE(SUBSTITUTE(SUBSTITUTE(AH44, CHAR(13), ""),CHAR(10),"\n"),"'","\'")&"'"&IF(Z44="○",", sealable: true","")&IF(AA44="○",", removable: true","")&"}") -> , '03-himika-o-s-3': {megami: 'himika', name: 'スカーレットイマジン', nameEn: 'Scarlet Visions', nameZh: '猩红狂想', nameZhG1: '猩红狂想', nameKo: '스칼렛 이매진', ruby: '', rubyEn: '', rubyZh: 'Scarlet Imagine', baseType: 'special', type: 'action', cost: '3', text: 'カードを2枚引く。その後、あなたは手札を1枚伏せ札にする。', textZh: '抓2张牌，然后盖伏1张手牌。', textZhG1: '抓2张牌，然后盖伏一张牌。', textKo: '카드를 2장 뽑는다. 그 후, 당신은 손패를 1장 덮임패로 한다.', textEn: 'Draw two cards, then discard a card.'} | AO44: =IF($A44<>"", " /** 《"&$E44&"》 */ export const "&SUBSTITUTE(UPPER(IF(MID($A44, 3, 1)="-", RIGHT($A44,LEN($A44)-3), $A44)), "-", "_")&": TCardId = '"&$A44&"';", "") -> /** 《スカーレットイマジン》 */ export const HIMIKA_O_S_3: TCardId = '03-himika-o-s-3'; | AP44: =IF($A44<>"", " | '"&$A44&"'", "") -> | '03-himika-o-s-3'
A45: 03-himika-o-s-4 | B45: himika | E45: ヴァーミリオンフィールド | G45: 真红领域 | H45: 真红领域 | I45: Vermillion Field | J45: 버밀리온 필드 | K45: Vermillion Field | M45: 切札 | R45: 行動 | Y45: 2 | AB45: 連火-このカードがこのターンに使用した3枚目以降のカードならば、ダスト→間合：2 ---- 【再起】あなたの手札が0枚である。 | AD45: 连火～若此牌是本回合你使用的第3张或更多的牌，则虚→2→距 ---- 【再起】你没有手牌。 | AF45: 连火-若本回合你已使用至少2张牌，则虚（2）→距 ---- 【再起】：你没有手牌。 | AG45: 연화-이 카드가 이 턴에 사용한 3장째 이후의 카드라면, 더스트→간격：2 ---- 【재기】당신의 손패가 0장이다. | AH45: Inferno - If this is the third or later card you've played this turn: Shadow (2)→ Distance ---- Resurgence: You have no cards in your hand. | AN45: =IF(A45="", "", IF(ROW()>=3, ", ", "")&"'"&A45&"': {megami: '"&B45&"'"&IF(C45<>"",", anotherID: '"&C45&"', replace: '"&D45&"'","")&", name: '"&SUBSTITUTE(E45,"'","\'")&"', nameEn: '"&SUBSTITUTE(K45,"'","\'")&"', nameZh: '"&SUBSTITUTE(G45,"'","\'")&"', nameZhG1: '"&SUBSTITUTE(H45,"'","\'")&"', nameKo: '"&SUBSTITUTE(J45,"'","\'")&"', ruby: '"&F45&"', rubyEn: '"&L45&IF(I45<>"", "', rubyZh: '"&I45, "")&"', baseType: '"&VLOOKUP(M45,マスタ!$A$1:$B$99,2,0)&"'"&IF(N45="○",", extra: true","")&IF(O45<>"",", extraFrom: '"&O45&"'","")&IF(P45<>"",", exchangableTo: '"&P45&"'","")&IF(Q45="○",", poison: true","")&IF(R45<>"", ", type: '"&VLOOKUP(R45,マスタ!$D$1:$E$99,2,0)&"'", "")&IF(S45<>"",", subType: '"&VLOOKUP(S45,マスタ!$D$1:$E$99,2,0)&"'","")&IF(T45<>"",", range: '"&T45&"'","")&IF(V45<>"",", damage: '"&V45&"'","")&IF(X45<>"",", capacity: '"&X45&"'","")&IF(Y45<>"",", cost: '"&Y45&"'","")&", text: '"&SUBSTITUTE(SUBSTITUTE(AB45, CHAR(13), ""),CHAR(10),"\n")&IF(AC45<>"", "', textAdditional: '"&SUBSTITUTE(SUBSTITUTE(AC45, CHAR(13), ""),CHAR(10),"\n"), "")&"', textZh: '"&SUBSTITUTE(SUBSTITUTE(SUBSTITUTE(AD45, CHAR(13), ""),CHAR(10),"\n"),"'","\'")&"', textZhG1: '"&SUBSTITUTE(SUBSTITUTE(SUBSTITUTE(AF45, CHAR(13), ""),CHAR(10),"\n"),"'","\'")&IF(AE45<>"", "', textZhAdditional: '"&SUBSTITUTE(SUBSTITUTE(AE45, CHAR(13), ""),CHAR(10),"\n"), "")&"', textKo: '"&SUBSTITUTE(SUBSTITUTE(SUBSTITUTE(AG45, CHAR(13), ""),CHAR(10),"\n"),"'","\'")&"', textEn: '"&SUBSTITUTE(SUBSTITUTE(SUBSTITUTE(AH45, CHAR(13), ""),CHAR(10),"\n"),"'","\'")&"'"&IF(Z45="○",", sealable: true","")&IF(AA45="○",", removable: true","")&"}") -> , '03-himika-o-s-4': {megami: 'himika', name: 'ヴァーミリオンフィールド', nameEn: 'Vermillion Field', nameZh: '真红领域', nameZhG1: '真红领域', nameKo: '버밀리온 필드', ruby: '', rubyEn: '', rubyZh: 'Vermillion Field', baseType: 'special', type: 'action', cost: '2', text: '連火-このカードがこのターンに使用した3枚目以降のカードならば、ダスト→間合：2\n----\n【再起】あなたの手札が0枚である。', textZh: '连火～若此牌是本回合你使用的第3张或更多的牌，则虚→2→距\n----\n【再起】你没有手牌。', textZhG1: '连火-若本回合你已使用至少2张牌，则虚（2）→距\n----\n【再起】：你没有手牌。', textKo: '연화-이 카드가 이 턴에 사용한 3장째 이후의 카드라면, 더스트→간격：2\n ----\n 【재기】당신의 손패가 0장이다.', textEn: 'Inferno - If this is the third or later card you\'ve played this turn:\nShadow (2)→ Distance\n----\nResurgence: You have no cards in your hand.'} | AO45: =IF($A45<>"", " /** 《"&$E45&"》 */ export const "&SUBSTITUTE(UPPER(IF(MID($A45, 3, 1)="-", RIGHT($A45,LEN($A45)-3), $A45)), "-", "_")&": TCardId = '"&$A45&"';", "") -> /** 《ヴァーミリオンフィールド》 */ export const HIMIKA_O_S_4: TCardId = '03-himika-o-s-4'; | AP45: =IF($A45<>"", " | '"&$A45&"'", "") -> | '03-himika-o-s-4'
AN46: =IF(A46="", "", IF(ROW()>=3, ", ", "")&"'"&A46&"': {megami: '"&B46&"'"&IF(C46<>"",", anotherID: '"&C46&"', replace: '"&D46&"'","")&", name: '"&SUBSTITUTE(E46,"'","\'")&"', nameEn: '"&SUBSTITUTE(K46,"'","\'")&"', nameZh: '"&SUBSTITUTE(G46,"'","\'")&"', nameZhG1: '"&SUBSTITUTE(H46,"'","\'")&"', nameKo: '"&SUBSTITUTE(J46,"'","\'")&"', ruby: '"&F46&"', rubyEn: '"&L46&IF(I46<>"", "', rubyZh: '"&I46, "")&"', baseType: '"&VLOOKUP(M46,マスタ!$A$1:$B$99,2,0)&"'"&IF(N46="○",", extra: true","")&IF(O46<>"",", extraFrom: '"&O46&"'","")&IF(P46<>"",", exchangableTo: '"&P46&"'","")&IF(Q46="○",", poison: true","")&IF(R46<>"", ", type: '"&VLOOKUP(R46,マスタ!$D$1:$E$99,2,0)&"'", "")&IF(S46<>"",", subType: '"&VLOOKUP(S46,マスタ!$D$1:$E$99,2,0)&"'","")&IF(T46<>"",", range: '"&T46&"'","")&IF(V46<>"",", damage: '"&V46&"'","")&IF(X46<>"",", capacity: '"&X46&"'","")&IF(Y46<>"",", cost: '"&Y46&"'","")&", text: '"&SUBSTITUTE(SUBSTITUTE(AB46, CHAR(13), ""),CHAR(10),"\n")&IF(AC46<>"", "', textAdditional: '"&SUBSTITUTE(SUBSTITUTE(AC46, CHAR(13), ""),CHAR(10),"\n"), "")&"', textZh: '"&SUBSTITUTE(SUBSTITUTE(SUBSTITUTE(AD46, CHAR(13), ""),CHAR(10),"\n"),"'","\'")&"', textZhG1: '"&SUBSTITUTE(SUBSTITUTE(SUBSTITUTE(AF46, CHAR(13), ""),CHAR(10),"\n"),"'","\'")&IF(AE46<>"", "', textZhAdditional: '"&SUBSTITUTE(SUBSTITUTE(AE46, CHAR(13), ""),CHAR(10),"\n"), "")&"', textKo: '"&SUBSTITUTE(SUBSTITUTE(SUBSTITUTE(AG46, CHAR(13), ""),CHAR(10),"\n"),"'","\'")&"', textEn: '"&SUBSTITUTE(SUBSTITUTE(SUBSTITUTE(AH46, CHAR(13), ""),CHAR(10),"\n"),"'","\'")&"'"&IF(Z46="○",", sealable: true","")&IF(AA46="○",", removable: true","")&"}") | AO46: =IF($A46<>"", " /** 《"&$E46&"》 */ export const "&SUBSTITUTE(UPPER(IF(MID($A46, 3, 1)="-", RIGHT($A46,LEN($A46)-3), $A46)), "-", "_")&": TCardId = '"&$A46&"';", "") | AP46: =IF($A46<>"", " | '"&$A46&"'", "")
A47: 04-tokoyo-o-n-1 | B47: tokoyo | E47: 梳流し | F47: すきながし | G47: 梳流扇 | H47: 梳流 | J47: 빗어내리기 | K47: Glancing Strike | M47: 通常札 | R47: 攻撃 | T47: 4 | V47: -/1 | AB47: 【攻撃後】境地-あなたの集中力が2ならば、このカードを山札の上に戻す。 | AD47: 【攻击后】境地～若你的集中力为2，则将此牌置于你的牌库顶。 | AF47: 【攻击后】境地-若你的集中力等于2，则将此牌置于你的牌库顶。 | AG47: 【공격후】경지-당신의 집중력이 2라면, 이 카드를 패산 위로 되돌린다. | AH47: After Attack: Artistic - Put this card on the top of your deck if your Vigor is 2. | AN47: =IF(A47="", "", IF(ROW()>=3, ", ", "")&"'"&A47&"': {megami: '"&B47&"'"&IF(C47<>"",", anotherID: '"&C47&"', replace: '"&D47&"'","")&", name: '"&SUBSTITUTE(E47,"'","\'")&"', nameEn: '"&SUBSTITUTE(K47,"'","\'")&"', nameZh: '"&SUBSTITUTE(G47,"'","\'")&"', nameZhG1: '"&SUBSTITUTE(H47,"'","\'")&"', nameKo: '"&SUBSTITUTE(J47,"'","\'")&"', ruby: '"&F47&"', rubyEn: '"&L47&IF(I47<>"", "', rubyZh: '"&I47, "")&"', baseType: '"&VLOOKUP(M47,マスタ!$A$1:$B$99,2,0)&"'"&IF(N47="○",", extra: true","")&IF(O47<>"",", extraFrom: '"&O47&"'","")&IF(P47<>"",", exchangableTo: '"&P47&"'","")&IF(Q47="○",", poison: true","")&IF(R47<>"", ", type: '"&VLOOKUP(R47,マスタ!$D$1:$E$99,2,0)&"'", "")&IF(S47<>"",", subType: '"&VLOOKUP(S47,マスタ!$D$1:$E$99,2,0)&"'","")&IF(T47<>"",", range: '"&T47&"'","")&IF(V47<>"",", damage: '"&V47&"'","")&IF(X47<>"",", capacity: '"&X47&"'","")&IF(Y47<>"",", cost: '"&Y47&"'","")&", text: '"&SUBSTITUTE(SUBSTITUTE(AB47, CHAR(13), ""),CHAR(10),"\n")&IF(AC47<>"", "', textAdditional: '"&SUBSTITUTE(SUBSTITUTE(AC47, CHAR(13), ""),CHAR(10),"\n"), "")&"', textZh: '"&SUBSTITUTE(SUBSTITUTE(SUBSTITUTE(AD47, CHAR(13), ""),CHAR(10),"\n"),"'","\'")&"', textZhG1: '"&SUBSTITUTE(SUBSTITUTE(SUBSTITUTE(AF47, CHAR(13), ""),CHAR(10),"\n"),"'","\'")&IF(AE47<>"", "', textZhAdditional: '"&SUBSTITUTE(SUBSTITUTE(AE47, CHAR(13), ""),CHAR(10),"\n"), "")&"', textKo: '"&SUBSTITUTE(SUBSTITUTE(SUBSTITUTE(AG47, CHAR(13), ""),CHAR(10),"\n"),"'","\'")&"', textEn: '"&SUBSTITUTE(SUBSTITUTE(SUBSTITUTE(AH47, CHAR(13), ""),CHAR(10),"\n"),"'","\'")&"'"&IF(Z47="○",", sealable: true","")&IF(AA47="○",", removable: true","")&"}") -> , '04-tokoyo-o-n-1': {megami: 'tokoyo', name: '梳流し', nameEn: 'Glancing Strike', nameZh: '梳流扇', nameZhG1: '梳流', nameKo: '빗어내리기', ruby: 'すきながし', rubyEn: '', baseType: 'normal', type: 'attack', range: '4', damage: '-/1', text: '【攻撃後】境地-あなたの集中力が2ならば、このカードを山札の上に戻す。', textZh: '【攻击后】境地～若你的集中力为2，则将此牌置于你的牌库顶。', textZhG1: '【攻击后】境地-若你的集中力等于2，则将此牌置于你的牌库顶。', textKo: '【공격후】경지-당신의 집중력이 2라면, 이 카드를 패산 위로 되돌린다.', textEn: 'After Attack: Artistic - Put this card on the top of your deck if your Vigor is 2.'} | AO47: =IF($A47<>"", " /** 《"&$E47&"》 */ export const "&SUBSTITUTE(UPPER(IF(MID($A47, 3, 1)="-", RIGHT($A47,LEN($A47)-3), $A47)), "-", "_")&": TCardId = '"&$A47&"';", "") -> /** 《梳流し》 */ export const TOKOYO_O_N_1: TCardId = '04-tokoyo-o-n-1'; | AP47: =IF($A47<>"", " | '"&$A47&"'", "") -> | '04-tokoyo-o-n-1'
A48: 04-tokoyo-A1-n-1 | B48: tokoyo | C48: A1 | D48: 04-tokoyo-o-n-1 | E48: 奏流し | F48: かなでながし | G48: 奏流乐 | H48: 奏流 | J48: 흐르는 연주 | K48: Entrancing Strike | M48: 通常札 | R48: 攻撃 | T48: 5 | V48: -/1 | AB48: 【常時】あなたのトコヨの切札が1枚以上使用済ならば、この《攻撃》は対応不可を得る。 【攻撃後】境地-あなたの集中力が2かつ、あなたの他のメガミの切札が1枚以上使用済ならば、このカードを山札の上に置く。 | AD48: 【常时】若你有至少1张常世的王牌处于已使用状态，则此《攻击》得不可被对应。 【攻击后】境地～若你的集中力为2，且你有至少1张另一柱女神的王牌处于已使用状态，则将此牌置于你的牌库顶。 | AF48: 【常时】若你有至少一张常世的王牌正面朝上，则此《攻击》得不可被对应。 【攻击后】境地-若你的集中力等于2，且你有至少一张另一柱女武神的王牌正面朝上，则将此牌置于你的牌库顶。 | AG48: 【상시】당신의 토코요의 비장패가 1장 이상 사용완료라면, 이 《공격》은 대응불가를 얻는다. 【공격후】경지-당신의 집중력이 2이고, 당신의 다른 여신의 비장패가 1장 이상 사용완료라면, 이 카드를 패산 위에 둔다. | AH48: Forced: If at least one of your Tokoyo's Special cards is Devoted, this attack gains No Reactions. After Attack: Artistic - If your Vigor is 2 and at least one of your other Megami's Special cards is Devoted, put this card on the top of your deck. | AN48: =IF(A48="", "", IF(ROW()>=3, ", ", "")&"'"&A48&"': {megami: '"&B48&"'"&IF(C48<>"",", anotherID: '"&C48&"', replace: '"&D48&"'","")&", name: '"&SUBSTITUTE(E48,"'","\'")&"', nameEn: '"&SUBSTITUTE(K48,"'","\'")&"', nameZh: '"&SUBSTITUTE(G48,"'","\'")&"', nameZhG1: '"&SUBSTITUTE(H48,"'","\'")&"', nameKo: '"&SUBSTITUTE(J48,"'","\'")&"', ruby: '"&F48&"', rubyEn: '"&L48&IF(I48<>"", "', rubyZh: '"&I48, "")&"', baseType: '"&VLOOKUP(M48,マスタ!$A$1:$B$99,2,0)&"'"&IF(N48="○",", extra: true","")&IF(O48<>"",", extraFrom: '"&O48&"'","")&IF(P48<>"",", exchangableTo: '"&P48&"'","")&IF(Q48="○",", poison: true","")&IF(R48<>"", ", type: '"&VLOOKUP(R48,マスタ!$D$1:$E$99,2,0)&"'", "")&IF(S48<>"",", subType: '"&VLOOKUP(S48,マスタ!$D$1:$E$99,2,0)&"'","")&IF(T48<>"",", range: '"&T48&"'","")&IF(V48<>"",", damage: '"&V48&"'","")&IF(X48<>"",", capacity: '"&X48&"'","")&IF(Y48<>"",", cost: '"&Y48&"'","")&", text: '"&SUBSTITUTE(SUBSTITUTE(AB48, CHAR(13), ""),CHAR(10),"\n")&IF(AC48<>"", "', textAdditional: '"&SUBSTITUTE(SUBSTITUTE(AC48, CHAR(13), ""),CHAR(10),"\n"), "")&"', textZh: '"&SUBSTITUTE(SUBSTITUTE(SUBSTITUTE(AD48, CHAR(13), ""),CHAR(10),"\n"),"'","\'")&"', textZhG1: '"&SUBSTITUTE(SUBSTITUTE(SUBSTITUTE(AF48, CHAR(13), ""),CHAR(10),"\n"),"'","\'")&IF(AE48<>"", "', textZhAdditional: '"&SUBSTITUTE(SUBSTITUTE(AE48, CHAR(13), ""),CHAR(10),"\n"), "")&"', textKo: '"&SUBSTITUTE(SUBSTITUTE(SUBSTITUTE(AG48, CHAR(13), ""),CHAR(10),"\n"),"'","\'")&"', textEn: '"&SUBSTITUTE(SUBSTITUTE(SUBSTITUTE(AH48, CHAR(13), ""),CHAR(10),"\n"),"'","\'")&"'"&IF(Z48="○",", sealable: true","")&IF(AA48="○",", removable: true","")&"}") -> , '04-tokoyo-A1-n-1': {megami: 'tokoyo', anotherID: 'A1', replace: '04-tokoyo-o-n-1', name: '奏流し', nameEn: 'Entrancing Strike', nameZh: '奏流乐', nameZhG1: '奏流', nameKo: '흐르는 연주', ruby: 'かなでながし', rubyEn: '', baseType: 'normal', type: 'attack', range: '5', damage: '-/1', text: '【常時】あなたのトコヨの切札が1枚以上使用済ならば、この《攻撃》は対応不可を得る。 \n【攻撃後】境地-あなたの集中力が2かつ、あなたの他のメガミの切札が1枚以上使用済ならば、このカードを山札の上に置く。', textZh: '【常时】若你有至少1张常世的王牌处于已使用状态，则此《攻击》得不可被对应。\n【攻击后】境地～若你的集中力为2，且你有至少1张另一柱女神的王牌处于已使用状态，则将此牌置于你的牌库顶。', textZhG1: '【常时】若你有至少一张常世的王牌正面朝上，则此《攻击》得不可被对应。\n【攻击后】境地-若你的集中力等于2，且你有至少一张另一柱女武神的王牌正面朝上，则将此牌置于你的牌库顶。', textKo: '【상시】당신의 토코요의 비장패가 1장 이상 사용완료라면, 이 《공격》은 대응불가를 얻는다.\n 【공격후】경지-당신의 집중력이 2이고, 당신의 다른 여신의 비장패가 1장 이상 사용완료라면, 이 카드를 패산 위에 둔다.', textEn: 'Forced: If at least one of your Tokoyo\'s Special cards is Devoted, this attack gains No Reactions.\n\nAfter Attack: Artistic - If your Vigor is 2 and at least one of your other Megami\'s Special cards is Devoted, put this card on the top of your deck.'} | AO48: =IF($A48<>"", " /** 《"&$E48&"》 */ export const "&SUBSTITUTE(UPPER(IF(MID($A48, 3, 1)="-", RIGHT($A48,LEN($A48)-3), $A48)), "-", "_")&": TCardId = '"&$A48&"';", "") -> /** 《奏流し》 */ export const TOKOYO_A1_N_1: TCardId = '04-tokoyo-A1-n-1'; | AP48: =IF($A48<>"", " | '"&$A48&"'", "") -> | '04-tokoyo-A1-n-1'
A49: 04-tokoyo-o-n-2 | B49: tokoyo | E49: 雅打ち | F49: みやびうち | G49: 风雅击 | H49: 雅击 | J49: 우아한 타격 | K49: Polite Return | M49: 通常札 | R49: 攻撃 | S49: 対応 | T49: 2-4 | V49: 2/1 | AB49: 【攻撃後】境地-あなたの集中力が2ならば、対応した切札でない《攻撃》を打ち消す。 | AD49: 【攻击后】境地～若你的集中力为2，则打消被对应的非王牌的《攻击》。 | AF49: 【攻击后】境地-若你的集中力等于2，则打消被对应的非王牌的《攻击》。 | AG49: 【공격후】경지-당신의 집중력이 2라면, 대응한 비장패가 아닌 《공격》을 무효화한다. | AH49: After Attack: Artistic - Cancel the non-Special attack you played this card as a Reaction to if your Vigor is 2. | AN49: =IF(A49="", "", IF(ROW()>=3, ", ", "")&"'"&A49&"': {megami: '"&B49&"'"&IF(C49<>"",", anotherID: '"&C49&"', replace: '"&D49&"'","")&", name: '"&SUBSTITUTE(E49,"'","\'")&"', nameEn: '"&SUBSTITUTE(K49,"'","\'")&"', nameZh: '"&SUBSTITUTE(G49,"'","\'")&"', nameZhG1: '"&SUBSTITUTE(H49,"'","\'")&"', nameKo: '"&SUBSTITUTE(J49,"'","\'")&"', ruby: '"&F49&"', rubyEn: '"&L49&IF(I49<>"", "', rubyZh: '"&I49, "")&"', baseType: '"&VLOOKUP(M49,マスタ!$A$1:$B$99,2,0)&"'"&IF(N49="○",", extra: true","")&IF(O49<>"",", extraFrom: '"&O49&"'","")&IF(P49<>"",", exchangableTo: '"&P49&"'","")&IF(Q49="○",", poison: true","")&IF(R49<>"", ", type: '"&VLOOKUP(R49,マスタ!$D$1:$E$99,2,0)&"'", "")&IF(S49<>"",", subType: '"&VLOOKUP(S49,マスタ!$D$1:$E$99,2,0)&"'","")&IF(T49<>"",", range: '"&T49&"'","")&IF(V49<>"",", damage: '"&V49&"'","")&IF(X49<>"",", capacity: '"&X49&"'","")&IF(Y49<>"",", cost: '"&Y49&"'","")&", text: '"&SUBSTITUTE(SUBSTITUTE(AB49, CHAR(13), ""),CHAR(10),"\n")&IF(AC49<>"", "', textAdditional: '"&SUBSTITUTE(SUBSTITUTE(AC49, CHAR(13), ""),CHAR(10),"\n"), "")&"', textZh: '"&SUBSTITUTE(SUBSTITUTE(SUBSTITUTE(AD49, CHAR(13), ""),CHAR(10),"\n"),"'","\'")&"', textZhG1: '"&SUBSTITUTE(SUBSTITUTE(SUBSTITUTE(AF49, CHAR(13), ""),CHAR(10),"\n"),"'","\'")&IF(AE49<>"", "', textZhAdditional: '"&SUBSTITUTE(SUBSTITUTE(AE49, CHAR(13), ""),CHAR(10),"\n"), "")&"', textKo: '"&SUBSTITUTE(SUBSTITUTE(SUBSTITUTE(AG49, CHAR(13), ""),CHAR(10),"\n"),"'","\'")&"', textEn: '"&SUBSTITUTE(SUBSTITUTE(SUBSTITUTE(AH49, CHAR(13), ""),CHAR(10),"\n"),"'","\'")&"'"&IF(Z49="○",", sealable: true","")&IF(AA49="○",", removable: true","")&"}") -> , '04-tokoyo-o-n-2': {megami: 'tokoyo', name: '雅打ち', nameEn: 'Polite Return', nameZh: '风雅击', nameZhG1: '雅击', nameKo: '우아한 타격', ruby: 'みやびうち', rubyEn: '', baseType: 'normal', type: 'attack', subType: 'reaction', range: '2-4', damage: '2/1', text: '【攻撃後】境地-あなたの集中力が2ならば、対応した切札でない《攻撃》を打ち消す。', textZh: '【攻击后】境地～若你的集中力为2，则打消被对应的非王牌的《攻击》。', textZhG1: '【攻击后】境地-若你的集中力等于2，则打消被对应的非王牌的《攻击》。', textKo: '【공격후】경지-당신의 집중력이 2라면, 대응한 비장패가 아닌 《공격》을 무효화한다.', textEn: 'After Attack: Artistic - Cancel the non-Special attack you played this card as a Reaction to if your Vigor is 2.'} | AO49: =IF($A49<>"", " /** 《"&$E49&"》 */ export const "&SUBSTITUTE(UPPER(IF(MID($A49, 3, 1)="-", RIGHT($A49,LEN($A49)-3), $A49)), "-", "_")&": TCardId = '"&$A49&"';", "") -> /** 《雅打ち》 */ export const TOKOYO_O_N_2: TCardId = '04-tokoyo-o-n-2'; | AP49: =IF($A49<>"", " | '"&$A49&"'", "") -> | '04-tokoyo-o-n-2'
A50: 04-tokoyo-o-n-3 | B50: tokoyo | E50: 跳ね兎 | F50: はねうさぎ | G50: 脱兔跃 | H50: 脱兔 | J50: 날뛰는 토끼 | K50: Rabbit Step | M50: 通常札 | R50: 行動 | AB50: 現在の間合が3以下ならば、ダスト→間合：2 | AD50: 若当前距离小于等于3，则：虚→2→距 | AF50: 若当前距离小于3，则虚（2）→距 | AG50: 현재 간격이 3 이하라면, 더스트→간격：2 | AH50: If the current Distance is 3 or less: Shadow (2)→ Distance | AN50: =IF(A50="", "", IF(ROW()>=3, ", ", "")&"'"&A50&"': {megami: '"&B50&"'"&IF(C50<>"",", anotherID: '"&C50&"', replace: '"&D50&"'","")&", name: '"&SUBSTITUTE(E50,"'","\'")&"', nameEn: '"&SUBSTITUTE(K50,"'","\'")&"', nameZh: '"&SUBSTITUTE(G50,"'","\'")&"', nameZhG1: '"&SUBSTITUTE(H50,"'","\'")&"', nameKo: '"&SUBSTITUTE(J50,"'","\'")&"', ruby: '"&F50&"', rubyEn: '"&L50&IF(I50<>"", "', rubyZh: '"&I50, "")&"', baseType: '"&VLOOKUP(M50,マスタ!$A$1:$B$99,2,0)&"'"&IF(N50="○",", extra: true","")&IF(O50<>"",", extraFrom: '"&O50&"'","")&IF(P50<>"",", exchangableTo: '"&P50&"'","")&IF(Q50="○",", poison: true","")&IF(R50<>"", ", type: '"&VLOOKUP(R50,マスタ!$D$1:$E$99,2,0)&"'", "")&IF(S50<>"",", subType: '"&VLOOKUP(S50,マスタ!$D$1:$E$99,2,0)&"'","")&IF(T50<>"",", range: '"&T50&"'","")&IF(V50<>"",", damage: '"&V50&"'","")&IF(X50<>"",", capacity: '"&X50&"'","")&IF(Y50<>"",", cost: '"&Y50&"'","")&", text: '"&SUBSTITUTE(SUBSTITUTE(AB50, CHAR(13), ""),CHAR(10),"\n")&IF(AC50<>"", "', textAdditional: '"&SUBSTITUTE(SUBSTITUTE(AC50, CHAR(13), ""),CHAR(10),"\n"), "")&"', textZh: '"&SUBSTITUTE(SUBSTITUTE(SUBSTITUTE(AD50, CHAR(13), ""),CHAR(10),"\n"),"'","\'")&"', textZhG1: '"&SUBSTITUTE(SUBSTITUTE(SUBSTITUTE(AF50, CHAR(13), ""),CHAR(10),"\n"),"'","\'")&IF(AE50<>"", "', textZhAdditional: '"&SUBSTITUTE(SUBSTITUTE(AE50, CHAR(13), ""),CHAR(10),"\n"), "")&"', textKo: '"&SUBSTITUTE(SUBSTITUTE(SUBSTITUTE(AG50, CHAR(13), ""),CHAR(10),"\n"),"'","\'")&"', textEn: '"&SUBSTITUTE(SUBSTITUTE(SUBSTITUTE(AH50, CHAR(13), ""),CHAR(10),"\n"),"'","\'")&"'"&IF(Z50="○",", sealable: true","")&IF(AA50="○",", removable: true","")&"}") -> , '04-tokoyo-o-n-3': {megami: 'tokoyo', name: '跳ね兎', nameEn: 'Rabbit Step', nameZh: '脱兔跃', nameZhG1: '脱兔', nameKo: '날뛰는 토끼', ruby: 'はねうさぎ', rubyEn: '', baseType: 'normal', type: 'action', text: '現在の間合が3以下ならば、ダスト→間合：2', textZh: '若当前距离小于等于3，则：虚→2→距', textZhG1: '若当前距离小于3，则虚（2）→距', textKo: '현재 간격이 3 이하라면, 더스트→간격：2', textEn: 'If the current Distance is 3 or less:\nShadow (2)→ Distance'} | AO50: =IF($A50<>"", " /** 《"&$E50&"》 */ export const "&SUBSTITUTE(UPPER(IF(MID($A50, 3, 1)="-", RIGHT($A50,LEN($A50)-3), $A50)), "-", "_")&": TCardId = '"&$A50&"';", "") -> /** 《跳ね兎》 */ export const TOKOYO_O_N_3: TCardId = '04-tokoyo-o-n-3'; | AP50: =IF($A50<>"", " | '"&$A50&"'", "") -> | '04-tokoyo-o-n-3'
A51: 04-tokoyo-o-n-4 | B51: tokoyo | E51: 詩舞 | F51: しぶ | G51: 吟诗舞 | H51: 诗舞 | J51: 시의 춤 | K51: Song and Dance | M51: 通常札 | R51: 行動 | S51: 対応 | AB51: 集中力を1得て、以下から1つを選ぶ。 ・自フレア→自オーラ：1 ・自オーラ→間合：1 | AD51: 获得1点集中力，选择一项： ●自气→1→自装 ●自装→1→距 | AF51: 获得1点集中力，选择一项： 1.自气（1）→自装； 2.自装（1）→距。 | AG51: 집중력을 1 얻고, 이하에서 하나를 고른다. ・자신 플레어→자신 오라：1 ・자신 오라→간격：1 | AH51: Gain 1 Vigor. Choose one: ・Your Flare (1)→ Your Aura ・Your Aura (1)→ Distance | AN51: =IF(A51="", "", IF(ROW()>=3, ", ", "")&"'"&A51&"': {megami: '"&B51&"'"&IF(C51<>"",", anotherID: '"&C51&"', replace: '"&D51&"'","")&", name: '"&SUBSTITUTE(E51,"'","\'")&"', nameEn: '"&SUBSTITUTE(K51,"'","\'")&"', nameZh: '"&SUBSTITUTE(G51,"'","\'")&"', nameZhG1: '"&SUBSTITUTE(H51,"'","\'")&"', nameKo: '"&SUBSTITUTE(J51,"'","\'")&"', ruby: '"&F51&"', rubyEn: '"&L51&IF(I51<>"", "', rubyZh: '"&I51, "")&"', baseType: '"&VLOOKUP(M51,マスタ!$A$1:$B$99,2,0)&"'"&IF(N51="○",", extra: true","")&IF(O51<>"",", extraFrom: '"&O51&"'","")&IF(P51<>"",", exchangableTo: '"&P51&"'","")&IF(Q51="○",", poison: true","")&IF(R51<>"", ", type: '"&VLOOKUP(R51,マスタ!$D$1:$E$99,2,0)&"'", "")&IF(S51<>"",", subType: '"&VLOOKUP(S51,マスタ!$D$1:$E$99,2,0)&"'","")&IF(T51<>"",", range: '"&T51&"'","")&IF(V51<>"",", damage: '"&V51&"'","")&IF(X51<>"",", capacity: '"&X51&"'","")&IF(Y51<>"",", cost: '"&Y51&"'","")&", text: '"&SUBSTITUTE(SUBSTITUTE(AB51, CHAR(13), ""),CHAR(10),"\n")&IF(AC51<>"", "', textAdditional: '"&SUBSTITUTE(SUBSTITUTE(AC51, CHAR(13), ""),CHAR(10),"\n"), "")&"', textZh: '"&SUBSTITUTE(SUBSTITUTE(SUBSTITUTE(AD51, CHAR(13), ""),CHAR(10),"\n"),"'","\'")&"', textZhG1: '"&SUBSTITUTE(SUBSTITUTE(SUBSTITUTE(AF51, CHAR(13), ""),CHAR(10),"\n"),"'","\'")&IF(AE51<>"", "', textZhAdditional: '"&SUBSTITUTE(SUBSTITUTE(AE51, CHAR(13), ""),CHAR(10),"\n"), "")&"', textKo: '"&SUBSTITUTE(SUBSTITUTE(SUBSTITUTE(AG51, CHAR(13), ""),CHAR(10),"\n"),"'","\'")&"', textEn: '"&SUBSTITUTE(SUBSTITUTE(SUBSTITUTE(AH51, CHAR(13), ""),CHAR(10),"\n"),"'","\'")&"'"&IF(Z51="○",", sealable: true","")&IF(AA51="○",", removable: true","")&"}") -> , '04-tokoyo-o-n-4': {megami: 'tokoyo', name: '詩舞', nameEn: 'Song and Dance', nameZh: '吟诗舞', nameZhG1: '诗舞', nameKo: '시의 춤', ruby: 'しぶ', rubyEn: '', baseType: 'normal', type: 'action', subType: 'reaction', text: '集中力を1得て、以下から1つを選ぶ。\n・自フレア→自オーラ：1\n・自オーラ→間合：1', textZh: '获得1点集中力，选择一项：\n●自气→1→自装\n●自装→1→距', textZhG1: '获得1点集中力，选择一项：\n1.自气（1）→自装；\n2.自装（1）→距。', textKo: '집중력을 1 얻고, 이하에서 하나를 고른다.\n ・자신 플레어→자신 오라：1\n ・자신 오라→간격：1', textEn: 'Gain 1 Vigor. Choose one:\n・Your Flare (1)→ Your Aura\n・Your Aura (1)→ Distance'} | AO51: =IF($A51<>"", " /** 《"&$E51&"》 */ export const "&SUBSTITUTE(UPPER(IF(MID($A51, 3, 1)="-", RIGHT($A51,LEN($A51)-3), $A51)), "-", "_")&": TCardId = '"&$A51&"';", "") -> /** 《詩舞》 */ export const TOKOYO_O_N_4: TCardId = '04-tokoyo-o-n-4'; | AP51: =IF($A51<>"", " | '"&$A51&"'", "") -> | '04-tokoyo-o-n-4'
A52: 04-tokoyo-o-n-5 | B52: tokoyo | E52: 要返し | F52: かなめがえし | G52: 扇回旋 | H52: 扇回旋 | J52: 부채 뒤집기 | K52: Break Point | M52: 通常札 | R52: 行動 | S52: 全力 | AB52: 捨て札か伏せ札からカードを2枚まで選ぶ。それらのカードを好きな順で山札の底に置く。 ダスト→自オーラ：2 | AD52: 从你的弃牌区和盖牌区中选择至多2张牌，将它们以任意顺序置于你的牌库底。 虚→2→自装 | AF52: 从你的弃牌区和盖牌区中选择2张牌，将它们以任意顺序置于你的牌库底。 虚（2）→自装 | AG52: 버림패나 덮임패에서 카드를 2장까지 고른다. 이 카드들을 원하는 순으로 패산의 밑에 둔다. 더스트→자신 오라：2 | AH52: Choose up to two cards in your discard or played piles. Put those cards on the bottom of your deck in any order. Shadow (2)→ Your Aura. | AN52: =IF(A52="", "", IF(ROW()>=3, ", ", "")&"'"&A52&"': {megami: '"&B52&"'"&IF(C52<>"",", anotherID: '"&C52&"', replace: '"&D52&"'","")&", name: '"&SUBSTITUTE(E52,"'","\'")&"', nameEn: '"&SUBSTITUTE(K52,"'","\'")&"', nameZh: '"&SUBSTITUTE(G52,"'","\'")&"', nameZhG1: '"&SUBSTITUTE(H52,"'","\'")&"', nameKo: '"&SUBSTITUTE(J52,"'","\'")&"', ruby: '"&F52&"', rubyEn: '"&L52&IF(I52<>"", "', rubyZh: '"&I52, "")&"', baseType: '"&VLOOKUP(M52,マスタ!$A$1:$B$99,2,0)&"'"&IF(N52="○",", extra: true","")&IF(O52<>"",", extraFrom: '"&O52&"'","")&IF(P52<>"",", exchangableTo: '"&P52&"'","")&IF(Q52="○",", poison: true","")&IF(R52<>"", ", type: '"&VLOOKUP(R52,マスタ!$D$1:$E$99,2,0)&"'", "")&IF(S52<>"",", subType: '"&VLOOKUP(S52,マスタ!$D$1:$E$99,2,0)&"'","")&IF(T52<>"",", range: '"&T52&"'","")&IF(V52<>"",", damage: '"&V52&"'","")&IF(X52<>"",", capacity: '"&X52&"'","")&IF(Y52<>"",", cost: '"&Y52&"'","")&", text: '"&SUBSTITUTE(SUBSTITUTE(AB52, CHAR(13), ""),CHAR(10),"\n")&IF(AC52<>"", "', textAdditional: '"&SUBSTITUTE(SUBSTITUTE(AC52, CHAR(13), ""),CHAR(10),"\n"), "")&"', textZh: '"&SUBSTITUTE(SUBSTITUTE(SUBSTITUTE(AD52, CHAR(13), ""),CHAR(10),"\n"),"'","\'")&"', textZhG1: '"&SUBSTITUTE(SUBSTITUTE(SUBSTITUTE(AF52, CHAR(13), ""),CHAR(10),"\n"),"'","\'")&IF(AE52<>"", "', textZhAdditional: '"&SUBSTITUTE(SUBSTITUTE(AE52, CHAR(13), ""),CHAR(10),"\n"), "")&"', textKo: '"&SUBSTITUTE(SUBSTITUTE(SUBSTITUTE(AG52, CHAR(13), ""),CHAR(10),"\n"),"'","\'")&"', textEn: '"&SUBSTITUTE(SUBSTITUTE(SUBSTITUTE(AH52, CHAR(13), ""),CHAR(10),"\n"),"'","\'")&"'"&IF(Z52="○",", sealable: true","")&IF(AA52="○",", removable: true","")&"}") -> , '04-tokoyo-o-n-5': {megami: 'tokoyo', name: '要返し', nameEn: 'Break Point', nameZh: '扇回旋', nameZhG1: '扇回旋', nameKo: '부채 뒤집기', ruby: 'かなめがえし', rubyEn: '', baseType: 'normal', type: 'action', subType: 'fullpower', text: '捨て札か伏せ札からカードを2枚まで選ぶ。それらのカードを好きな順で山札の底に置く。 \nダスト→自オーラ：2', textZh: '从你的弃牌区和盖牌区中选择至多2张牌，将它们以任意顺序置于你的牌库底。 \n虚→2→自装', textZhG1: '从你的弃牌区和盖牌区中选择2张牌，将它们以任意顺序置于你的牌库底。 \n虚（2）→自装', textKo: '버림패나 덮임패에서 카드를 2장까지 고른다. 이 카드들을 원하는 순으로 패산의 밑에 둔다. \n 더스트→자신 오라：2', textEn: 'Choose up to two cards in your discard or played piles. Put those cards on the bottom of your deck in any order.\n\nShadow (2)→ Your Aura.'} | AO52: =IF($A52<>"", " /** 《"&$E52&"》 */ export const "&SUBSTITUTE(UPPER(IF(MID($A52, 3, 1)="-", RIGHT($A52,LEN($A52)-3), $A52)), "-", "_")&": TCardId = '"&$A52&"';", "") -> /** 《要返し》 */ export const TOKOYO_O_N_5: TCardId = '04-tokoyo-o-n-5'; | AP52: =IF($A52<>"", " | '"&$A52&"'", "") -> | '04-tokoyo-o-n-5'
A53: 04-tokoyo-o-n-6 | B53: tokoyo | E53: 風舞台 | F53: かぜぶたい | G53: 风舞台 | H53: 风舞台 | J53: 바람의 무대 | K53: Windy Stage | M53: 通常札 | R53: 付与 | X53: 2 | AB53: 【展開時】間合→自オーラ：2 【破棄時】自オーラ→間合：2 | AD53: 【展开时】距→2→自装 【破弃时】自装→2→距 | AF53: 【展开时】距（2）→自装 【破弃时】自装（2）→距 | AG53: 【전개시】간격→자신 오라：2 【파기시】자신 오라→간격：2 | AH53: Initialize: Distance (2)→ Your Aura Disenchant: Your Aura (2)→ Distance | AN53: =IF(A53="", "", IF(ROW()>=3, ", ", "")&"'"&A53&"': {megami: '"&B53&"'"&IF(C53<>"",", anotherID: '"&C53&"', replace: '"&D53&"'","")&", name: '"&SUBSTITUTE(E53,"'","\'")&"', nameEn: '"&SUBSTITUTE(K53,"'","\'")&"', nameZh: '"&SUBSTITUTE(G53,"'","\'")&"', nameZhG1: '"&SUBSTITUTE(H53,"'","\'")&"', nameKo: '"&SUBSTITUTE(J53,"'","\'")&"', ruby: '"&F53&"', rubyEn: '"&L53&IF(I53<>"", "', rubyZh: '"&I53, "")&"', baseType: '"&VLOOKUP(M53,マスタ!$A$1:$B$99,2,0)&"'"&IF(N53="○",", extra: true","")&IF(O53<>"",", extraFrom: '"&O53&"'","")&IF(P53<>"",", exchangableTo: '"&P53&"'","")&IF(Q53="○",", poison: true","")&IF(R53<>"", ", type: '"&VLOOKUP(R53,マスタ!$D$1:$E$99,2,0)&"'", "")&IF(S53<>"",", subType: '"&VLOOKUP(S53,マスタ!$D$1:$E$99,2,0)&"'","")&IF(T53<>"",", range: '"&T53&"'","")&IF(V53<>"",", damage: '"&V53&"'","")&IF(X53<>"",", capacity: '"&X53&"'","")&IF(Y53<>"",", cost: '"&Y53&"'","")&", text: '"&SUBSTITUTE(SUBSTITUTE(AB53, CHAR(13), ""),CHAR(10),"\n")&IF(AC53<>"", "', textAdditional: '"&SUBSTITUTE(SUBSTITUTE(AC53, CHAR(13), ""),CHAR(10),"\n"), "")&"', textZh: '"&SUBSTITUTE(SUBSTITUTE(SUBSTITUTE(AD53, CHAR(13), ""),CHAR(10),"\n"),"'","\'")&"', textZhG1: '"&SUBSTITUTE(SUBSTITUTE(SUBSTITUTE(AF53, CHAR(13), ""),CHAR(10),"\n"),"'","\'")&IF(AE53<>"", "', textZhAdditional: '"&SUBSTITUTE(SUBSTITUTE(AE53, CHAR(13), ""),CHAR(10),"\n"), "")&"', textKo: '"&SUBSTITUTE(SUBSTITUTE(SUBSTITUTE(AG53, CHAR(13), ""),CHAR(10),"\n"),"'","\'")&"', textEn: '"&SUBSTITUTE(SUBSTITUTE(SUBSTITUTE(AH53, CHAR(13), ""),CHAR(10),"\n"),"'","\'")&"'"&IF(Z53="○",", sealable: true","")&IF(AA53="○",", removable: true","")&"}") -> , '04-tokoyo-o-n-6': {megami: 'tokoyo', name: '風舞台', nameEn: 'Windy Stage', nameZh: '风舞台', nameZhG1: '风舞台', nameKo: '바람의 무대', ruby: 'かぜぶたい', rubyEn: '', baseType: 'normal', type: 'enhance', capacity: '2', text: '【展開時】間合→自オーラ：2 \n【破棄時】自オーラ→間合：2', textZh: '【展开时】距→2→自装 \n【破弃时】自装→2→距', textZhG1: '【展开时】距（2）→自装 \n【破弃时】自装（2）→距', textKo: '【전개시】간격→자신 오라：2 \n 【파기시】자신 오라→간격：2', textEn: 'Initialize:\nDistance (2)→ Your Aura\n\nDisenchant:\nYour Aura (2)→ Distance'} | AO53: =IF($A53<>"", " /** 《"&$E53&"》 */ export const "&SUBSTITUTE(UPPER(IF(MID($A53, 3, 1)="-", RIGHT($A53,LEN($A53)-3), $A53)), "-", "_")&": TCardId = '"&$A53&"';", "") -> /** 《風舞台》 */ export const TOKOYO_O_N_6: TCardId = '04-tokoyo-o-n-6'; | AP53: =IF($A53<>"", " | '"&$A53&"'", "") -> | '04-tokoyo-o-n-6'
A54: 04-tokoyo-o-n-7 | B54: tokoyo | E54: 晴舞台 | F54: はれぶたい | G54: 晴舞台 | H54: 晴舞台 | J54: 맑음의 무대 | K54: Sunny Stage | M54: 通常札 | R54: 付与 | X54: 1 | AB54: 【破棄時】境地-あなたの集中力が2ならば、ダスト→自オーラ：2 【破棄時】あなたは集中力を1得る。 | AD54: 【破弃时】境地～若你的集中力为2，则虚→2→自装 【破弃时】你获得1点集中力。 | AF54: 【破弃时】境地-若你的集中力等于2，则虚（2）→自装 【破弃时】你获得1点集中力。 | AG54: 【파기시】경지-당신의 집중력이 2라면, 더스트→자신 오라：2 【파기시】당신은 집중력을 1 얻는다. | AH54: Disenchant: Artistic - If your Vigor is 2: Shadow (2)→ Your Aura Disenchant: Gain 1 Vigor. | AN54: =IF(A54="", "", IF(ROW()>=3, ", ", "")&"'"&A54&"': {megami: '"&B54&"'"&IF(C54<>"",", anotherID: '"&C54&"', replace: '"&D54&"'","")&", name: '"&SUBSTITUTE(E54,"'","\'")&"', nameEn: '"&SUBSTITUTE(K54,"'","\'")&"', nameZh: '"&SUBSTITUTE(G54,"'","\'")&"', nameZhG1: '"&SUBSTITUTE(H54,"'","\'")&"', nameKo: '"&SUBSTITUTE(J54,"'","\'")&"', ruby: '"&F54&"', rubyEn: '"&L54&IF(I54<>"", "', rubyZh: '"&I54, "")&"', baseType: '"&VLOOKUP(M54,マスタ!$A$1:$B$99,2,0)&"'"&IF(N54="○",", extra: true","")&IF(O54<>"",", extraFrom: '"&O54&"'","")&IF(P54<>"",", exchangableTo: '"&P54&"'","")&IF(Q54="○",", poison: true","")&IF(R54<>"", ", type: '"&VLOOKUP(R54,マスタ!$D$1:$E$99,2,0)&"'", "")&IF(S54<>"",", subType: '"&VLOOKUP(S54,マスタ!$D$1:$E$99,2,0)&"'","")&IF(T54<>"",", range: '"&T54&"'","")&IF(V54<>"",", damage: '"&V54&"'","")&IF(X54<>"",", capacity: '"&X54&"'","")&IF(Y54<>"",", cost: '"&Y54&"'","")&", text: '"&SUBSTITUTE(SUBSTITUTE(AB54, CHAR(13), ""),CHAR(10),"\n")&IF(AC54<>"", "', textAdditional: '"&SUBSTITUTE(SUBSTITUTE(AC54, CHAR(13), ""),CHAR(10),"\n"), "")&"', textZh: '"&SUBSTITUTE(SUBSTITUTE(SUBSTITUTE(AD54, CHAR(13), ""),CHAR(10),"\n"),"'","\'")&"', textZhG1: '"&SUBSTITUTE(SUBSTITUTE(SUBSTITUTE(AF54, CHAR(13), ""),CHAR(10),"\n"),"'","\'")&IF(AE54<>"", "', textZhAdditional: '"&SUBSTITUTE(SUBSTITUTE(AE54, CHAR(13), ""),CHAR(10),"\n"), "")&"', textKo: '"&SUBSTITUTE(SUBSTITUTE(SUBSTITUTE(AG54, CHAR(13), ""),CHAR(10),"\n"),"'","\'")&"', textEn: '"&SUBSTITUTE(SUBSTITUTE(SUBSTITUTE(AH54, CHAR(13), ""),CHAR(10),"\n"),"'","\'")&"'"&IF(Z54="○",", sealable: true","")&IF(AA54="○",", removable: true","")&"}") -> , '04-tokoyo-o-n-7': {megami: 'tokoyo', name: '晴舞台', nameEn: 'Sunny Stage', nameZh: '晴舞台', nameZhG1: '晴舞台', nameKo: '맑음의 무대', ruby: 'はれぶたい', rubyEn: '', baseType: 'normal', type: 'enhance', capacity: '1', text: '【破棄時】境地-あなたの集中力が2ならば、ダスト→自オーラ：2 \n【破棄時】あなたは集中力を1得る。', textZh: '【破弃时】境地～若你的集中力为2，则虚→2→自装\n【破弃时】你获得1点集中力。', textZhG1: '【破弃时】境地-若你的集中力等于2，则虚（2）→自装\n【破弃时】你获得1点集中力。', textKo: '【파기시】경지-당신의 집중력이 2라면, 더스트→자신 오라：2 \n 【파기시】당신은 집중력을 1 얻는다.', textEn: 'Disenchant: Artistic - If your Vigor is 2:\nShadow (2)→ Your Aura\n\nDisenchant: Gain 1 Vigor.'} | AO54: =IF($A54<>"", " /** 《"&$E54&"》 */ export const "&SUBSTITUTE(UPPER(IF(MID($A54, 3, 1)="-", RIGHT($A54,LEN($A54)-3), $A54)), "-", "_")&": TCardId = '"&$A54&"';", "") -> /** 《晴舞台》 */ export const TOKOYO_O_N_7: TCardId = '04-tokoyo-o-n-7'; | AP54: =IF($A54<>"", " | '"&$A54&"'", "") -> | '04-tokoyo-o-n-7'
A55: 04-tokoyo-A1-n-7 | B55: tokoyo | C55: A1 | D55: 04-tokoyo-o-n-7 | E55: 陽の音 | F55: ひのね | G55: 阳之音 | H55: 阳之音 | J55: 햇볕의 소리 | K55: Sound of Sun | M55: 通常札 | R55: 付与 | X55: 2 | AB55: 【展開時/展開中】展開時、およびあなたが《対応》カードを使用した時、その解決後にダスト→自オーラ：1 【展開中】相手のターンにこのカードの上の桜花結晶は移動しない。 | AD55: 【展开时】虚→1→自装 【展开中】每当你使用的具《对应》副类别的牌结算完毕时：虚→1→自装 【展开中】对手的回合内，此牌上的樱花结晶不会移动。 | AF55: 【展开时】虚（1）→自装 【展开中】每当你使用的具《对应》副类别的牌结算完毕时，虚（1）→自装 【展开中】对手的回合内不能移除此牌上的樱花结晶。 | AG55: 【전개시/전개중】전개시, 그리고 당신이 《대응》카드를 사용했을 때, 그 해결 후 더스트→자신 오라：1 【전개중】 상대 턴에는 이 카드 위의 벚꽃 결정은 이동하지 않는다. | AH55: Initialize/Ongoing: When you play this, or you play a Reaction while this is in play, after that card resolves: Shadow (1)→ Your Aura Ongoing: Sakura tokens cannot leave this card on your opponent's turn. | AN55: =IF(A55="", "", IF(ROW()>=3, ", ", "")&"'"&A55&"': {megami: '"&B55&"'"&IF(C55<>"",", anotherID: '"&C55&"', replace: '"&D55&"'","")&", name: '"&SUBSTITUTE(E55,"'","\'")&"', nameEn: '"&SUBSTITUTE(K55,"'","\'")&"', nameZh: '"&SUBSTITUTE(G55,"'","\'")&"', nameZhG1: '"&SUBSTITUTE(H55,"'","\'")&"', nameKo: '"&SUBSTITUTE(J55,"'","\'")&"', ruby: '"&F55&"', rubyEn: '"&L55&IF(I55<>"", "', rubyZh: '"&I55, "")&"', baseType: '"&VLOOKUP(M55,マスタ!$A$1:$B$99,2,0)&"'"&IF(N55="○",", extra: true","")&IF(O55<>"",", extraFrom: '"&O55&"'","")&IF(P55<>"",", exchangableTo: '"&P55&"'","")&IF(Q55="○",", poison: true","")&IF(R55<>"", ", type: '"&VLOOKUP(R55,マスタ!$D$1:$E$99,2,0)&"'", "")&IF(S55<>"",", subType: '"&VLOOKUP(S55,マスタ!$D$1:$E$99,2,0)&"'","")&IF(T55<>"",", range: '"&T55&"'","")&IF(V55<>"",", damage: '"&V55&"'","")&IF(X55<>"",", capacity: '"&X55&"'","")&IF(Y55<>"",", cost: '"&Y55&"'","")&", text: '"&SUBSTITUTE(SUBSTITUTE(AB55, CHAR(13), ""),CHAR(10),"\n")&IF(AC55<>"", "', textAdditional: '"&SUBSTITUTE(SUBSTITUTE(AC55, CHAR(13), ""),CHAR(10),"\n"), "")&"', textZh: '"&SUBSTITUTE(SUBSTITUTE(SUBSTITUTE(AD55, CHAR(13), ""),CHAR(10),"\n"),"'","\'")&"', textZhG1: '"&SUBSTITUTE(SUBSTITUTE(SUBSTITUTE(AF55, CHAR(13), ""),CHAR(10),"\n"),"'","\'")&IF(AE55<>"", "', textZhAdditional: '"&SUBSTITUTE(SUBSTITUTE(AE55, CHAR(13), ""),CHAR(10),"\n"), "")&"', textKo: '"&SUBSTITUTE(SUBSTITUTE(SUBSTITUTE(AG55, CHAR(13), ""),CHAR(10),"\n"),"'","\'")&"', textEn: '"&SUBSTITUTE(SUBSTITUTE(SUBSTITUTE(AH55, CHAR(13), ""),CHAR(10),"\n"),"'","\'")&"'"&IF(Z55="○",", sealable: true","")&IF(AA55="○",", removable: true","")&"}") -> , '04-tokoyo-A1-n-7': {megami: 'tokoyo', anotherID: 'A1', replace: '04-tokoyo-o-n-7', name: '陽の音', nameEn: 'Sound of Sun', nameZh: '阳之音', nameZhG1: '阳之音', nameKo: '햇볕의 소리', ruby: 'ひのね', rubyEn: '', baseType: 'normal', type: 'enhance', capacity: '2', text: '【展開時/展開中】展開時、およびあなたが《対応》カードを使用した時、その解決後にダスト→自オーラ：1 \n【展開中】相手のターンにこのカードの上の桜花結晶は移動しない。', textZh: '【展开时】虚→1→自装\n【展开中】每当你使用的具《对应》副类别的牌结算完毕时：虚→1→自装\n【展开中】对手的回合内，此牌上的樱花结晶不会移动。', textZhG1: '【展开时】虚（1）→自装\n【展开中】每当你使用的具《对应》副类别的牌结算完毕时，虚（1）→自装\n【展开中】对手的回合内不能移除此牌上的樱花结晶。', textKo: '【전개시/전개중】전개시, 그리고 당신이 《대응》카드를 사용했을 때, 그 해결 후 더스트→자신 오라：1 \n 【전개중】 상대 턴에는 이 카드 위의 벚꽃 결정은 이동하지 않는다.', textEn: 'Initialize/Ongoing: When you play this, or you play a Reaction while this is in play, after that card resolves:\nShadow (1)→ Your Aura\n\nOngoing: Sakura tokens cannot leave this card on your opponent\'s turn.'} | AO55: =IF($A55<>"", " /** 《"&$E55&"》 */ export const "&SUBSTITUTE(UPPER(IF(MID($A55, 3, 1)="-", RIGHT($A55,LEN($A55)-3), $A55)), "-", "_")&": TCardId = '"&$A55&"';", "") -> /** 《陽の音》 */ export const TOKOYO_A1_N_7: TCardId = '04-tokoyo-A1-n-7'; | AP55: =IF($A55<>"", " | '"&$A55&"'", "") -> | '04-tokoyo-A1-n-7'
A56: 04-tokoyo-o-s-1 | B56: tokoyo | E56: 久遠ノ花 | F56: くおんのはな | G56: 久远之花 | H56: 久远之花 | J56: 영원한 꽃 | K56: Immortal Flower | M56: 切札 | R56: 攻撃 | S56: 対応 | T56: 0-10 | V56: -/1 | Y56: 5 | AB56: 【攻撃後】対応した《攻撃》を打ち消す。 | AD56: 【攻击后】打消被对应的《攻击》。 | AF56: 【攻击后】打消被对应的《攻击》。 | AG56: 【공격후】대응한 《공격》을 무효화한다. | AH56: After Attack: Cancel the attack you played this card as a Reaction to. | AN56: =IF(A56="", "", IF(ROW()>=3, ", ", "")&"'"&A56&"': {megami: '"&B56&"'"&IF(C56<>"",", anotherID: '"&C56&"', replace: '"&D56&"'","")&", name: '"&SUBSTITUTE(E56,"'","\'")&"', nameEn: '"&SUBSTITUTE(K56,"'","\'")&"', nameZh: '"&SUBSTITUTE(G56,"'","\'")&"', nameZhG1: '"&SUBSTITUTE(H56,"'","\'")&"', nameKo: '"&SUBSTITUTE(J56,"'","\'")&"', ruby: '"&F56&"', rubyEn: '"&L56&IF(I56<>"", "', rubyZh: '"&I56, "")&"', baseType: '"&VLOOKUP(M56,マスタ!$A$1:$B$99,2,0)&"'"&IF(N56="○",", extra: true","")&IF(O56<>"",", extraFrom: '"&O56&"'","")&IF(P56<>"",", exchangableTo: '"&P56&"'","")&IF(Q56="○",", poison: true","")&IF(R56<>"", ", type: '"&VLOOKUP(R56,マスタ!$D$1:$E$99,2,0)&"'", "")&IF(S56<>"",", subType: '"&VLOOKUP(S56,マスタ!$D$1:$E$99,2,0)&"'","")&IF(T56<>"",", range: '"&T56&"'","")&IF(V56<>"",", damage: '"&V56&"'","")&IF(X56<>"",", capacity: '"&X56&"'","")&IF(Y56<>"",", cost: '"&Y56&"'","")&", text: '"&SUBSTITUTE(SUBSTITUTE(AB56, CHAR(13), ""),CHAR(10),"\n")&IF(AC56<>"", "', textAdditional: '"&SUBSTITUTE(SUBSTITUTE(AC56, CHAR(13), ""),CHAR(10),"\n"), "")&"', textZh: '"&SUBSTITUTE(SUBSTITUTE(SUBSTITUTE(AD56, CHAR(13), ""),CHAR(10),"\n"),"'","\'")&"', textZhG1: '"&SUBSTITUTE(SUBSTITUTE(SUBSTITUTE(AF56, CHAR(13), ""),CHAR(10),"\n"),"'","\'")&IF(AE56<>"", "', textZhAdditional: '"&SUBSTITUTE(SUBSTITUTE(AE56, CHAR(13), ""),CHAR(10),"\n"), "")&"', textKo: '"&SUBSTITUTE(SUBSTITUTE(SUBSTITUTE(AG56, CHAR(13), ""),CHAR(10),"\n"),"'","\'")&"', textEn: '"&SUBSTITUTE(SUBSTITUTE(SUBSTITUTE(AH56, CHAR(13), ""),CHAR(10),"\n"),"'","\'")&"'"&IF(Z56="○",", sealable: true","")&IF(AA56="○",", removable: true","")&"}") -> , '04-tokoyo-o-s-1': {megami: 'tokoyo', name: '久遠ノ花', nameEn: 'Immortal Flower', nameZh: '久远之花', nameZhG1: '久远之花', nameKo: '영원한 꽃', ruby: 'くおんのはな', rubyEn: '', baseType: 'special', type: 'attack', subType: 'reaction', range: '0-10', damage: '-/1', cost: '5', text: '【攻撃後】対応した《攻撃》を打ち消す。', textZh: '【攻击后】打消被对应的《攻击》。', textZhG1: '【攻击后】打消被对应的《攻击》。 ', textKo: '【공격후】대응한 《공격》을 무효화한다.', textEn: 'After Attack: Cancel the attack you played this card as a Reaction to.'} | AO56: =IF($A56<>"", " /** 《"&$E56&"》 */ export const "&SUBSTITUTE(UPPER(IF(MID($A56, 3, 1)="-", RIGHT($A56,LEN($A56)-3), $A56)), "-", "_")&": TCardId = '"&$A56&"';", "") -> /** 《久遠ノ花》 */ export const TOKOYO_O_S_1: TCardId = '04-tokoyo-o-s-1'; | AP56: =IF($A56<>"", " | '"&$A56&"'", "") -> | '04-tokoyo-o-s-1'
A57: 04-tokoyo-o-s-2 | B57: tokoyo | E57: 千歳ノ鳥 | F57: ちとせのとり | G57: 千岁之鸟 | H57: 千岁之鸟 | J57: 천년의 새 | K57: Eternal Migrant | M57: 切札 | R57: 攻撃 | T57: 3-4 | V57: 2/2 | Y57: 2 | AB57: 【攻撃後】山札を再構成する。 (その際にダメージは受けない) | AD57: 【攻击后】重铸牌库（你不会因此受到伤害）。 | AF57: 【攻击后】重铸牌库（你不会因此受到伤害）。 | AG57: 【공격후】패산을 재구성한다. (이 때에는 대미지를 받지 않는다.) | AH57: After Attack: Reshuffle your deck (without taking Damage to your Life). | AN57: =IF(A57="", "", IF(ROW()>=3, ", ", "")&"'"&A57&"': {megami: '"&B57&"'"&IF(C57<>"",", anotherID: '"&C57&"', replace: '"&D57&"'","")&", name: '"&SUBSTITUTE(E57,"'","\'")&"', nameEn: '"&SUBSTITUTE(K57,"'","\'")&"', nameZh: '"&SUBSTITUTE(G57,"'","\'")&"', nameZhG1: '"&SUBSTITUTE(H57,"'","\'")&"', nameKo: '"&SUBSTITUTE(J57,"'","\'")&"', ruby: '"&F57&"', rubyEn: '"&L57&IF(I57<>"", "', rubyZh: '"&I57, "")&"', baseType: '"&VLOOKUP(M57,マスタ!$A$1:$B$99,2,0)&"'"&IF(N57="○",", extra: true","")&IF(O57<>"",", extraFrom: '"&O57&"'","")&IF(P57<>"",", exchangableTo: '"&P57&"'","")&IF(Q57="○",", poison: true","")&IF(R57<>"", ", type: '"&VLOOKUP(R57,マスタ!$D$1:$E$99,2,0)&"'", "")&IF(S57<>"",", subType: '"&VLOOKUP(S57,マスタ!$D$1:$E$99,2,0)&"'","")&IF(T57<>"",", range: '"&T57&"'","")&IF(V57<>"",", damage: '"&V57&"'","")&IF(X57<>"",", capacity: '"&X57&"'","")&IF(Y57<>"",", cost: '"&Y57&"'","")&", text: '"&SUBSTITUTE(SUBSTITUTE(AB57, CHAR(13), ""),CHAR(10),"\n")&IF(AC57<>"", "', textAdditional: '"&SUBSTITUTE(SUBSTITUTE(AC57, CHAR(13), ""),CHAR(10),"\n"), "")&"', textZh: '"&SUBSTITUTE(SUBSTITUTE(SUBSTITUTE(AD57, CHAR(13), ""),CHAR(10),"\n"),"'","\'")&"', textZhG1: '"&SUBSTITUTE(SUBSTITUTE(SUBSTITUTE(AF57, CHAR(13), ""),CHAR(10),"\n"),"'","\'")&IF(AE57<>"", "', textZhAdditional: '"&SUBSTITUTE(SUBSTITUTE(AE57, CHAR(13), ""),CHAR(10),"\n"), "")&"', textKo: '"&SUBSTITUTE(SUBSTITUTE(SUBSTITUTE(AG57, CHAR(13), ""),CHAR(10),"\n"),"'","\'")&"', textEn: '"&SUBSTITUTE(SUBSTITUTE(SUBSTITUTE(AH57, CHAR(13), ""),CHAR(10),"\n"),"'","\'")&"'"&IF(Z57="○",", sealable: true","")&IF(AA57="○",", removable: true","")&"}") -> , '04-tokoyo-o-s-2': {megami: 'tokoyo', name: '千歳ノ鳥', nameEn: 'Eternal Migrant', nameZh: '千岁之鸟', nameZhG1: '千岁之鸟', nameKo: '천년의 새', ruby: 'ちとせのとり', rubyEn: '', baseType: 'special', type: 'attack', range: '3-4', damage: '2/2', cost: '2', text: '【攻撃後】山札を再構成する。 \n(その際にダメージは受けない)', textZh: '【攻击后】重铸牌库（你不会因此受到伤害）。', textZhG1: '【攻击后】重铸牌库（你不会因此受到伤害）。', textKo: '【공격후】패산을 재구성한다.\n (이 때에는 대미지를 받지 않는다.)', textEn: 'After Attack: Reshuffle your deck (without taking Damage to your Life).'} | AO57: =IF($A57<>"", " /** 《"&$E57&"》 */ export const "&SUBSTITUTE(UPPER(IF(MID($A57, 3, 1)="-", RIGHT($A57,LEN($A57)-3), $A57)), "-", "_")&": TCardId = '"&$A57&"';", "") -> /** 《千歳ノ鳥》 */ export const TOKOYO_O_S_2: TCardId = '04-tokoyo-o-s-2'; | AP57: =IF($A57<>"", " | '"&$A57&"'", "") -> | '04-tokoyo-o-s-2'
A58: 04-tokoyo-A1-s-2 | B58: tokoyo | C58: A1 | D58: 04-tokoyo-o-s-2 | E58: 二重奏:吹弾陽明 | F58: にじゅうそう：すいだんようめい | G58: 二重奏：吹弹阳明 | H58: 二重奏：吹弹阳明 | J58: 이중주:취탄양명 | K58: Duet: Radiant Luminosity | M58: 切札 | R58: 行動 | Y58: 1 | AB58: 【使用済】あなたの開始フェイズの開始時に捨て札または伏せ札からカード1枚を選び、それを山札の底に置いてもよい。 ---- 【即再起】あなたが再構成以外でライフに1以上のダメージを受ける。 | AD58: 【已使用】每当你的准备阶段开始时，你可以从你的弃牌区或盖牌区中选择1张牌，将其置于你的牌库底。 ---- 【即再起】自命受到除重铸牌库以外的1点或以上的伤害。 | AF58: 【已使用】你的准备阶段开始时，你可以从你的弃牌区或盖牌区中选择一张牌，将其置于你的牌库底。 ---- 【即再起】自命受到除重铸牌库以外的1点以上的伤害。 | AG58: 【사용완료】당신의 개시 페이즈 시작시에 버림패, 혹은 덮임패에서 카드 1장을 골라, 그것을 패산 밑에 두어도 좋다. ---- 【즉재기】당신이 재구성 이외로 라이프에 1 이상의 대미지를 받는다. | AH58: Devoted: At the beginning of your turn, you may put a card from your discard pile or your played pile on the bottom of your deck. ---- Immediate Resurgence: You take 1 or more damage to your Life, excluding reshuffle damage. | AN58: =IF(A58="", "", IF(ROW()>=3, ", ", "")&"'"&A58&"': {megami: '"&B58&"'"&IF(C58<>"",", anotherID: '"&C58&"', replace: '"&D58&"'","")&", name: '"&SUBSTITUTE(E58,"'","\'")&"', nameEn: '"&SUBSTITUTE(K58,"'","\'")&"', nameZh: '"&SUBSTITUTE(G58,"'","\'")&"', nameZhG1: '"&SUBSTITUTE(H58,"'","\'")&"', nameKo: '"&SUBSTITUTE(J58,"'","\'")&"', ruby: '"&F58&"', rubyEn: '"&L58&IF(I58<>"", "', rubyZh: '"&I58, "")&"', baseType: '"&VLOOKUP(M58,マスタ!$A$1:$B$99,2,0)&"'"&IF(N58="○",", extra: true","")&IF(O58<>"",", extraFrom: '"&O58&"'","")&IF(P58<>"",", exchangableTo: '"&P58&"'","")&IF(Q58="○",", poison: true","")&IF(R58<>"", ", type: '"&VLOOKUP(R58,マスタ!$D$1:$E$99,2,0)&"'", "")&IF(S58<>"",", subType: '"&VLOOKUP(S58,マスタ!$D$1:$E$99,2,0)&"'","")&IF(T58<>"",", range: '"&T58&"'","")&IF(V58<>"",", damage: '"&V58&"'","")&IF(X58<>"",", capacity: '"&X58&"'","")&IF(Y58<>"",", cost: '"&Y58&"'","")&", text: '"&SUBSTITUTE(SUBSTITUTE(AB58, CHAR(13), ""),CHAR(10),"\n")&IF(AC58<>"", "', textAdditional: '"&SUBSTITUTE(SUBSTITUTE(AC58, CHAR(13), ""),CHAR(10),"\n"), "")&"', textZh: '"&SUBSTITUTE(SUBSTITUTE(SUBSTITUTE(AD58, CHAR(13), ""),CHAR(10),"\n"),"'","\'")&"', textZhG1: '"&SUBSTITUTE(SUBSTITUTE(SUBSTITUTE(AF58, CHAR(13), ""),CHAR(10),"\n"),"'","\'")&IF(AE58<>"", "', textZhAdditional: '"&SUBSTITUTE(SUBSTITUTE(AE58, CHAR(13), ""),CHAR(10),"\n"), "")&"', textKo: '"&SUBSTITUTE(SUBSTITUTE(SUBSTITUTE(AG58, CHAR(13), ""),CHAR(10),"\n"),"'","\'")&"', textEn: '"&SUBSTITUTE(SUBSTITUTE(SUBSTITUTE(AH58, CHAR(13), ""),CHAR(10),"\n"),"'","\'")&"'"&IF(Z58="○",", sealable: true","")&IF(AA58="○",", removable: true","")&"}") -> , '04-tokoyo-A1-s-2': {megami: 'tokoyo', anotherID: 'A1', replace: '04-tokoyo-o-s-2', name: '二重奏:吹弾陽明', nameEn: 'Duet: Radiant Luminosity', nameZh: '二重奏：吹弹阳明', nameZhG1: '二重奏：吹弹阳明', nameKo: '이중주:취탄양명', ruby: 'にじゅうそう：すいだんようめい', rubyEn: '', baseType: 'special', type: 'action', cost: '1', text: '【使用済】あなたの開始フェイズの開始時に捨て札または伏せ札からカード1枚を選び、それを山札の底に置いてもよい。 \n----\n【即再起】あなたが再構成以外でライフに1以上のダメージを受ける。', textZh: '【已使用】每当你的准备阶段开始时，你可以从你的弃牌区或盖牌区中选择1张牌，将其置于你的牌库底。\n----\n【即再起】自命受到除重铸牌库以外的1点或以上的伤害。', textZhG1: '【已使用】你的准备阶段开始时，你可以从你的弃牌区或盖牌区中选择一张牌，将其置于你的牌库底。\n----\n【即再起】自命受到除重铸牌库以外的1点以上的伤害。', textKo: '【사용완료】당신의 개시 페이즈 시작시에 버림패, 혹은 덮임패에서 카드 1장을 골라, 그것을 패산 밑에 두어도 좋다.\n ----\n 【즉재기】당신이 재구성 이외로 라이프에 1 이상의 대미지를 받는다.', textEn: 'Devoted: At the beginning of your turn, you may put a card from your discard pile or your played pile on the bottom of your deck.\n----\nImmediate Resurgence: You take 1 or more damage to your Life, excluding reshuffle damage.'} | AO58: =IF($A58<>"", " /** 《"&$E58&"》 */ export const "&SUBSTITUTE(UPPER(IF(MID($A58, 3, 1)="-", RIGHT($A58,LEN($A58)-3), $A58)), "-", "_")&": TCardId = '"&$A58&"';", "") -> /** 《二重奏:吹弾陽明》 */ export const TOKOYO_A1_S_2: TCardId = '04-tokoyo-A1-s-2'; | AP58: =IF($A58<>"", " | '"&$A58&"'", "") -> | '04-tokoyo-A1-s-2'
A59: 04-tokoyo-o-s-3 | B59: tokoyo | E59: 無窮ノ風 | F59: むきゅうのかぜ | G59: 无穷之风 | H59: 无穷之风 | J59: 무궁한 바람 | K59: Perpetual Wind | M59: 切札 | R59: 攻撃 | T59: 3-8 | V59: 1/1 | Y59: 1 | AB59: 対応不可 【攻撃後】相手は手札から《攻撃》でないカード1枚を捨て札にする。それが行えない場合、相手は手札を公開する。 ---- 【再起】境地-あなたの集中力が2である。 | AD59: 不可被对应。 【攻击后】对手弃1张非《攻击》的牌。若不能如此做，对手须展示其手牌。 ---- 【再起】境地～你的集中力为2。 | AF59: 不可被对应。 【攻击后】对手弃一张非《攻击》的牌。若不能如此做，则对手须展示其手牌。 ---- 【再起】境地-你的集中力等于2。 | AG59: 대응불가 【공격후】상대는 손패에서 《공격》이 아닌 카드 1장을 버림패로 한다. 불가능하다면, 상대는 손패를 공개한다. ---- 【재기】경지-당신의 집중력이 2이다. | AH59: No Reactions After Attack: Your opponent puts a non-Attack card from their hand into their played pile. If they can't, they must reveal their hand. ---- Resurgence: Artistic - Your Vigor is 2. | AN59: =IF(A59="", "", IF(ROW()>=3, ", ", "")&"'"&A59&"': {megami: '"&B59&"'"&IF(C59<>"",", anotherID: '"&C59&"', replace: '"&D59&"'","")&", name: '"&SUBSTITUTE(E59,"'","\'")&"', nameEn: '"&SUBSTITUTE(K59,"'","\'")&"', nameZh: '"&SUBSTITUTE(G59,"'","\'")&"', nameZhG1: '"&SUBSTITUTE(H59,"'","\'")&"', nameKo: '"&SUBSTITUTE(J59,"'","\'")&"', ruby: '"&F59&"', rubyEn: '"&L59&IF(I59<>"", "', rubyZh: '"&I59, "")&"', baseType: '"&VLOOKUP(M59,マスタ!$A$1:$B$99,2,0)&"'"&IF(N59="○",", extra: true","")&IF(O59<>"",", extraFrom: '"&O59&"'","")&IF(P59<>"",", exchangableTo: '"&P59&"'","")&IF(Q59="○",", poison: true","")&IF(R59<>"", ", type: '"&VLOOKUP(R59,マスタ!$D$1:$E$99,2,0)&"'", "")&IF(S59<>"",", subType: '"&VLOOKUP(S59,マスタ!$D$1:$E$99,2,0)&"'","")&IF(T59<>"",", range: '"&T59&"'","")&IF(V59<>"",", damage: '"&V59&"'","")&IF(X59<>"",", capacity: '"&X59&"'","")&IF(Y59<>"",", cost: '"&Y59&"'","")&", text: '"&SUBSTITUTE(SUBSTITUTE(AB59, CHAR(13), ""),CHAR(10),"\n")&IF(AC59<>"", "', textAdditional: '"&SUBSTITUTE(SUBSTITUTE(AC59, CHAR(13), ""),CHAR(10),"\n"), "")&"', textZh: '"&SUBSTITUTE(SUBSTITUTE(SUBSTITUTE(AD59, CHAR(13), ""),CHAR(10),"\n"),"'","\'")&"', textZhG1: '"&SUBSTITUTE(SUBSTITUTE(SUBSTITUTE(AF59, CHAR(13), ""),CHAR(10),"\n"),"'","\'")&IF(AE59<>"", "', textZhAdditional: '"&SUBSTITUTE(SUBSTITUTE(AE59, CHAR(13), ""),CHAR(10),"\n"), "")&"', textKo: '"&SUBSTITUTE(SUBSTITUTE(SUBSTITUTE(AG59, CHAR(13), ""),CHAR(10),"\n"),"'","\'")&"', textEn: '"&SUBSTITUTE(SUBSTITUTE(SUBSTITUTE(AH59, CHAR(13), ""),CHAR(10),"\n"),"'","\'")&"'"&IF(Z59="○",", sealable: true","")&IF(AA59="○",", removable: true","")&"}") -> , '04-tokoyo-o-s-3': {megami: 'tokoyo', name: '無窮ノ風', nameEn: 'Perpetual Wind', nameZh: '无穷之风', nameZhG1: '无穷之风', nameKo: '무궁한 바람', ruby: 'むきゅうのかぜ', rubyEn: '', baseType: 'special', type: 'attack', range: '3-8', damage: '1/1', cost: '1', text: '対応不可 \n【攻撃後】相手は手札から《攻撃》でないカード1枚を捨て札にする。それが行えない場合、相手は手札を公開する。 \n----\n【再起】境地-あなたの集中力が2である。', textZh: '不可被对应。\n【攻击后】对手弃1张非《攻击》的牌。若不能如此做，对手须展示其手牌。\n----\n【再起】境地～你的集中力为2。', textZhG1: '不可被对应。\n【攻击后】对手弃一张非《攻击》的牌。若不能如此做，则对手须展示其手牌。\n----\n【再起】境地-你的集中力等于2。', textKo: '대응불가 \n 【공격후】상대는 손패에서 《공격》이 아닌 카드 1장을 버림패로 한다. 불가능하다면, 상대는 손패를 공개한다.\n ----\n 【재기】경지-당신의 집중력이 2이다.', textEn: 'No Reactions\n\nAfter Attack: Your opponent puts a non-Attack card from their hand into their played pile. If they can\'t, they must reveal their hand.\n----\nResurgence: Artistic - Your Vigor is 2.'} | AO59: =IF($A59<>"", " /** 《"&$E59&"》 */ export const "&SUBSTITUTE(UPPER(IF(MID($A59, 3, 1)="-", RIGHT($A59,LEN($A59)-3), $A59)), "-", "_")&": TCardId = '"&$A59&"';", "") -> /** 《無窮ノ風》 */ export const TOKOYO_O_S_3: TCardId = '04-tokoyo-o-s-3'; | AP59: =IF($A59<>"", " | '"&$A59&"'", "") -> | '04-tokoyo-o-s-3'
A60: 04-tokoyo-o-s-4 | B60: tokoyo | E60: 常世ノ月 | F60: とこよのつき | G60: 常世之月 | H60: 常世之月 | J60: 토코요의 달 | K60: Eternal Moon | M60: 切札 | R60: 行動 | Y60: 2 | AB60: あなたの集中力は2になり、相手の集中力は0になり、相手を畏縮させる。 | AD60: 你的集中力变为2，对手的集中力变为0，令对手畏缩。 | AF60: 你的集中力变为2，对手的集中力变为0，对手畏缩。 | AG60: 당신의 집중력이 2가 되고, 상대의 집중력이 0이 되고, 상대를 위축시킨다。 | AH60: Your Vigor becomes 2. Your opponent's Vigor becomes 0. Flinch your opponent. | AN60: =IF(A60="", "", IF(ROW()>=3, ", ", "")&"'"&A60&"': {megami: '"&B60&"'"&IF(C60<>"",", anotherID: '"&C60&"', replace: '"&D60&"'","")&", name: '"&SUBSTITUTE(E60,"'","\'")&"', nameEn: '"&SUBSTITUTE(K60,"'","\'")&"', nameZh: '"&SUBSTITUTE(G60,"'","\'")&"', nameZhG1: '"&SUBSTITUTE(H60,"'","\'")&"', nameKo: '"&SUBSTITUTE(J60,"'","\'")&"', ruby: '"&F60&"', rubyEn: '"&L60&IF(I60<>"", "', rubyZh: '"&I60, "")&"', baseType: '"&VLOOKUP(M60,マスタ!$A$1:$B$99,2,0)&"'"&IF(N60="○",", extra: true","")&IF(O60<>"",", extraFrom: '"&O60&"'","")&IF(P60<>"",", exchangableTo: '"&P60&"'","")&IF(Q60="○",", poison: true","")&IF(R60<>"", ", type: '"&VLOOKUP(R60,マスタ!$D$1:$E$99,2,0)&"'", "")&IF(S60<>"",", subType: '"&VLOOKUP(S60,マスタ!$D$1:$E$99,2,0)&"'","")&IF(T60<>"",", range: '"&T60&"'","")&IF(V60<>"",", damage: '"&V60&"'","")&IF(X60<>"",", capacity: '"&X60&"'","")&IF(Y60<>"",", cost: '"&Y60&"'","")&", text: '"&SUBSTITUTE(SUBSTITUTE(AB60, CHAR(13), ""),CHAR(10),"\n")&IF(AC60<>"", "', textAdditional: '"&SUBSTITUTE(SUBSTITUTE(AC60, CHAR(13), ""),CHAR(10),"\n"), "")&"', textZh: '"&SUBSTITUTE(SUBSTITUTE(SUBSTITUTE(AD60, CHAR(13), ""),CHAR(10),"\n"),"'","\'")&"', textZhG1: '"&SUBSTITUTE(SUBSTITUTE(SUBSTITUTE(AF60, CHAR(13), ""),CHAR(10),"\n"),"'","\'")&IF(AE60<>"", "', textZhAdditional: '"&SUBSTITUTE(SUBSTITUTE(AE60, CHAR(13), ""),CHAR(10),"\n"), "")&"', textKo: '"&SUBSTITUTE(SUBSTITUTE(SUBSTITUTE(AG60, CHAR(13), ""),CHAR(10),"\n"),"'","\'")&"', textEn: '"&SUBSTITUTE(SUBSTITUTE(SUBSTITUTE(AH60, CHAR(13), ""),CHAR(10),"\n"),"'","\'")&"'"&IF(Z60="○",", sealable: true","")&IF(AA60="○",", removable: true","")&"}") -> , '04-tokoyo-o-s-4': {megami: 'tokoyo', name: '常世ノ月', nameEn: 'Eternal Moon', nameZh: '常世之月', nameZhG1: '常世之月', nameKo: '토코요의 달', ruby: 'とこよのつき', rubyEn: '', baseType: 'special', type: 'action', cost: '2', text: 'あなたの集中力は2になり、相手の集中力は0になり、相手を畏縮させる。', textZh: '你的集中力变为2，对手的集中力变为0，令对手畏缩。', textZhG1: '你的集中力变为2，对手的集中力变为0，对手畏缩。', textKo: '당신의 집중력이 2가 되고, 상대의 집중력이 0이 되고, 상대를 위축시킨다。', textEn: 'Your Vigor becomes 2. Your opponent\'s Vigor becomes 0. Flinch your opponent.'} | AO60: =IF($A60<>"", " /** 《"&$E60&"》 */ export const "&SUBSTITUTE(UPPER(IF(MID($A60, 3, 1)="-", RIGHT($A60,LEN($A60)-3), $A60)), "-", "_")&": TCardId = '"&$A60&"';", "") -> /** 《常世ノ月》 */ export const TOKOYO_O_S_4: TCardId = '04-tokoyo-o-s-4'; | AP60: =IF($A60<>"", " | '"&$A60&"'", "") -> | '04-tokoyo-o-s-4'
AN61: =IF(A61="", "", IF(ROW()>=3, ", ", "")&"'"&A61&"': {megami: '"&B61&"'"&IF(C61<>"",", anotherID: '"&C61&"', replace: '"&D61&"'","")&", name: '"&SUBSTITUTE(E61,"'","\'")&"', nameEn: '"&SUBSTITUTE(K61,"'","\'")&"', nameZh: '"&SUBSTITUTE(G61,"'","\'")&"', nameZhG1: '"&SUBSTITUTE(H61,"'","\'")&"', nameKo: '"&SUBSTITUTE(J61,"'","\'")&"', ruby: '"&F61&"', rubyEn: '"&L61&IF(I61<>"", "', rubyZh: '"&I61, "")&"', baseType: '"&VLOOKUP(M61,マスタ!$A$1:$B$99,2,0)&"'"&IF(N61="○",", extra: true","")&IF(O61<>"",", extraFrom: '"&O61&"'","")&IF(P61<>"",", exchangableTo: '"&P61&"'","")&IF(Q61="○",", poison: true","")&IF(R61<>"", ", type: '"&VLOOKUP(R61,マスタ!$D$1:$E$99,2,0)&"'", "")&IF(S61<>"",", subType: '"&VLOOKUP(S61,マスタ!$D$1:$E$99,2,0)&"'","")&IF(T61<>"",", range: '"&T61&"'","")&IF(V61<>"",", damage: '"&V61&"'","")&IF(X61<>"",", capacity: '"&X61&"'","")&IF(Y61<>"",", cost: '"&Y61&"'","")&", text: '"&SUBSTITUTE(SUBSTITUTE(AB61, CHAR(13), ""),CHAR(10),"\n")&IF(AC61<>"", "', textAdditional: '"&SUBSTITUTE(SUBSTITUTE(AC61, CHAR(13), ""),CHAR(10),"\n"), "")&"', textZh: '"&SUBSTITUTE(SUBSTITUTE(SUBSTITUTE(AD61, CHAR(13), ""),CHAR(10),"\n"),"'","\'")&"', textZhG1: '"&SUBSTITUTE(SUBSTITUTE(SUBSTITUTE(AF61, CHAR(13), ""),CHAR(10),"\n"),"'","\'")&IF(AE61<>"", "', textZhAdditional: '"&SUBSTITUTE(SUBSTITUTE(AE61, CHAR(13), ""),CHAR(10),"\n"), "")&"', textKo: '"&SUBSTITUTE(SUBSTITUTE(SUBSTITUTE(AG61, CHAR(13), ""),CHAR(10),"\n"),"'","\'")&"', textEn: '"&SUBSTITUTE(SUBSTITUTE(SUBSTITUTE(AH61, CHAR(13), ""),CHAR(10),"\n"),"'","\'")&"'"&IF(Z61="○",", sealable: true","")&IF(AA61="○",", removable: true","")&"}") | AO61: =IF($A61<>"", " /** 《"&$E61&"》 */ export const "&SUBSTITUTE(UPPER(IF(MID($A61, 3, 1)="-", RIGHT($A61,LEN($A61)-3), $A61)), "-", "_")&": TCardId = '"&$A61&"';", "") | AP61: =IF($A61<>"", " | '"&$A61&"'", "")
A62: 05-oboro-o-n-1 | B62: oboro | E62: 鋼糸 | F62: こうし | G62: 钢丝 | H62: 钢丝 | J62: 철사 | K62: Steel Strings | M62: 通常札 | R62: 攻撃 | T62: 3-4 | V62: 2/2 | AB62: 設置 | AD62: 设置 | AF62: 设置 | AG62: 설치 | AH62: Trap | AN62: =IF(A62="", "", IF(ROW()>=3, ", ", "")&"'"&A62&"': {megami: '"&B62&"'"&IF(C62<>"",", anotherID: '"&C62&"', replace: '"&D62&"'","")&", name: '"&SUBSTITUTE(E62,"'","\'")&"', nameEn: '"&SUBSTITUTE(K62,"'","\'")&"', nameZh: '"&SUBSTITUTE(G62,"'","\'")&"', nameZhG1: '"&SUBSTITUTE(H62,"'","\'")&"', nameKo: '"&SUBSTITUTE(J62,"'","\'")&"', ruby: '"&F62&"', rubyEn: '"&L62&IF(I62<>"", "', rubyZh: '"&I62, "")&"', baseType: '"&VLOOKUP(M62,マスタ!$A$1:$B$99,2,0)&"'"&IF(N62="○",", extra: true","")&IF(O62<>"",", extraFrom: '"&O62&"'","")&IF(P62<>"",", exchangableTo: '"&P62&"'","")&IF(Q62="○",", poison: true","")&IF(R62<>"", ", type: '"&VLOOKUP(R62,マスタ!$D$1:$E$99,2,0)&"'", "")&IF(S62<>"",", subType: '"&VLOOKUP(S62,マスタ!$D$1:$E$99,2,0)&"'","")&IF(T62<>"",", range: '"&T62&"'","")&IF(V62<>"",", damage: '"&V62&"'","")&IF(X62<>"",", capacity: '"&X62&"'","")&IF(Y62<>"",", cost: '"&Y62&"'","")&", text: '"&SUBSTITUTE(SUBSTITUTE(AB62, CHAR(13), ""),CHAR(10),"\n")&IF(AC62<>"", "', textAdditional: '"&SUBSTITUTE(SUBSTITUTE(AC62, CHAR(13), ""),CHAR(10),"\n"), "")&"', textZh: '"&SUBSTITUTE(SUBSTITUTE(SUBSTITUTE(AD62, CHAR(13), ""),CHAR(10),"\n"),"'","\'")&"', textZhG1: '"&SUBSTITUTE(SUBSTITUTE(SUBSTITUTE(AF62, CHAR(13), ""),CHAR(10),"\n"),"'","\'")&IF(AE62<>"", "', textZhAdditional: '"&SUBSTITUTE(SUBSTITUTE(AE62, CHAR(13), ""),CHAR(10),"\n"), "")&"', textKo: '"&SUBSTITUTE(SUBSTITUTE(SUBSTITUTE(AG62, CHAR(13), ""),CHAR(10),"\n"),"'","\'")&"', textEn: '"&SUBSTITUTE(SUBSTITUTE(SUBSTITUTE(AH62, CHAR(13), ""),CHAR(10),"\n"),"'","\'")&"'"&IF(Z62="○",", sealable: true","")&IF(AA62="○",", removable: true","")&"}") -> , '05-oboro-o-n-1': {megami: 'oboro', name: '鋼糸', nameEn: 'Steel Strings', nameZh: '钢丝', nameZhG1: '钢丝', nameKo: '철사', ruby: 'こうし', rubyEn: '', baseType: 'normal', type: 'attack', range: '3-4', damage: '2/2', text: '設置', textZh: '设置', textZhG1: '设置', textKo: '설치', textEn: 'Trap'} | AO62: =IF($A62<>"", " /** 《"&$E62&"》 */ export const "&SUBSTITUTE(UPPER(IF(MID($A62, 3, 1)="-", RIGHT($A62,LEN($A62)-3), $A62)), "-", "_")&": TCardId = '"&$A62&"';", "") -> /** 《鋼糸》 */ export const OBORO_O_N_1: TCardId = '05-oboro-o-n-1'; | AP62: =IF($A62<>"", " | '"&$A62&"'", "") -> | '05-oboro-o-n-1'
A63: 05-oboro-o-n-2 | B63: oboro | E63: 影菱 | F63: かげびし | G63: 影菱 | H63: 影菱 | J63: 그림자 마름 | K63: Caltrops | M63: 通常札 | R63: 攻撃 | T63: 2 | V63: 2/1 | AB63: 設置 対応不可 【攻撃後】このカードを伏せ札から使用したならば、相手の手札を見てその中から1枚を選び、それを伏せ札にする。 | AD63: 设置 不可被对应 【攻击后】若你从盖牌区使用此牌，则检视对手的手牌，盖伏其中1张。 | AF63: 设置 不可被对应 【攻击后】若你从盖牌区使用此牌，则检视对手的手牌，盖伏其中一张。 | AG63: 설치 대응불가 【공격후】이 카드를 덮임패에서 사용했다면, 상대의 손패를 보고 그 중 1장을 골라, 그것을 덮임패로 한다. | AH63: Trap No Reactions After Attack: If this card was played from your discard pile, look at your opponent's hand. Choose one of those cards and put it into their discard pile. | AN63: =IF(A63="", "", IF(ROW()>=3, ", ", "")&"'"&A63&"': {megami: '"&B63&"'"&IF(C63<>"",", anotherID: '"&C63&"', replace: '"&D63&"'","")&", name: '"&SUBSTITUTE(E63,"'","\'")&"', nameEn: '"&SUBSTITUTE(K63,"'","\'")&"', nameZh: '"&SUBSTITUTE(G63,"'","\'")&"', nameZhG1: '"&SUBSTITUTE(H63,"'","\'")&"', nameKo: '"&SUBSTITUTE(J63,"'","\'")&"', ruby: '"&F63&"', rubyEn: '"&L63&IF(I63<>"", "', rubyZh: '"&I63, "")&"', baseType: '"&VLOOKUP(M63,マスタ!$A$1:$B$99,2,0)&"'"&IF(N63="○",", extra: true","")&IF(O63<>"",", extraFrom: '"&O63&"'","")&IF(P63<>"",", exchangableTo: '"&P63&"'","")&IF(Q63="○",", poison: true","")&IF(R63<>"", ", type: '"&VLOOKUP(R63,マスタ!$D$1:$E$99,2,0)&"'", "")&IF(S63<>"",", subType: '"&VLOOKUP(S63,マスタ!$D$1:$E$99,2,0)&"'","")&IF(T63<>"",", range: '"&T63&"'","")&IF(V63<>"",", damage: '"&V63&"'","")&IF(X63<>"",", capacity: '"&X63&"'","")&IF(Y63<>"",", cost: '"&Y63&"'","")&", text: '"&SUBSTITUTE(SUBSTITUTE(AB63, CHAR(13), ""),CHAR(10),"\n")&IF(AC63<>"", "', textAdditional: '"&SUBSTITUTE(SUBSTITUTE(AC63, CHAR(13), ""),CHAR(10),"\n"), "")&"', textZh: '"&SUBSTITUTE(SUBSTITUTE(SUBSTITUTE(AD63, CHAR(13), ""),CHAR(10),"\n"),"'","\'")&"', textZhG1: '"&SUBSTITUTE(SUBSTITUTE(SUBSTITUTE(AF63, CHAR(13), ""),CHAR(10),"\n"),"'","\'")&IF(AE63<>"", "', textZhAdditional: '"&SUBSTITUTE(SUBSTITUTE(AE63, CHAR(13), ""),CHAR(10),"\n"), "")&"', textKo: '"&SUBSTITUTE(SUBSTITUTE(SUBSTITUTE(AG63, CHAR(13), ""),CHAR(10),"\n"),"'","\'")&"', textEn: '"&SUBSTITUTE(SUBSTITUTE(SUBSTITUTE(AH63, CHAR(13), ""),CHAR(10),"\n"),"'","\'")&"'"&IF(Z63="○",", sealable: true","")&IF(AA63="○",", removable: true","")&"}") -> , '05-oboro-o-n-2': {megami: 'oboro', name: '影菱', nameEn: 'Caltrops', nameZh: '影菱', nameZhG1: '影菱', nameKo: '그림자 마름', ruby: 'かげびし', rubyEn: '', baseType: 'normal', type: 'attack', range: '2', damage: '2/1', text: '設置 対応不可\n【攻撃後】このカードを伏せ札から使用したならば、相手の手札を見てその中から1枚を選び、それを伏せ札にする。', textZh: '设置 不可被对应 \n【攻击后】若你从盖牌区使用此牌，则检视对手的手牌，盖伏其中1张。', textZhG1: '设置 不可被对应 \n【攻击后】若你从盖牌区使用此牌，则检视对手的手牌，盖伏其中一张。', textKo: '설치 대응불가\n 【공격후】이 카드를 덮임패에서 사용했다면, 상대의 손패를 보고 그 중 1장을 골라, 그것을 덮임패로 한다.', textEn: 'Trap No Reactions\n\nAfter Attack: If this card was played from your discard pile, look at your opponent\'s hand. Choose one of those cards and put it into their discard pile.'} | AO63: =IF($A63<>"", " /** 《"&$E63&"》 */ export const "&SUBSTITUTE(UPPER(IF(MID($A63, 3, 1)="-", RIGHT($A63,LEN($A63)-3), $A63)), "-", "_")&": TCardId = '"&$A63&"';", "") -> /** 《影菱》 */ export const OBORO_O_N_2: TCardId = '05-oboro-o-n-2'; | AP63: =IF($A63<>"", " | '"&$A63&"'", "") -> | '05-oboro-o-n-2'
A64: 05-oboro-o-n-3 | B64: oboro | E64: 斬撃乱舞 | F64: ざんげきらんぶ | G64: 斩击乱舞 | H64: 斩击乱舞 | J64: 참격난무 | K64: Rush of Blades | M64: 通常札 | R64: 攻撃 | S64: 全力 | T64: 2-4 | V64: 3/2 | AB64: 【常時】相手がこのターン中にオーラへのダメージを受けているならば、この《攻撃》は+1/+1となる。 | AD64: 【常时】若本回合内敌装受到过伤害，则此《攻击》得+1/+1。 | AF64: 【常时】若本回合内敌装受到过伤害，则此《攻击》得+1/+1 | AG64: 【상시】상대가 이 턴 안에 오라로의 대미지를 받았다면, 이 《공격》은 +1/+1이 된다. | AH64: Forced: This attack gains +1/+1 if your opponent has taken damage to their Aura this turn. | AN64: =IF(A64="", "", IF(ROW()>=3, ", ", "")&"'"&A64&"': {megami: '"&B64&"'"&IF(C64<>"",", anotherID: '"&C64&"', replace: '"&D64&"'","")&", name: '"&SUBSTITUTE(E64,"'","\'")&"', nameEn: '"&SUBSTITUTE(K64,"'","\'")&"', nameZh: '"&SUBSTITUTE(G64,"'","\'")&"', nameZhG1: '"&SUBSTITUTE(H64,"'","\'")&"', nameKo: '"&SUBSTITUTE(J64,"'","\'")&"', ruby: '"&F64&"', rubyEn: '"&L64&IF(I64<>"", "', rubyZh: '"&I64, "")&"', baseType: '"&VLOOKUP(M64,マスタ!$A$1:$B$99,2,0)&"'"&IF(N64="○",", extra: true","")&IF(O64<>"",", extraFrom: '"&O64&"'","")&IF(P64<>"",", exchangableTo: '"&P64&"'","")&IF(Q64="○",", poison: true","")&IF(R64<>"", ", type: '"&VLOOKUP(R64,マスタ!$D$1:$E$99,2,0)&"'", "")&IF(S64<>"",", subType: '"&VLOOKUP(S64,マスタ!$D$1:$E$99,2,0)&"'","")&IF(T64<>"",", range: '"&T64&"'","")&IF(V64<>"",", damage: '"&V64&"'","")&IF(X64<>"",", capacity: '"&X64&"'","")&IF(Y64<>"",", cost: '"&Y64&"'","")&", text: '"&SUBSTITUTE(SUBSTITUTE(AB64, CHAR(13), ""),CHAR(10),"\n")&IF(AC64<>"", "', textAdditional: '"&SUBSTITUTE(SUBSTITUTE(AC64, CHAR(13), ""),CHAR(10),"\n"), "")&"', textZh: '"&SUBSTITUTE(SUBSTITUTE(SUBSTITUTE(AD64, CHAR(13), ""),CHAR(10),"\n"),"'","\'")&"', textZhG1: '"&SUBSTITUTE(SUBSTITUTE(SUBSTITUTE(AF64, CHAR(13), ""),CHAR(10),"\n"),"'","\'")&IF(AE64<>"", "', textZhAdditional: '"&SUBSTITUTE(SUBSTITUTE(AE64, CHAR(13), ""),CHAR(10),"\n"), "")&"', textKo: '"&SUBSTITUTE(SUBSTITUTE(SUBSTITUTE(AG64, CHAR(13), ""),CHAR(10),"\n"),"'","\'")&"', textEn: '"&SUBSTITUTE(SUBSTITUTE(SUBSTITUTE(AH64, CHAR(13), ""),CHAR(10),"\n"),"'","\'")&"'"&IF(Z64="○",", sealable: true","")&IF(AA64="○",", removable: true","")&"}") -> , '05-oboro-o-n-3': {megami: 'oboro', name: '斬撃乱舞', nameEn: 'Rush of Blades', nameZh: '斩击乱舞', nameZhG1: '斩击乱舞', nameKo: '참격난무', ruby: 'ざんげきらんぶ', rubyEn: '', baseType: 'normal', type: 'attack', subType: 'fullpower', range: '2-4', damage: '3/2', text: '【常時】相手がこのターン中にオーラへのダメージを受けているならば、この《攻撃》は+1/+1となる。', textZh: '【常时】若本回合内敌装受到过伤害，则此《攻击》得+1/+1。', textZhG1: '【常时】若本回合内敌装受到过伤害，则此《攻击》得+1/+1', textKo: '【상시】상대가 이 턴 안에 오라로의 대미지를 받았다면, 이 《공격》은 +1/+1이 된다.', textEn: 'Forced: This attack gains +1/+1 if your opponent has taken damage to their Aura this turn.'} | AO64: =IF($A64<>"", " /** 《"&$E64&"》 */ export const "&SUBSTITUTE(UPPER(IF(MID($A64, 3, 1)="-", RIGHT($A64,LEN($A64)-3), $A64)), "-", "_")&": TCardId = '"&$A64&"';", "") -> /** 《斬撃乱舞》 */ export const OBORO_O_N_3: TCardId = '05-oboro-o-n-3'; | AP64: =IF($A64<>"", " | '"&$A64&"'", "") -> | '05-oboro-o-n-3'
A65: 05-oboro-o-n-4 | B65: oboro | E65: 忍歩 | F65: にんぽ | G65: 忍步 | H65: 忍步 | J65: 닌자걸음 | K65: Ninpo-Walk | M65: 通常札 | R65: 行動 | AB65: 設置 間合⇔ダスト：1 このカードを伏せ札から使用したならば、伏せ札から設置を持つカードを1枚使用してもよい。 | AD65: 设置 距↔1↔虚 若你从盖牌区中使用此牌，则你可以从盖牌区中额外使用1张具设置关键字的牌。 | AF65: 设置 距 (1)⇔ 虚 若你从盖牌区中使用此牌，则你可以从盖牌区中额外使用一张具设置关键字的牌。 | AG65: 설치 간격⇔더스트：1 이 카드를 덮임패에서 사용했다면, 덮임패에서 설치를 갖는 카드를 1장 사용해도 좋다. | AH65: Trap Distance (1)⇔ Shadow If this card was played from your discard pile, you may play a card with Trap from your discard pile. | AN65: =IF(A65="", "", IF(ROW()>=3, ", ", "")&"'"&A65&"': {megami: '"&B65&"'"&IF(C65<>"",", anotherID: '"&C65&"', replace: '"&D65&"'","")&", name: '"&SUBSTITUTE(E65,"'","\'")&"', nameEn: '"&SUBSTITUTE(K65,"'","\'")&"', nameZh: '"&SUBSTITUTE(G65,"'","\'")&"', nameZhG1: '"&SUBSTITUTE(H65,"'","\'")&"', nameKo: '"&SUBSTITUTE(J65,"'","\'")&"', ruby: '"&F65&"', rubyEn: '"&L65&IF(I65<>"", "', rubyZh: '"&I65, "")&"', baseType: '"&VLOOKUP(M65,マスタ!$A$1:$B$99,2,0)&"'"&IF(N65="○",", extra: true","")&IF(O65<>"",", extraFrom: '"&O65&"'","")&IF(P65<>"",", exchangableTo: '"&P65&"'","")&IF(Q65="○",", poison: true","")&IF(R65<>"", ", type: '"&VLOOKUP(R65,マスタ!$D$1:$E$99,2,0)&"'", "")&IF(S65<>"",", subType: '"&VLOOKUP(S65,マスタ!$D$1:$E$99,2,0)&"'","")&IF(T65<>"",", range: '"&T65&"'","")&IF(V65<>"",", damage: '"&V65&"'","")&IF(X65<>"",", capacity: '"&X65&"'","")&IF(Y65<>"",", cost: '"&Y65&"'","")&", text: '"&SUBSTITUTE(SUBSTITUTE(AB65, CHAR(13), ""),CHAR(10),"\n")&IF(AC65<>"", "', textAdditional: '"&SUBSTITUTE(SUBSTITUTE(AC65, CHAR(13), ""),CHAR(10),"\n"), "")&"', textZh: '"&SUBSTITUTE(SUBSTITUTE(SUBSTITUTE(AD65, CHAR(13), ""),CHAR(10),"\n"),"'","\'")&"', textZhG1: '"&SUBSTITUTE(SUBSTITUTE(SUBSTITUTE(AF65, CHAR(13), ""),CHAR(10),"\n"),"'","\'")&IF(AE65<>"", "', textZhAdditional: '"&SUBSTITUTE(SUBSTITUTE(AE65, CHAR(13), ""),CHAR(10),"\n"), "")&"', textKo: '"&SUBSTITUTE(SUBSTITUTE(SUBSTITUTE(AG65, CHAR(13), ""),CHAR(10),"\n"),"'","\'")&"', textEn: '"&SUBSTITUTE(SUBSTITUTE(SUBSTITUTE(AH65, CHAR(13), ""),CHAR(10),"\n"),"'","\'")&"'"&IF(Z65="○",", sealable: true","")&IF(AA65="○",", removable: true","")&"}") -> , '05-oboro-o-n-4': {megami: 'oboro', name: '忍歩', nameEn: 'Ninpo-Walk', nameZh: '忍步', nameZhG1: '忍步', nameKo: '닌자걸음', ruby: 'にんぽ', rubyEn: '', baseType: 'normal', type: 'action', text: '設置 \n間合⇔ダスト：1 \nこのカードを伏せ札から使用したならば、伏せ札から設置を持つカードを1枚使用してもよい。', textZh: '设置\n距↔1↔虚\n若你从盖牌区中使用此牌，则你可以从盖牌区中额外使用1张具设置关键字的牌。', textZhG1: '设置\n距 (1)⇔ 虚\n若你从盖牌区中使用此牌，则你可以从盖牌区中额外使用一张具设置关键字的牌。', textKo: '설치 \n 간격⇔더스트：1 \n 이 카드를 덮임패에서 사용했다면, 덮임패에서 설치를 갖는 카드를 1장 사용해도 좋다.', textEn: 'Trap\n\nDistance (1)⇔ Shadow\n\nIf this card was played from your discard pile, you may play a card with Trap from your discard pile.'} | AO65: =IF($A65<>"", " /** 《"&$E65&"》 */ export const "&SUBSTITUTE(UPPER(IF(MID($A65, 3, 1)="-", RIGHT($A65,LEN($A65)-3), $A65)), "-", "_")&": TCardId = '"&$A65&"';", "") -> /** 《忍歩》 */ export const OBORO_O_N_4: TCardId = '05-oboro-o-n-4'; | AP65: =IF($A65<>"", " | '"&$A65&"'", "") -> | '05-oboro-o-n-4'
A66: 05-oboro-o-n-5 | B66: oboro | E66: 誘導 | F66: ゆうどう | G66: 诱导 | H66: 诱导 | J66: 유도 | K66: Induce | M66: 通常札 | R66: 行動 | S66: 対応 | AB66: 設置 以下から１つを選ぶ。 ・間合→相オーラ：1 ・相オーラ→相フレア：1 | AD66: 设置 选择一项： ●距→1→敌装 ●敌装→1→敌气 | AF66: 设置 选择一项： 1.距（1）→敌装 2.敌装（1）→敌气 | AG66: 설치 이하에서 하나를 고른다. ・간격→상대 오라：1 ・상대 오라→상대 플레어：1 | AH66: Trap Choose one: ・Distance (1)→ Opponent's Aura ・Opponent's Aura (1)→ Opponent's Flare | AN66: =IF(A66="", "", IF(ROW()>=3, ", ", "")&"'"&A66&"': {megami: '"&B66&"'"&IF(C66<>"",", anotherID: '"&C66&"', replace: '"&D66&"'","")&", name: '"&SUBSTITUTE(E66,"'","\'")&"', nameEn: '"&SUBSTITUTE(K66,"'","\'")&"', nameZh: '"&SUBSTITUTE(G66,"'","\'")&"', nameZhG1: '"&SUBSTITUTE(H66,"'","\'")&"', nameKo: '"&SUBSTITUTE(J66,"'","\'")&"', ruby: '"&F66&"', rubyEn: '"&L66&IF(I66<>"", "', rubyZh: '"&I66, "")&"', baseType: '"&VLOOKUP(M66,マスタ!$A$1:$B$99,2,0)&"'"&IF(N66="○",", extra: true","")&IF(O66<>"",", extraFrom: '"&O66&"'","")&IF(P66<>"",", exchangableTo: '"&P66&"'","")&IF(Q66="○",", poison: true","")&IF(R66<>"", ", type: '"&VLOOKUP(R66,マスタ!$D$1:$E$99,2,0)&"'", "")&IF(S66<>"",", subType: '"&VLOOKUP(S66,マスタ!$D$1:$E$99,2,0)&"'","")&IF(T66<>"",", range: '"&T66&"'","")&IF(V66<>"",", damage: '"&V66&"'","")&IF(X66<>"",", capacity: '"&X66&"'","")&IF(Y66<>"",", cost: '"&Y66&"'","")&", text: '"&SUBSTITUTE(SUBSTITUTE(AB66, CHAR(13), ""),CHAR(10),"\n")&IF(AC66<>"", "', textAdditional: '"&SUBSTITUTE(SUBSTITUTE(AC66, CHAR(13), ""),CHAR(10),"\n"), "")&"', textZh: '"&SUBSTITUTE(SUBSTITUTE(SUBSTITUTE(AD66, CHAR(13), ""),CHAR(10),"\n"),"'","\'")&"', textZhG1: '"&SUBSTITUTE(SUBSTITUTE(SUBSTITUTE(AF66, CHAR(13), ""),CHAR(10),"\n"),"'","\'")&IF(AE66<>"", "', textZhAdditional: '"&SUBSTITUTE(SUBSTITUTE(AE66, CHAR(13), ""),CHAR(10),"\n"), "")&"', textKo: '"&SUBSTITUTE(SUBSTITUTE(SUBSTITUTE(AG66, CHAR(13), ""),CHAR(10),"\n"),"'","\'")&"', textEn: '"&SUBSTITUTE(SUBSTITUTE(SUBSTITUTE(AH66, CHAR(13), ""),CHAR(10),"\n"),"'","\'")&"'"&IF(Z66="○",", sealable: true","")&IF(AA66="○",", removable: true","")&"}") -> , '05-oboro-o-n-5': {megami: 'oboro', name: '誘導', nameEn: 'Induce', nameZh: '诱导', nameZhG1: '诱导', nameKo: '유도', ruby: 'ゆうどう', rubyEn: '', baseType: 'normal', type: 'action', subType: 'reaction', text: '設置\n以下から１つを選ぶ。\n・間合→相オーラ：1\n・相オーラ→相フレア：1', textZh: '设置 \n选择一项：\n●距→1→敌装\n●敌装→1→敌气', textZhG1: '设置 \n选择一项：\n1.距（1）→敌装\n2.敌装（1）→敌气', textKo: '설치\n 이하에서 하나를 고른다.\n ・간격→상대 오라：1\n ・상대 오라→상대 플레어：1', textEn: 'Trap\n\nChoose one:\n・Distance (1)→ Opponent\'s Aura\n・Opponent\'s Aura (1)→ Opponent\'s Flare'} | AO66: =IF($A66<>"", " /** 《"&$E66&"》 */ export const "&SUBSTITUTE(UPPER(IF(MID($A66, 3, 1)="-", RIGHT($A66,LEN($A66)-3), $A66)), "-", "_")&": TCardId = '"&$A66&"';", "") -> /** 《誘導》 */ export const OBORO_O_N_5: TCardId = '05-oboro-o-n-5'; | AP66: =IF($A66<>"", " | '"&$A66&"'", "") -> | '05-oboro-o-n-5'
A67: 05-oboro-o-n-6 | B67: oboro | E67: 分身の術 | F67: ぶんしんのじゅつ | G67: 分身术 | H67: 分身术 | J67: 분신술 | K67: Shadow Cloning | M67: 通常札 | R67: 行動 | S67: 全力 | AB67: 伏せ札から《全力》でないカードを1枚選び、そのカードを使用する。その後、そのカードが捨て札にあるならば捨て札からもう1回使用する。《攻撃》カードが使用されたならばそれらの《攻撃》は対応不可を得る（2回ともに対応不可を得る）。 | AD67: 从盖牌区中选择1张非《全力》的牌使用。若以此法使用的牌结算完毕进入弃牌区，则从弃牌区中再次使用之。若所选择的牌是《攻击》牌，则此《攻击》得不可被对应（2次都获得）。 | AF67: 从盖牌区中选择一张非《全力》的牌使用。当所选择的牌结算完毕进入弃牌区时，从弃牌区中再次使用之（这个效果仅结算一次）。若所选择的牌是《攻击》牌，则此《攻击》得不可被对应（2次都获得）。 | AG67: 덮임패에서 《전력》이 아닌 카드를 1장 골라, 그 카드를 사용한다. 그 후, 그 카드가 버림패에 있다면 버림패에서 한번 더 사용한다. 《공격》카드가 사용됐다면 그 《공격》들은 대응불가를 얻는다（2번 모두 대응불가를 얻는다）. | AH67: Reveal a non-Throughout card in your discard pile and play it. Then play it again if it is in your played pile. If the played card is an Attack card, it gains No Reactions (both times). | AN67: =IF(A67="", "", IF(ROW()>=3, ", ", "")&"'"&A67&"': {megami: '"&B67&"'"&IF(C67<>"",", anotherID: '"&C67&"', replace: '"&D67&"'","")&", name: '"&SUBSTITUTE(E67,"'","\'")&"', nameEn: '"&SUBSTITUTE(K67,"'","\'")&"', nameZh: '"&SUBSTITUTE(G67,"'","\'")&"', nameZhG1: '"&SUBSTITUTE(H67,"'","\'")&"', nameKo: '"&SUBSTITUTE(J67,"'","\'")&"', ruby: '"&F67&"', rubyEn: '"&L67&IF(I67<>"", "', rubyZh: '"&I67, "")&"', baseType: '"&VLOOKUP(M67,マスタ!$A$1:$B$99,2,0)&"'"&IF(N67="○",", extra: true","")&IF(O67<>"",", extraFrom: '"&O67&"'","")&IF(P67<>"",", exchangableTo: '"&P67&"'","")&IF(Q67="○",", poison: true","")&IF(R67<>"", ", type: '"&VLOOKUP(R67,マスタ!$D$1:$E$99,2,0)&"'", "")&IF(S67<>"",", subType: '"&VLOOKUP(S67,マスタ!$D$1:$E$99,2,0)&"'","")&IF(T67<>"",", range: '"&T67&"'","")&IF(V67<>"",", damage: '"&V67&"'","")&IF(X67<>"",", capacity: '"&X67&"'","")&IF(Y67<>"",", cost: '"&Y67&"'","")&", text: '"&SUBSTITUTE(SUBSTITUTE(AB67, CHAR(13), ""),CHAR(10),"\n")&IF(AC67<>"", "', textAdditional: '"&SUBSTITUTE(SUBSTITUTE(AC67, CHAR(13), ""),CHAR(10),"\n"), "")&"', textZh: '"&SUBSTITUTE(SUBSTITUTE(SUBSTITUTE(AD67, CHAR(13), ""),CHAR(10),"\n"),"'","\'")&"', textZhG1: '"&SUBSTITUTE(SUBSTITUTE(SUBSTITUTE(AF67, CHAR(13), ""),CHAR(10),"\n"),"'","\'")&IF(AE67<>"", "', textZhAdditional: '"&SUBSTITUTE(SUBSTITUTE(AE67, CHAR(13), ""),CHAR(10),"\n"), "")&"', textKo: '"&SUBSTITUTE(SUBSTITUTE(SUBSTITUTE(AG67, CHAR(13), ""),CHAR(10),"\n"),"'","\'")&"', textEn: '"&SUBSTITUTE(SUBSTITUTE(SUBSTITUTE(AH67, CHAR(13), ""),CHAR(10),"\n"),"'","\'")&"'"&IF(Z67="○",", sealable: true","")&IF(AA67="○",", removable: true","")&"}") -> , '05-oboro-o-n-6': {megami: 'oboro', name: '分身の術', nameEn: 'Shadow Cloning', nameZh: '分身术', nameZhG1: '分身术', nameKo: '분신술', ruby: 'ぶんしんのじゅつ', rubyEn: '', baseType: 'normal', type: 'action', subType: 'fullpower', text: '伏せ札から《全力》でないカードを1枚選び、そのカードを使用する。その後、そのカードが捨て札にあるならば捨て札からもう1回使用する。《攻撃》カードが使用されたならばそれらの《攻撃》は対応不可を得る（2回ともに対応不可を得る）。', textZh: '从盖牌区中选择1张非《全力》的牌使用。若以此法使用的牌结算完毕进入弃牌区，则从弃牌区中再次使用之。若所选择的牌是《攻击》牌，则此《攻击》得不可被对应（2次都获得）。', textZhG1: '从盖牌区中选择一张非《全力》的牌使用。当所选择的牌结算完毕进入弃牌区时，从弃牌区中再次使用之（这个效果仅结算一次）。若所选择的牌是《攻击》牌，则此《攻击》得不可被对应（2次都获得）。', textKo: '덮임패에서 《전력》이 아닌 카드를 1장 골라, 그 카드를 사용한다. 그 후, 그 카드가 버림패에 있다면 버림패에서 한번 더 사용한다. 《공격》카드가 사용됐다면 그 《공격》들은 대응불가를 얻는다（2번 모두 대응불가를 얻는다）.', textEn: 'Reveal a non-Throughout card in your discard pile and play it. Then play it again if it is in your played pile. If the played card is an Attack card, it gains No Reactions (both times).'} | AO67: =IF($A67<>"", " /** 《"&$E67&"》 */ export const "&SUBSTITUTE(UPPER(IF(MID($A67, 3, 1)="-", RIGHT($A67,LEN($A67)-3), $A67)), "-", "_")&": TCardId = '"&$A67&"';", "") -> /** 《分身の術》 */ export const OBORO_O_N_6: TCardId = '05-oboro-o-n-6'; | AP67: =IF($A67<>"", " | '"&$A67&"'", "") -> | '05-oboro-o-n-6'
A68: 05-oboro-o-n-7 | B68: oboro | E68: 生体活性 | F68: せいたいかっせい | G68: 生物活性 | H68: 生物活性 | J68: 생체활성 | K68: Revitalize | M68: 通常札 | R68: 付与 | X68: 4 | AB68: 隙 設置 【破棄時】あなたの使用済の切札を1枚選び、それを未使用に戻す。 | AD68: 破绽 设置 【破弃时】将你的1张处于已使用状态的王牌变为未使用状态。 | AF68: 破绽 设置 【破弃时】将你的一张面朝上的王牌翻面。 | AG68: 빈틈 설치 【파기시】당신의 사용완료 비장패를 1장 골라, 그것을 미사용으로 되돌린다. | AH68: Unguarded Trap Disenchant: Choose one of your Devoted Special cards and turn it face-down. | AN68: =IF(A68="", "", IF(ROW()>=3, ", ", "")&"'"&A68&"': {megami: '"&B68&"'"&IF(C68<>"",", anotherID: '"&C68&"', replace: '"&D68&"'","")&", name: '"&SUBSTITUTE(E68,"'","\'")&"', nameEn: '"&SUBSTITUTE(K68,"'","\'")&"', nameZh: '"&SUBSTITUTE(G68,"'","\'")&"', nameZhG1: '"&SUBSTITUTE(H68,"'","\'")&"', nameKo: '"&SUBSTITUTE(J68,"'","\'")&"', ruby: '"&F68&"', rubyEn: '"&L68&IF(I68<>"", "', rubyZh: '"&I68, "")&"', baseType: '"&VLOOKUP(M68,マスタ!$A$1:$B$99,2,0)&"'"&IF(N68="○",", extra: true","")&IF(O68<>"",", extraFrom: '"&O68&"'","")&IF(P68<>"",", exchangableTo: '"&P68&"'","")&IF(Q68="○",", poison: true","")&IF(R68<>"", ", type: '"&VLOOKUP(R68,マスタ!$D$1:$E$99,2,0)&"'", "")&IF(S68<>"",", subType: '"&VLOOKUP(S68,マスタ!$D$1:$E$99,2,0)&"'","")&IF(T68<>"",", range: '"&T68&"'","")&IF(V68<>"",", damage: '"&V68&"'","")&IF(X68<>"",", capacity: '"&X68&"'","")&IF(Y68<>"",", cost: '"&Y68&"'","")&", text: '"&SUBSTITUTE(SUBSTITUTE(AB68, CHAR(13), ""),CHAR(10),"\n")&IF(AC68<>"", "', textAdditional: '"&SUBSTITUTE(SUBSTITUTE(AC68, CHAR(13), ""),CHAR(10),"\n"), "")&"', textZh: '"&SUBSTITUTE(SUBSTITUTE(SUBSTITUTE(AD68, CHAR(13), ""),CHAR(10),"\n"),"'","\'")&"', textZhG1: '"&SUBSTITUTE(SUBSTITUTE(SUBSTITUTE(AF68, CHAR(13), ""),CHAR(10),"\n"),"'","\'")&IF(AE68<>"", "', textZhAdditional: '"&SUBSTITUTE(SUBSTITUTE(AE68, CHAR(13), ""),CHAR(10),"\n"), "")&"', textKo: '"&SUBSTITUTE(SUBSTITUTE(SUBSTITUTE(AG68, CHAR(13), ""),CHAR(10),"\n"),"'","\'")&"', textEn: '"&SUBSTITUTE(SUBSTITUTE(SUBSTITUTE(AH68, CHAR(13), ""),CHAR(10),"\n"),"'","\'")&"'"&IF(Z68="○",", sealable: true","")&IF(AA68="○",", removable: true","")&"}") -> , '05-oboro-o-n-7': {megami: 'oboro', name: '生体活性', nameEn: 'Revitalize', nameZh: '生物活性', nameZhG1: '生物活性', nameKo: '생체활성', ruby: 'せいたいかっせい', rubyEn: '', baseType: 'normal', type: 'enhance', capacity: '4', text: '隙 設置 \n【破棄時】あなたの使用済の切札を1枚選び、それを未使用に戻す。', textZh: '破绽 设置 \n【破弃时】将你的1张处于已使用状态的王牌变为未使用状态。', textZhG1: '破绽 设置 \n【破弃时】将你的一张面朝上的王牌翻面。', textKo: '빈틈 설치 \n 【파기시】당신의 사용완료 비장패를 1장 골라, 그것을 미사용으로 되돌린다.', textEn: 'Unguarded Trap\n\nDisenchant: Choose one of your Devoted Special cards and turn it face-down.'} | AO68: =IF($A68<>"", " /** 《"&$E68&"》 */ export const "&SUBSTITUTE(UPPER(IF(MID($A68, 3, 1)="-", RIGHT($A68,LEN($A68)-3), $A68)), "-", "_")&": TCardId = '"&$A68&"';", "") -> /** 《生体活性》 */ export const OBORO_O_N_7: TCardId = '05-oboro-o-n-7'; | AP68: =IF($A68<>"", " | '"&$A68&"'", "") -> | '05-oboro-o-n-7'
A69: 05-oboro-o-s-1 | B69: oboro | E69: 熊介 | F69: くますけ | G69: 熊介 | H69: 熊介 | J69: 쿠마스케 | K69: Kuma-Suke | M69: 切札 | R69: 攻撃 | S69: 全力 | T69: 3-4 | V69: 2/2 | Y69: 4 | AB69: 【攻撃後】攻撃『適正距離3-4、2/2』をX回行う。Xはあなたの伏せ札の枚数に等しい。 | AD69: 【攻击后】进行X次“攻击距离3-4、伤害2/2”的攻击，X等于你盖牌区中的牌张数。 | AF69: 【攻击后】进行X次“攻击距离3-4 伤害2/2”的攻击。X等于你盖牌区中的牌张数。 | AG69: 【공격후】공격『적정거리3-4、2/2』을 X번 행한다. X는 당신의 덮임패 장수와 같다. | AH69: After Attack: You attack with "Range: 3-4, Damage: 2/2" X times, where X is the number of cards in your discard pile. | AN69: =IF(A69="", "", IF(ROW()>=3, ", ", "")&"'"&A69&"': {megami: '"&B69&"'"&IF(C69<>"",", anotherID: '"&C69&"', replace: '"&D69&"'","")&", name: '"&SUBSTITUTE(E69,"'","\'")&"', nameEn: '"&SUBSTITUTE(K69,"'","\'")&"', nameZh: '"&SUBSTITUTE(G69,"'","\'")&"', nameZhG1: '"&SUBSTITUTE(H69,"'","\'")&"', nameKo: '"&SUBSTITUTE(J69,"'","\'")&"', ruby: '"&F69&"', rubyEn: '"&L69&IF(I69<>"", "', rubyZh: '"&I69, "")&"', baseType: '"&VLOOKUP(M69,マスタ!$A$1:$B$99,2,0)&"'"&IF(N69="○",", extra: true","")&IF(O69<>"",", extraFrom: '"&O69&"'","")&IF(P69<>"",", exchangableTo: '"&P69&"'","")&IF(Q69="○",", poison: true","")&IF(R69<>"", ", type: '"&VLOOKUP(R69,マスタ!$D$1:$E$99,2,0)&"'", "")&IF(S69<>"",", subType: '"&VLOOKUP(S69,マスタ!$D$1:$E$99,2,0)&"'","")&IF(T69<>"",", range: '"&T69&"'","")&IF(V69<>"",", damage: '"&V69&"'","")&IF(X69<>"",", capacity: '"&X69&"'","")&IF(Y69<>"",", cost: '"&Y69&"'","")&", text: '"&SUBSTITUTE(SUBSTITUTE(AB69, CHAR(13), ""),CHAR(10),"\n")&IF(AC69<>"", "', textAdditional: '"&SUBSTITUTE(SUBSTITUTE(AC69, CHAR(13), ""),CHAR(10),"\n"), "")&"', textZh: '"&SUBSTITUTE(SUBSTITUTE(SUBSTITUTE(AD69, CHAR(13), ""),CHAR(10),"\n"),"'","\'")&"', textZhG1: '"&SUBSTITUTE(SUBSTITUTE(SUBSTITUTE(AF69, CHAR(13), ""),CHAR(10),"\n"),"'","\'")&IF(AE69<>"", "', textZhAdditional: '"&SUBSTITUTE(SUBSTITUTE(AE69, CHAR(13), ""),CHAR(10),"\n"), "")&"', textKo: '"&SUBSTITUTE(SUBSTITUTE(SUBSTITUTE(AG69, CHAR(13), ""),CHAR(10),"\n"),"'","\'")&"', textEn: '"&SUBSTITUTE(SUBSTITUTE(SUBSTITUTE(AH69, CHAR(13), ""),CHAR(10),"\n"),"'","\'")&"'"&IF(Z69="○",", sealable: true","")&IF(AA69="○",", removable: true","")&"}") -> , '05-oboro-o-s-1': {megami: 'oboro', name: '熊介', nameEn: 'Kuma-Suke', nameZh: '熊介', nameZhG1: '熊介', nameKo: '쿠마스케', ruby: 'くますけ', rubyEn: '', baseType: 'special', type: 'attack', subType: 'fullpower', range: '3-4', damage: '2/2', cost: '4', text: '【攻撃後】攻撃『適正距離3-4、2/2』をX回行う。Xはあなたの伏せ札の枚数に等しい。', textZh: '【攻击后】进行X次“攻击距离3-4、伤害2/2”的攻击，X等于你盖牌区中的牌张数。', textZhG1: '【攻击后】进行X次“攻击距离3-4 伤害2/2”的攻击。X等于你盖牌区中的牌张数。 ', textKo: '【공격후】공격『적정거리3-4、2/2』을 X번 행한다. X는 당신의 덮임패 장수와 같다.', textEn: 'After Attack: You attack with "Range: 3-4, Damage: 2/2" X times, where X is the number of cards in your discard pile.'} | AO69: =IF($A69<>"", " /** 《"&$E69&"》 */ export const "&SUBSTITUTE(UPPER(IF(MID($A69, 3, 1)="-", RIGHT($A69,LEN($A69)-3), $A69)), "-", "_")&": TCardId = '"&$A69&"';", "") -> /** 《熊介》 */ export const OBORO_O_S_1: TCardId = '05-oboro-o-s-1'; | AP69: =IF($A69<>"", " | '"&$A69&"'", "") -> | '05-oboro-o-s-1'
A70: 05-oboro-o-s-2 | B70: oboro | E70: 鳶影 | F70: とびかげ | G70: 鸢影 | H70: 鸢影 | J70: 토비카게 | K70: Tobi-Kage | M70: 切札 | R70: 行動 | S70: 対応 | Y70: 3 | AB70: 伏せ札から《全力》でないカードを1枚選び、そのカードを使用してもよい。この際、このカードが対応している《攻撃》があるならば、使用されたカードはそれに対応しているものと扱う。 | AD70: 从盖牌区中选择1张非《全力》的牌使用。若此牌对应了一个《攻击》，则视为所选择的牌也对应了那个《攻击》。 | AF70: 从盖牌区中选择一张非《全力》的牌使用。若此牌对应了一个《攻击》，则视为所选择的牌代替此牌对应了那个《攻击》。 | AG70: 덮임패에서 《전력》이 아닌 카드를 1장 골라, 그 카드를 사용해도 좋다. 이 때, 이 카드가 대응하는 《공격》이 있다면, 사용된 카드는 그것에 대응하고 있는것으로 취급한다. | AH70: Reveal a non-Throughout card in your discard pile and play it. If this card was played as a Reaction to an attack, treat that card as if it were played as a Reaction to that attack. | AN70: =IF(A70="", "", IF(ROW()>=3, ", ", "")&"'"&A70&"': {megami: '"&B70&"'"&IF(C70<>"",", anotherID: '"&C70&"', replace: '"&D70&"'","")&", name: '"&SUBSTITUTE(E70,"'","\'")&"', nameEn: '"&SUBSTITUTE(K70,"'","\'")&"', nameZh: '"&SUBSTITUTE(G70,"'","\'")&"', nameZhG1: '"&SUBSTITUTE(H70,"'","\'")&"', nameKo: '"&SUBSTITUTE(J70,"'","\'")&"', ruby: '"&F70&"', rubyEn: '"&L70&IF(I70<>"", "', rubyZh: '"&I70, "")&"', baseType: '"&VLOOKUP(M70,マスタ!$A$1:$B$99,2,0)&"'"&IF(N70="○",", extra: true","")&IF(O70<>"",", extraFrom: '"&O70&"'","")&IF(P70<>"",", exchangableTo: '"&P70&"'","")&IF(Q70="○",", poison: true","")&IF(R70<>"", ", type: '"&VLOOKUP(R70,マスタ!$D$1:$E$99,2,0)&"'", "")&IF(S70<>"",", subType: '"&VLOOKUP(S70,マスタ!$D$1:$E$99,2,0)&"'","")&IF(T70<>"",", range: '"&T70&"'","")&IF(V70<>"",", damage: '"&V70&"'","")&IF(X70<>"",", capacity: '"&X70&"'","")&IF(Y70<>"",", cost: '"&Y70&"'","")&", text: '"&SUBSTITUTE(SUBSTITUTE(AB70, CHAR(13), ""),CHAR(10),"\n")&IF(AC70<>"", "', textAdditional: '"&SUBSTITUTE(SUBSTITUTE(AC70, CHAR(13), ""),CHAR(10),"\n"), "")&"', textZh: '"&SUBSTITUTE(SUBSTITUTE(SUBSTITUTE(AD70, CHAR(13), ""),CHAR(10),"\n"),"'","\'")&"', textZhG1: '"&SUBSTITUTE(SUBSTITUTE(SUBSTITUTE(AF70, CHAR(13), ""),CHAR(10),"\n"),"'","\'")&IF(AE70<>"", "', textZhAdditional: '"&SUBSTITUTE(SUBSTITUTE(AE70, CHAR(13), ""),CHAR(10),"\n"), "")&"', textKo: '"&SUBSTITUTE(SUBSTITUTE(SUBSTITUTE(AG70, CHAR(13), ""),CHAR(10),"\n"),"'","\'")&"', textEn: '"&SUBSTITUTE(SUBSTITUTE(SUBSTITUTE(AH70, CHAR(13), ""),CHAR(10),"\n"),"'","\'")&"'"&IF(Z70="○",", sealable: true","")&IF(AA70="○",", removable: true","")&"}") -> , '05-oboro-o-s-2': {megami: 'oboro', name: '鳶影', nameEn: 'Tobi-Kage', nameZh: '鸢影', nameZhG1: '鸢影', nameKo: '토비카게', ruby: 'とびかげ', rubyEn: '', baseType: 'special', type: 'action', subType: 'reaction', cost: '3', text: '伏せ札から《全力》でないカードを1枚選び、そのカードを使用してもよい。この際、このカードが対応している《攻撃》があるならば、使用されたカードはそれに対応しているものと扱う。', textZh: '从盖牌区中选择1张非《全力》的牌使用。若此牌对应了一个《攻击》，则视为所选择的牌也对应了那个《攻击》。', textZhG1: '从盖牌区中选择一张非《全力》的牌使用。若此牌对应了一个《攻击》，则视为所选择的牌代替此牌对应了那个《攻击》。', textKo: '덮임패에서 《전력》이 아닌 카드를 1장 골라, 그 카드를 사용해도 좋다. 이 때, 이 카드가 대응하는 《공격》이 있다면, 사용된 카드는 그것에 대응하고 있는것으로 취급한다.', textEn: 'Reveal a non-Throughout card in your discard pile and play it. If this card was played as a Reaction to an attack, treat that card as if it were played as a Reaction to that attack.'} | AO70: =IF($A70<>"", " /** 《"&$E70&"》 */ export const "&SUBSTITUTE(UPPER(IF(MID($A70, 3, 1)="-", RIGHT($A70,LEN($A70)-3), $A70)), "-", "_")&": TCardId = '"&$A70&"';", "") -> /** 《鳶影》 */ export const OBORO_O_S_2: TCardId = '05-oboro-o-s-2'; | AP70: =IF($A70<>"", " | '"&$A70&"'", "") -> | '05-oboro-o-s-2'
